Workbook

Sheet Inputs
A1: UK Property Flip Deal Calculator
A2: Inputs are blue (editable). Results are calculated. Tax rates are based on official guidance—always verify for your transaction.
A4: DEAL BASICS
A5: Purchase price | B5: 250000
A6: Expected sale price | B6: 320000
A7: Location (tax system) | B7: England & N. Ireland
A8: Buyer type | B8: Additional / Investor
A9: Non‑UK resident surcharge (Eng/N.I. only) | B9: No
A10: Project duration (months) | B10: 6
A12: ACQUISITION COSTS
A13: Transaction tax (auto) → | B13: =IF($D$13<>"",$D$13,IF($B$7="England & N. Ireland",(IF($B$8="First-time buyer",(IF($B$5<=500000,MAX(0,$B$5-300000)*0.05,(MAX(0,MIN($B$5,250000)-125000)*0.02+MAX(0,MIN($B$5,925000)-250000)*0.05+MAX(0,MIN($B$5,1500000)-925000)*0.1+MAX(0,$B$5-1500000)*0.12))),(MAX(0,MIN($B$5,250000)-125000)*0.02+MAX(0,MIN($B$5,925000)-250000)*0.05+MAX(0,MIN($B$5,1500000)-925000)*0.1+MAX(0,$B$5-1500000)*0.12)+IF($B$8="Additional / Investor",0.05*$B$5,0)+IF($B$9="Yes",0.02*$B$5,0))),IF($B$7="Scotland",((MAX(0,MIN($B$5,250000)-145000)*0.02+MAX(0,MIN($B$5,325000)-250000)*0.05+MAX(0,MIN($B$5,750000)-325000)*0.1+MAX(0,$B$5-750000)*0.12)-IF($B$8="First-time buyer",(IF($B$5>145000,MIN(600,0.02*(MIN($B$5,175000)-145000)),0)),0)+IF($B$8="Additional / Investor",0.08*$B$5,0)),IF($B$7="Wales",(IF($B$8="Additional / Investor",(MIN($B$5,180000)*0.05+MAX(0,MIN($B$5,250000)-180000)*0.085+MAX(0,MIN($B$5,400000)-250000)*0.1+MAX(0,MIN($B$5,750000)-400000)*0.125+MAX(0,MIN($B$5,1500000)-750000)*0.15+MAX(0,$B$5-1500000)*0.17),(MAX(0,MIN($B$5,400000)-225000)*0.06+MAX(0,MIN($B$5,750000)-400000)*0.075+MAX(0,MIN($B$5,1500000)-750000)*0.1+MAX(0,$B$5-1500000)*0.12))),0)))) -> 15000 | C13: Manual override (leave blank to use auto)
A14: Purchase legal fees | B14: 1500
A15: Survey / valuation | B15: 500
A16: Broker / sourcing fee | B16: 0
A17: Other acquisition costs | B17: 0
A19: FINANCE (OPTIONAL / BRIDGING STYLE)
A20: Loan-to-value (LTV) % | B20: 0.75
A21: Annual interest rate % | B21: 0.12
A22: Arrangement fee % (of total loan) | B22: 0.02
A23: Exit fee % (of total loan) | B23: 0.01
A24: Refurb financed? | B24: No
A25: Refurb loan % of total refurb (if financed) | B25: 0
A26: Average refurb drawdown factor (0–1) | B26: 0.5
A28: REFURB / VALUE-ADD
A29: Refurb budget | B29: 25000
A30: Contingency % | B30: 0.1
A31: Furniture / staging (capex) | B31: 0
A32: Professional fees (architect, etc.) | B32: 0
A33: Other works | B33: 0
A35: HOLDING COSTS (MONTHLY)
A36: Council tax + utilities + insurance / month | B36: 350
A37: Other holding costs / month | B37: 0
A39: SELLING COSTS
A40: Estate agent fee % (of sale price) | B40: 0.015
A41: Sale legal fees | B41: 1200
A42: EPC / certificates | B42: 0
A43: Marketing / staging (opex) | B43: 0
A44: Other sale costs | B44: 0
A46: TAX (OPTIONAL QUICK ESTIMATE)
A47: Apply tax estimate? | B47: No
A48: Effective tax rate % (if applied) | B48: 0.2

Sheet Summary
A1: Summary (auto-calculated)
A2: Key outputs for your flip. Change Inputs → the results update.
A4: INPUTS (REFERENCE)
A5: Purchase price | B5: =Inputs!B5 -> 250000
A6: Sale price | B6: =Inputs!B6 -> 320000
A7: Location | B7: =Inputs!B7 -> England & N. Ireland
A8: Buyer type | B8: =Inputs!B8 -> Additional / Investor
A9: Duration (months) | B9: =Inputs!B10 -> 6
A10: Transaction tax | B10: =Inputs!B13 -> 15000
A12: COST BREAKDOWN
A13: Total acquisition (incl. tax) | B13: =(Inputs!B5)+(Inputs!B13)+(Inputs!B14)+(Inputs!B15)+(Inputs!B16)+(Inputs!B17) -> 267000
A14: Total refurb (incl. contingency) | B14: =(Inputs!B29)*(1+(Inputs!B30))+(Inputs!B31)+(Inputs!B32)+(Inputs!B33) -> 27500
A15: Total holding (monthly x months) | B15: =((Inputs!B36)+(Inputs!B37))*(Inputs!B10) -> 2100
A16: Total finance (interest + fees) | B16: =((((Inputs!B5)*(Inputs!B20))+(IF(Inputs!B24="Yes",(B14)*(Inputs!B25),0))*(Inputs!B26))*(Inputs!B21)*(Inputs!B10)/12)+((((Inputs!B5)*(Inputs!B20))+(IF(Inputs!B24="Yes",(B14)*(Inputs!B25),0)))*(Inputs!B22))+((((Inputs!B5)*(Inputs!B20))+(IF(Inputs!B24="Yes",(B14)*(Inputs!B25),0)))*(Inputs!B23)) -> 16875
A17: Total selling (incl. agent) | B17: =(Inputs!B6)*(Inputs!B40)+(Inputs!B41)+(Inputs!B42)+(Inputs!B43)+(Inputs!B44) -> 6000
A18: TOTAL COST | B18: =B13+B14+B15+B16+B17 -> 319475
A19: GROSS PROFIT (pre-tax) | B19: =(Inputs!B6)-B18 -> 525
A20: Profit margin | B20: =IF((Inputs!B6)=0,0,B19/(Inputs!B6)) -> 0.001640625
A21: Peak cash required (rough) | B21: =((Inputs!B5)*(1-(Inputs!B20)))+(Inputs!B13)+(Inputs!B14)+(Inputs!B15)+(Inputs!B16)+(Inputs!B17)+((B14)-(IF(Inputs!B24="Yes",(B14)*(Inputs!B25),0)))+B15+B16+(Inputs!B43) -> 125975
A22: ROI on cash (pre-tax) | B22: =IF(B21=0,0,B19/B21) -> 0.0041674936
A23: Annualised ROI (pre-tax) | B23: =IF((Inputs!B10)=0,0,(1+B22)^(12/(Inputs!B10))-1) -> 0.0083523551
A24: Break-even sale price | B24: =(B18-(Inputs!B6)*(Inputs!B40))/(1-(Inputs!B40)) -> 319467.01
A25: Post-tax profit (optional) | B25: =IF(Inputs!B47="Yes",B19*(1-(Inputs!B48)),B19) -> 525
A26: ROI on cash (post-tax) | B26: =IF(B21=0,0,B25/B21) -> 0.0041674936

Sheet Max Offer
A1: Max Offer Finder (target profit)
A2: Sets a target profit and searches a price range to find the highest purchase price that still meets it.
A4: Target profit (pre-tax) | B4: 20000 | C4: Max offer meeting target | D4: =IFERROR(LOOKUP(2,1/(B11:B210>= $B$4),A11:A210),"") -> 1095000
A5: Min offer price | B5: 100000
A6: Max offer price | B6: 600000
A7: Step | B7: 5000
A10: Offer price | B10: Profit (pre-tax)
A11: =$B$5+(0)*$B$7 -> 100000 | B11: =IF(A11>$B$6,"",(Inputs!B6)-((A11)+(IF(Inputs!D13<>"",Inputs!D13,IF(Inputs!B7="England & N. Ireland",(IF(Inputs!B8="First-time buyer",(IF(A11<=500000,MAX(0,A11-300000)*0.05,(MAX(0,MIN(A11,250000)-125000)*0.02+MAX(0,MIN(A11,925000)-250000)*0.05+MAX(0,MIN(A11,1500000)-925000)*0.1+MAX(0,A11-1500000)*0.12))),(MAX(0,MIN(A11,250000)-125000)*0.02+MAX(0,MIN(A11,925000)-250000)*0.05+MAX(0,MIN(A11,1500000)-925000)*0.1+MAX(0,A11-1500000)*0.12)+IF(Inputs!B8="Additional / Investor",0.05*A11,0)+IF(Inputs!B9="Yes",0.02*A11,0))),IF(Inputs!B7="Scotland",((MAX(0,MIN(A11,250000)-145000)*0.02+MAX(0,MIN(A11,325000)-250000)*0.05+MAX(0,MIN(A11,750000)-325000)*0.1+MAX(0,A11-750000)*0.12)-IF(Inputs!B8="First-time buyer",(IF(A11>145000,MIN(600,0.02*(MIN(A11,175000)-145000)),0)),0)+IF(Inputs!B8="Additional / Investor",0.08*A11,0)),IF(Inputs!B7="Wales",(IF(Inputs!B8="Additional / Investor",(MIN(A11,180000)*0.05+MAX(0,MIN(A11,250000)-180000)*0.085+MAX(0,MIN(A11,400000)-250000)*0.1+MAX(0,MIN(A11,750000)-400000)*0.125+MAX(0,MIN(A11,1500000)-750000)*0.15+MAX(0,A11-1500000)*0.17),(MAX(0,MIN(A11,400000)-225000)*0.06+MAX(0,MIN(A11,750000)-400000)*0.075+MAX(0,MIN(A11,1500000)-750000)*0.1+MAX(0,A11-1500000)*0.12))),0)))))+(Inputs!B14+Inputs!B15+Inputs!B16+Inputs!B17)+(Summary!B14)+(Summary!B15)+(((((A11)*Inputs!B20)+(IF(Inputs!B24="Yes",(Summary!B14)*Inputs!B25,0))*Inputs!B26)*Inputs!B21*Inputs!B10/12)+((((A11)*Inputs!B20)+(IF(Inputs!B24="Yes",(Summary!B14)*Inputs!B25,0)))*Inputs!B22)+((((A11)*Inputs!B20)+(IF(Inputs!B24="Yes",(Summary!B14)*Inputs!B25,0)))*Inputs!B23))+(Summary!B17))) -> 170650 | C11: =IF(A11>$B$6,"","")
A12: =$B$5+(1)*$B$7 -> 105000 | B12: =IF(A12>$B$6,"",(Inputs!B6)-((A12)+(IF(Inputs!D13<>"",Inputs!D13,IF(Inputs!B7="England & N. Ireland",(IF(Inputs!B8="First-time buyer",(IF(A12<=500000,MAX(0,A12-300000)*0.05,(MAX(0,MIN(A12,250000)-125000)*0.02+MAX(0,MIN(A12,925000)-250000)*0.05+MAX(0,MIN(A12,1500000)-925000)*0.1+MAX(0,A12-1500000)*0.12))),(MAX(0,MIN(A12,250000)-125000)*0.02+MAX(0,MIN(A12,925000)-250000)*0.05+MAX(0,MIN(A12,1500000)-925000)*0.1+MAX(0,A12-1500000)*0.12)+IF(Inputs!B8="Additional / Investor",0.05*A12,0)+IF(Inputs!B9="Yes",0.02*A12,0))),IF(Inputs!B7="Scotland",((MAX(0,MIN(A12,250000)-145000)*0.02+MAX(0,MIN(A12,325000)-250000)*0.05+MAX(0,MIN(A12,750000)-325000)*0.1+MAX(0,A12-750000)*0.12)-IF(Inputs!B8="First-time buyer",(IF(A12>145000,MIN(600,0.02*(MIN(A12,175000)-145000)),0)),0)+IF(Inputs!B8="Additional / Investor",0.08*A12,0)),IF(Inputs!B7="Wales",(IF(Inputs!B8="Additional / Investor",(MIN(A12,180000)*0.05+MAX(0,MIN(A12,250000)-180000)*0.085+MAX(0,MIN(A12,400000)-250000)*0.1+MAX(0,MIN(A12,750000)-400000)*0.125+MAX(0,MIN(A12,1500000)-750000)*0.15+MAX(0,A12-1500000)*0.17),(MAX(0,MIN(A12,400000)-225000)*0.06+MAX(0,MIN(A12,750000)-400000)*0.075+MAX(0,MIN(A12,1500000)-750000)*0.1+MAX(0,A12-1500000)*0.12))),0)))))+(Inputs!B14+Inputs!B15+Inputs!B16+Inputs!B17)+(Summary!B14)+(Summary!B15)+(((((A12)*Inputs!B20)+(IF(Inputs!B24="Yes",(Summary!B14)*Inputs!B25,0))*Inputs!B26)*Inputs!B21*Inputs!B10/12)+((((A12)*Inputs!B20)+(IF(Inputs!B24="Yes",(Summary!B14)*Inputs!B25,0)))*Inputs!B22)+((((A12)*Inputs!B20)+(IF(Inputs!B24="Yes",(Summary!B14)*Inputs!B25,0)))*Inputs!B23))+(Summary!B17))) -> 165062.5 | C12: =IF(A12>$B$6,"","")
A13: =$B$5+(2)*$B$7 -> 110000 | B13: =IF(A13>$B$6,"",(Inputs!B6)-((A13)+(IF(Inputs!D13<>"",Inputs!D13,IF(Inputs!B7="England & N. Ireland",(IF(Inputs!B8="First-time buyer",(IF(A13<=500000,MAX(0,A13-300000)*0.05,(MAX(0,MIN(A13,250000)-125000)*0.02+MAX(0,MIN(A13,925000)-250000)*0.05+MAX(0,MIN(A13,1500000)-925000)*0.1+MAX(0,A13-1500000)*0.12))),(MAX(0,MIN(A13,250000)-125000)*0.02+MAX(0,MIN(A13,925000)-250000)*0.05+MAX(0,MIN(A13,1500000)-925000)*0.1+MAX(0,A13-1500000)*0.12)+IF(Inputs!B8="Additional / Investor",0.05*A13,0)+IF(Inputs!B9="Yes",0.02*A13,0))),IF(Inputs!B7="Scotland",((MAX(0,MIN(A13,250000)-145000)*0.02+MAX(0,MIN(A13,325000)-250000)*0.05+MAX(0,MIN(A13,750000)-325000)*0.1+MAX(0,A13-750000)*0.12)-IF(Inputs!B8="First-time buyer",(IF(A13>145000,MIN(600,0.02*(MIN(A13,175000)-145000)),0)),0)+IF(Inputs!B8="Additional / Investor",0.08*A13,0)),IF(Inputs!B7="Wales",(IF(Inputs!B8="Additional / Investor",(MIN(A13,180000)*0.05+MAX(0,MIN(A13,250000)-180000)*0.085+MAX(0,MIN(A13,400000)-250000)*0.1+MAX(0,MIN(A13,750000)-400000)*0.125+MAX(0,MIN(A13,1500000)-750000)*0.15+MAX(0,A13-1500000)*0.17),(MAX(0,MIN(A13,400000)-225000)*0.06+MAX(0,MIN(A13,750000)-400000)*0.075+MAX(0,MIN(A13,1500000)-750000)*0.1+MAX(0,A13-1500000)*0.12))),0)))))+(Inputs!B14+Inputs!B15+Inputs!B16+Inputs!B17)+(Summary!B14)+(Summary!B15)+(((((A13)*Inputs!B20)+(IF(Inputs!B24="Yes",(Summary!B14)*Inputs!B25,0))*Inputs!B26)*Inputs!B21*Inputs!B10/12)+((((A13)*Inputs!B20)+(IF(Inputs!B24="Yes",(Summary!B14)*Inputs!B25,0)))*Inputs!B22)+((((A13)*Inputs!B20)+(IF(Inputs!B24="Yes",(Summary!B14)*Inputs!B25,0)))*Inputs!B23))+(Summary!B17))) -> 159475 | C13: =IF(A13>$B$6,"","")
A14: =$B$5+(3)*$B$7 -> 115000 | B14: =IF(A14>$B$6,"",(Inputs!B6)-((A14)+(IF(Inputs!D13<>"",Inputs!D13,IF(Inputs!B7="England & N. Ireland",(IF(Inputs!B8="First-time buyer",(IF(A14<=500000,MAX(0,A14-300000)*0.05,(MAX(0,MIN(A14,250000)-125000)*0.02+MAX(0,MIN(A14,925000)-250000)*0.05+MAX(0,MIN(A14,1500000)-925000)*0.1+MAX(0,A14-1500000)*0.12))),(MAX(0,MIN(A14,250000)-125000)*0.02+MAX(0,MIN(A14,925000)-250000)*0.05+MAX(0,MIN(A14,1500000)-925000)*0.1+MAX(0,A14-1500000)*0.12)+IF(Inputs!B8="Additional / Investor",0.05*A14,0)+IF(Inputs!B9="Yes",0.02*A14,0))),IF(Inputs!B7="Scotland",((MAX(0,MIN(A14,250000)-145000)*0.02+MAX(0,MIN(A14,325000)-250000)*0.05+MAX(0,MIN(A14,750000)-325000)*0.1+MAX(0,A14-750000)*0.12)-IF(Inputs!B8="First-time buyer",(IF(A14>145000,MIN(600,0.02*(MIN(A14,175000)-145000)),0)),0)+IF(Inputs!B8="Additional / Investor",0.08*A14,0)),IF(Inputs!B7="Wales",(IF(Inputs!B8="Additional / Investor",(MIN(A14,180000)*0.05+MAX(0,MIN(A14,250000)-180000)*0.085+MAX(0,MIN(A14,400000)-250000)*0.1+MAX(0,MIN(A14,750000)-400000)*0.125+MAX(0,MIN(A14,1500000)-750000)*0.15+MAX(0,A14-1500000)*0.17),(MAX(0,MIN(A14,400000)-225000)*0.06+MAX(0,MIN(A14,750000)-400000)*0.075+MAX(0,MIN(A14,1500000)-750000)*0.1+MAX(0,A14-1500000)*0.12))),0)))))+(Inputs!B14+Inputs!B15+Inputs!B16+Inputs!B17)+(Summary!B14)+(Summary!B15)+(((((A14)*Inputs!B20)+(IF(Inputs!B24="Yes",(Summary!B14)*Inputs!B25,0))*Inputs!B26)*Inputs!B21*Inputs!B10/12)+((((A14)*Inputs!B20)+(IF(Inputs!B24="Yes",(Summary!B14)*Inputs!B25,0)))*Inputs!B22)+((((A14)*Inputs!B20)+(IF(Inputs!B24="Yes",(Summary!B14)*Inputs!B25,0)))*Inputs!B23))+(Summary!B17))) -> 153887.5 | C14: =IF(A14>$B$6,"","")
A15: =$B$5+(4)*$B$7 -> 120000 | B15: =IF(A15>$B$6,"",(Inputs!B6)-((A15)+(IF(Inputs!D13<>"",Inputs!D13,IF(Inputs!B7="England & N. Ireland",(IF(Inputs!B8="First-time buyer",(IF(A15<=500000,MAX(0,A15-300000)*0.05,(MAX(0,MIN(A15,250000)-125000)*0.02+MAX(0,MIN(A15,925000)-250000)*0.05+MAX(0,MIN(A15,1500000)-925000)*0.1+MAX(0,A15-1500000)*0.12))),(MAX(0,MIN(A15,250000)-125000)*0.02+MAX(0,MIN(A15,925000)-250000)*0.05+MAX(0,MIN(A15,1500000)-925000)*0.1+MAX(0,A15-1500000)*0.12)+IF(Inputs!B8="Additional / Investor",0.05*A15,0)+IF(Inputs!B9="Yes",0.02*A15,0))),IF(Inputs!B7="Scotland",((MAX(0,MIN(A15,250000)-145000)*0.02+MAX(0,MIN(A15,325000)-250000)*0.05+MAX(0,MIN(A15,750000)-325000)*0.1+MAX(0,A15-750000)*0.12)-IF(Inputs!B8="First-time buyer",(IF(A15>145000,MIN(600,0.02*(MIN(A15,175000)-145000)),0)),0)+IF(Inputs!B8="Additional / Investor",0.08*A15,0)),IF(Inputs!B7="Wales",(IF(Inputs!B8="Additional / Investor",(MIN(A15,180000)*0.05+MAX(0,MIN(A15,250000)-180000)*0.085+MAX(0,MIN(A15,400000)-250000)*0.1+MAX(0,MIN(A15,750000)-400000)*0.125+MAX(0,MIN(A15,1500000)-750000)*0.15+MAX(0,A15-1500000)*0.17),(MAX(0,MIN(A15,400000)-225000)*0.06+MAX(0,MIN(A15,750000)-400000)*0.075+MAX(0,MIN(A15,1500000)-750000)*0.1+MAX(0,A15-1500000)*0.12))),0)))))+(Inputs!B14+Inputs!B15+Inputs!B16+Inputs!B17)+(Summary!B14)+(Summary!B15)+(((((A15)*Inputs!B20)+(IF(Inputs!B24="Yes",(Summary!B14)*Inputs!B25,0))*Inputs!B26)*Inputs!B21*Inputs!B10/12)+((((A15)*Inputs!B20)+(IF(Inputs!B24="Yes",(Summary!B14)*Inputs!B25,0)))*Inputs!B22)+((((A15)*Inputs!B20)+(IF(Inputs!B24="Yes",(Summary!B14)*Inputs!B25,0)))*Inputs!B23))+(Summary!B17))) -> 148300 | C15: =IF(A15>$B$6,"","")
A16: =$B$5+(5)*$B$7 -> 125000 | B16: =IF(A16>$B$6,"",(Inputs!B6)-((A16)+(IF(Inputs!D13<>"",Inputs!D13,IF(Inputs!B7="England & N. Ireland",(IF(Inputs!B8="First-time buyer",(IF(A16<=500000,MAX(0,A16-300000)*0.05,(MAX(0,MIN(A16,250000)-125000)*0.02+MAX(0,MIN(A16,925000)-250000)*0.05+MAX(0,MIN(A16,1500000)-925000)*0.1+MAX(0,A16-1500000)*0.12))),(MAX(0,MIN(A16,250000)-125000)*0.02+MAX(0,MIN(A16,925000)-250000)*0.05+MAX(0,MIN(A16,1500000)-925000)*0.1+MAX(0,A16-1500000)*0.12)+IF(Inputs!B8="Additional / Investor",0.05*A16,0)+IF(Inputs!B9="Yes",0.02*A16,0))),IF(Inputs!B7="Scotland",((MAX(0,MIN(A16,250000)-145000)*0.02+MAX(0,MIN(A16,325000)-250000)*0.05+MAX(0,MIN(A16,750000)-325000)*0.1+MAX(0,A16-750000)*0.12)-IF(Inputs!B8="First-time buyer",(IF(A16>145000,MIN(600,0.02*(MIN(A16,175000)-145000)),0)),0)+IF(Inputs!B8="Additional / Investor",0.08*A16,0)),IF(Inputs!B7="Wales",(IF(Inputs!B8="Additional / Investor",(MIN(A16,180000)*0.05+MAX(0,MIN(A16,250000)-180000)*0.085+MAX(0,MIN(A16,400000)-250000)*0.1+MAX(0,MIN(A16,750000)-400000)*0.125+MAX(0,MIN(A16,1500000)-750000)*0.15+MAX(0,A16-1500000)*0.17),(MAX(0,MIN(A16,400000)-225000)*0.06+MAX(0,MIN(A16,750000)-400000)*0.075+MAX(0,MIN(A16,1500000)-750000)*0.1+MAX(0,A16-1500000)*0.12))),0)))))+(Inputs!B14+Inputs!B15+Inputs!B16+Inputs!B17)+(Summary!B14)+(Summary!B15)+(((((A16)*Inputs!B20)+(IF(Inputs!B24="Yes",(Summary!B14)*Inputs!B25,0))*Inputs!B26)*Inputs!B21*Inputs!B10/12)+((((A16)*Inputs!B20)+(IF(Inputs!B24="Yes",(Summary!B14)*Inputs!B25,0)))*Inputs!B22)+((((A16)*Inputs!B20)+(IF(Inputs!B24="Yes",(Summary!B14)*Inputs!B25,0)))*Inputs!B23))+(Summary!B17))) -> 142712.5 | C16: =IF(A16>$B$6,"","")
A17: =$B$5+(6)*$B$7 -> 130000 | B17: =IF(A17>$B$6,"",(Inputs!B6)-((A17)+(IF(Inputs!D13<>"",Inputs!D13,IF(Inputs!B7="England & N. Ireland",(IF(Inputs!B8="First-time buyer",(IF(A17<=500000,MAX(0,A17-300000)*0.05,(MAX(0,MIN(A17,250000)-125000)*0.02+MAX(0,MIN(A17,925000)-250000)*0.05+MAX(0,MIN(A17,1500000)-925000)*0.1+MAX(0,A17-1500000)*0.12))),(MAX(0,MIN(A17,250000)-125000)*0.02+MAX(0,MIN(A17,925000)-250000)*0.05+MAX(0,MIN(A17,1500000)-925000)*0.1+MAX(0,A17-1500000)*0.12)+IF(Inputs!B8="Additional / Investor",0.05*A17,0)+IF(Inputs!B9="Yes",0.02*A17,0))),IF(Inputs!B7="Scotland",((MAX(0,MIN(A17,250000)-145000)*0.02+MAX(0,MIN(A17,325000)-250000)*0.05+MAX(0,MIN(A17,750000)-325000)*0.1+MAX(0,A17-750000)*0.12)-IF(Inputs!B8="First-time buyer",(IF(A17>145000,MIN(600,0.02*(MIN(A17,175000)-145000)),0)),0)+IF(Inputs!B8="Additional / Investor",0.08*A17,0)),IF(Inputs!B7="Wales",(IF(Inputs!B8="Additional / Investor",(MIN(A17,180000)*0.05+MAX(0,MIN(A17,250000)-180000)*0.085+MAX(0,MIN(A17,400000)-250000)*0.1+MAX(0,MIN(A17,750000)-400000)*0.125+MAX(0,MIN(A17,1500000)-750000)*0.15+MAX(0,A17-1500000)*0.17),(MAX(0,MIN(A17,400000)-225000)*0.06+MAX(0,MIN(A17,750000)-400000)*0.075+MAX(0,MIN(A17,1500000)-750000)*0.1+MAX(0,A17-1500000)*0.12))),0)))))+(Inputs!B14+Inputs!B15+Inputs!B16+Inputs!B17)+(Summary!B14)+(Summary!B15)+(((((A17)*Inputs!B20)+(IF(Inputs!B24="Yes",(Summary!B14)*Inputs!B25,0))*Inputs!B26)*Inputs!B21*Inputs!B10/12)+((((A17)*Inputs!B20)+(IF(Inputs!B24="Yes",(Summary!B14)*Inputs!B25,0)))*Inputs!B22)+((((A17)*Inputs!B20)+(IF(Inputs!B24="Yes",(Summary!B14)*Inputs!B25,0)))*Inputs!B23))+(Summary!B17))) -> 137025 | C17: =IF(A17>$B$6,"","")
A18: =$B$5+(7)*$B$7 -> 135000 | B18: =IF(A18>$B$6,"",(Inputs!B6)-((A18)+(IF(Inputs!D13<>"",Inputs!D13,IF(Inputs!B7="England & N. Ireland",(IF(Inputs!B8="First-time buyer",(IF(A18<=500000,MAX(0,A18-300000)*0.05,(MAX(0,MIN(A18,250000)-125000)*0.02+MAX(0,MIN(A18,925000)-250000)*0.05+MAX(0,MIN(A18,1500000)-925000)*0.1+MAX(0,A18-1500000)*0.12))),(MAX(0,MIN(A18,250000)-125000)*0.02+MAX(0,MIN(A18,925000)-250000)*0.05+MAX(0,MIN(A18,1500000)-925000)*0.1+MAX(0,A18-1500000)*0.12)+IF(Inputs!B8="Additional / Investor",0.05*A18,0)+IF(Inputs!B9="Yes",0.02*A18,0))),IF(Inputs!B7="Scotland",((MAX(0,MIN(A18,250000)-145000)*0.02+MAX(0,MIN(A18,325000)-250000)*0.05+MAX(0,MIN(A18,750000)-325000)*0.1+MAX(0,A18-750000)*0.12)-IF(Inputs!B8="First-time buyer",(IF(A18>145000,MIN(600,0.02*(MIN(A18,175000)-145000)),0)),0)+IF(Inputs!B8="Additional / Investor",0.08*A18,0)),IF(Inputs!B7="Wales",(IF(Inputs!B8="Additional / Investor",(MIN(A18,180000)*0.05+MAX(0,MIN(A18,250000)-180000)*0.085+MAX(0,MIN(A18,400000)-250000)*0.1+MAX(0,MIN(A18,750000)-400000)*0.125+MAX(0,MIN(A18,1500000)-750000)*0.15+MAX(0,A18-1500000)*0.17),(MAX(0,MIN(A18,400000)-225000)*0.06+MAX(0,MIN(A18,750000)-400000)*0.075+MAX(0,MIN(A18,1500000)-750000)*0.1+MAX(0,A18-1500000)*0.12))),0)))))+(Inputs!B14+Inputs!B15+Inputs!B16+Inputs!B17)+(Summary!B14)+(Summary!B15)+(((((A18)*Inputs!B20)+(IF(Inputs!B24="Yes",(Summary!B14)*Inputs!B25,0))*Inputs!B26)*Inputs!B21*Inputs!B10/12)+((((A18)*Inputs!B20)+(IF(Inputs!B24="Yes",(Summary!B14)*Inputs!B25,0)))*Inputs!B22)+((((A18)*Inputs!B20)+(IF(Inputs!B24="Yes",(Summary!B14)*Inputs!B25,0)))*Inputs!B23))+(Summary!B17))) -> 131337.5 | C18: =IF(A18>$B$6,"","")
A19: =$B$5+(8)*$B$7 -> 140000 | B19: =IF(A19>$B$6,"",(Inputs!B6)-((A19)+(IF(Inputs!D13<>"",Inputs!D13,IF(Inputs!B7="England & N. Ireland",(IF(Inputs!B8="First-time buyer",(IF(A19<=500000,MAX(0,A19-300000)*0.05,(MAX(0,MIN(A19,250000)-125000)*0.02+MAX(0,MIN(A19,925000)-250000)*0.05+MAX(0,MIN(A19,1500000)-925000)*0.1+MAX(0,A19-1500000)*0.12))),(MAX(0,MIN(A19,250000)-125000)*0.02+MAX(0,MIN(A19,925000)-250000)*0.05+MAX(0,MIN(A19,1500000)-925000)*0.1+MAX(0,A19-1500000)*0.12)+IF(Inputs!B8="Additional / Investor",0.05*A19,0)+IF(Inputs!B9="Yes",0.02*A19,0))),IF(Inputs!B7="Scotland",((MAX(0,MIN(A19,250000)-145000)*0.02+MAX(0,MIN(A19,325000)-250000)*0.05+MAX(0,MIN(A19,750000)-325000)*0.1+MAX(0,A19-750000)*0.12)-IF(Inputs!B8="First-time buyer",(IF(A19>145000,MIN(600,0.02*(MIN(A19,175000)-145000)),0)),0)+IF(Inputs!B8="Additional / Investor",0.08*A19,0)),IF(Inputs!B7="Wales",(IF(Inputs!B8="Additional / Investor",(MIN(A19,180000)*0.05+MAX(0,MIN(A19,250000)-180000)*0.085+MAX(0,MIN(A19,400000)-250000)*0.1+MAX(0,MIN(A19,750000)-400000)*0.125+MAX(0,MIN(A19,1500000)-750000)*0.15+MAX(0,A19-1500000)*0.17),(MAX(0,MIN(A19,400000)-225000)*0.06+MAX(0,MIN(A19,750000)-400000)*0.075+MAX(0,MIN(A19,1500000)-750000)*0.1+MAX(0,A19-1500000)*0.12))),0)))))+(Inputs!B14+Inputs!B15+Inputs!B16+Inputs!B17)+(Summary!B14)+(Summary!B15)+(((((A19)*Inputs!B20)+(IF(Inputs!B24="Yes",(Summary!B14)*Inputs!B25,0))*Inputs!B26)*Inputs!B21*Inputs!B10/12)+((((A19)*Inputs!B20)+(IF(Inputs!B24="Yes",(Summary!B14)*Inputs!B25,0)))*Inputs!B22)+((((A19)*Inputs!B20)+(IF(Inputs!B24="Yes",(Summary!B14)*Inputs!B25,0)))*Inputs!B23))+(Summary!B17))) -> 125650 | C19: =IF(A19>$B$6,"","")
A20: =$B$5+(9)*$B$7 -> 145000 | B20: =IF(A20>$B$6,"",(Inputs!B6)-((A20)+(IF(Inputs!D13<>"",Inputs!D13,IF(Inputs!B7="England & N. Ireland",(IF(Inputs!B8="First-time buyer",(IF(A20<=500000,MAX(0,A20-300000)*0.05,(MAX(0,MIN(A20,250000)-125000)*0.02+MAX(0,MIN(A20,925000)-250000)*0.05+MAX(0,MIN(A20,1500000)-925000)*0.1+MAX(0,A20-1500000)*0.12))),(MAX(0,MIN(A20,250000)-125000)*0.02+MAX(0,MIN(A20,925000)-250000)*0.05+MAX(0,MIN(A20,1500000)-925000)*0.1+MAX(0,A20-1500000)*0.12)+IF(Inputs!B8="Additional / Investor",0.05*A20,0)+IF(Inputs!B9="Yes",0.02*A20,0))),IF(Inputs!B7="Scotland",((MAX(0,MIN(A20,250000)-145000)*0.02+MAX(0,MIN(A20,325000)-250000)*0.05+MAX(0,MIN(A20,750000)-325000)*0.1+MAX(0,A20-750000)*0.12)-IF(Inputs!B8="First-time buyer",(IF(A20>145000,MIN(600,0.02*(MIN(A20,175000)-145000)),0)),0)+IF(Inputs!B8="Additional / Investor",0.08*A20,0)),IF(Inputs!B7="Wales",(IF(Inputs!B8="Additional / Investor",(MIN(A20,180000)*0.05+MAX(0,MIN(A20,250000)-180000)*0.085+MAX(0,MIN(A20,400000)-250000)*0.1+MAX(0,MIN(A20,750000)-400000)*0.125+MAX(0,MIN(A20,1500000)-750000)*0.15+MAX(0,A20-1500000)*0.17),(MAX(0,MIN(A20,400000)-225000)*0.06+MAX(0,MIN(A20,750000)-400000)*0.075+MAX(0,MIN(A20,1500000)-750000)*0.1+MAX(0,A20-1500000)*0.12))),0)))))+(Inputs!B14+Inputs!B15+Inputs!B16+Inputs!B17)+(Summary!B14)+(Summary!B15)+(((((A20)*Inputs!B20)+(IF(Inputs!B24="Yes",(Summary!B14)*Inputs!B25,0))*Inputs!B26)*Inputs!B21*Inputs!B10/12)+((((A20)*Inputs!B20)+(IF(Inputs!B24="Yes",(Summary!B14)*Inputs!B25,0)))*Inputs!B22)+((((A20)*Inputs!B20)+(IF(Inputs!B24="Yes",(Summary!B14)*Inputs!B25,0)))*Inputs!B23))+(Summary!B17))) -> 119962.5 | C20: =IF(A20>$B$6,"","")
A21: =$B$5+(10)*$B$7 -> 150000 | B21: =IF(A21>$B$6,"",(Inputs!B6)-((A21)+(IF(Inputs!D13<>"",Inputs!D13,IF(Inputs!B7="England & N. Ireland",(IF(Inputs!B8="First-time buyer",(IF(A21<=500000,MAX(0,A21-300000)*0.05,(MAX(0,MIN(A21,250000)-125000)*0.02+MAX(0,MIN(A21,925000)-250000)*0.05+MAX(0,MIN(A21,1500000)-925000)*0.1+MAX(0,A21-1500000)*0.12))),(MAX(0,MIN(A21,250000)-125000)*0.02+MAX(0,MIN(A21,925000)-250000)*0.05+MAX(0,MIN(A21,1500000)-925000)*0.1+MAX(0,A21-1500000)*0.12)+IF(Inputs!B8="Additional / Investor",0.05*A21,0)+IF(Inputs!B9="Yes",0.02*A21,0))),IF(Inputs!B7="Scotland",((MAX(0,MIN(A21,250000)-145000)*0.02+MAX(0,MIN(A21,325000)-250000)*0.05+MAX(0,MIN(A21,750000)-325000)*0.1+MAX(0,A21-750000)*0.12)-IF(Inputs!B8="First-time buyer",(IF(A21>145000,MIN(600,0.02*(MIN(A21,175000)-145000)),0)),0)+IF(Inputs!B8="Additional / Investor",0.08*A21,0)),IF(Inputs!B7="Wales",(IF(Inputs!B8="Additional / Investor",(MIN(A21,180000)*0.05+MAX(0,MIN(A21,250000)-180000)*0.085+MAX(0,MIN(A21,400000)-250000)*0.1+MAX(0,MIN(A21,750000)-400000)*0.125+MAX(0,MIN(A21,1500000)-750000)*0.15+MAX(0,A21-1500000)*0.17),(MAX(0,MIN(A21,400000)-225000)*0.06+MAX(0,MIN(A21,750000)-400000)*0.075+MAX(0,MIN(A21,1500000)-750000)*0.1+MAX(0,A21-1500000)*0.12))),0)))))+(Inputs!B14+Inputs!B15+Inputs!B16+Inputs!B17)+(Summary!B14)+(Summary!B15)+(((((A21)*Inputs!B20)+(IF(Inputs!B24="Yes",(Summary!B14)*Inputs!B25,0))*Inputs!B26)*Inputs!B21*Inputs!B10/12)+((((A21)*Inputs!B20)+(IF(Inputs!B24="Yes",(Summary!B14)*Inputs!B25,0)))*Inputs!B22)+((((A21)*Inputs!B20)+(IF(Inputs!B24="Yes",(Summary!B14)*Inputs!B25,0)))*Inputs!B23))+(Summary!B17))) -> 114275 | C21: =IF(A21>$B$6,"","")
A22: =$B$5+(11)*$B$7 -> 155000 | B22: =IF(A22>$B$6,"",(Inputs!B6)-((A22)+(IF(Inputs!D13<>"",Inputs!D13,IF(Inputs!B7="England & N. Ireland",(IF(Inputs!B8="First-time buyer",(IF(A22<=500000,MAX(0,A22-300000)*0.05,(MAX(0,MIN(A22,250000)-125000)*0.02+MAX(0,MIN(A22,925000)-250000)*0.05+MAX(0,MIN(A22,1500000)-925000)*0.1+MAX(0,A22-1500000)*0.12))),(MAX(0,MIN(A22,250000)-125000)*0.02+MAX(0,MIN(A22,925000)-250000)*0.05+MAX(0,MIN(A22,1500000)-925000)*0.1+MAX(0,A22-1500000)*0.12)+IF(Inputs!B8="Additional / Investor",0.05*A22,0)+IF(Inputs!B9="Yes",0.02*A22,0))),IF(Inputs!B7="Scotland",((MAX(0,MIN(A22,250000)-145000)*0.02+MAX(0,MIN(A22,325000)-250000)*0.05+MAX(0,MIN(A22,750000)-325000)*0.1+MAX(0,A22-750000)*0.12)-IF(Inputs!B8="First-time buyer",(IF(A22>145000,MIN(600,0.02*(MIN(A22,175000)-145000)),0)),0)+IF(Inputs!B8="Additional / Investor",0.08*A22,0)),IF(Inputs!B7="Wales",(IF(Inputs!B8="Additional / Investor",(MIN(A22,180000)*0.05+MAX(0,MIN(A22,250000)-180000)*0.085+MAX(0,MIN(A22,400000)-250000)*0.1+MAX(0,MIN(A22,750000)-400000)*0.125+MAX(0,MIN(A22,1500000)-750000)*0.15+MAX(0,A22-1500000)*0.17),(MAX(0,MIN(A22,400000)-225000)*0.06+MAX(0,MIN(A22,750000)-400000)*0.075+MAX(0,MIN(A22,1500000)-750000)*0.1+MAX(0,A22-1500000)*0.12))),0)))))+(Inputs!B14+Inputs!B15+Inputs!B16+Inputs!B17)+(Summary!B14)+(Summary!B15)+(((((A22)*Inputs!B20)+(IF(Inputs!B24="Yes",(Summary!B14)*Inputs!B25,0))*Inputs!B26)*Inputs!B21*Inputs!B10/12)+((((A22)*Inputs!B20)+(IF(Inputs!B24="Yes",(Summary!B14)*Inputs!B25,0)))*Inputs!B22)+((((A22)*Inputs!B20)+(IF(Inputs!B24="Yes",(Summary!B14)*Inputs!B25,0)))*Inputs!B23))+(Summary!B17))) -> 108587.5 | C22: =IF(A22>$B$6,"","")
A23: =$B$5+(12)*$B$7 -> 160000 | B23: =IF(A23>$B$6,"",(Inputs!B6)-((A23)+(IF(Inputs!D13<>"",Inputs!D13,IF(Inputs!B7="England & N. Ireland",(IF(Inputs!B8="First-time buyer",(IF(A23<=500000,MAX(0,A23-300000)*0.05,(MAX(0,MIN(A23,250000)-125000)*0.02+MAX(0,MIN(A23,925000)-250000)*0.05+MAX(0,MIN(A23,1500000)-925000)*0.1+MAX(0,A23-1500000)*0.12))),(MAX(0,MIN(A23,250000)-125000)*0.02+MAX(0,MIN(A23,925000)-250000)*0.05+MAX(0,MIN(A23,1500000)-925000)*0.1+MAX(0,A23-1500000)*0.12)+IF(Inputs!B8="Additional / Investor",0.05*A23,0)+IF(Inputs!B9="Yes",0.02*A23,0))),IF(Inputs!B7="Scotland",((MAX(0,MIN(A23,250000)-145000)*0.02+MAX(0,MIN(A23,325000)-250000)*0.05+MAX(0,MIN(A23,750000)-325000)*0.1+MAX(0,A23-750000)*0.12)-IF(Inputs!B8="First-time buyer",(IF(A23>145000,MIN(600,0.02*(MIN(A23,175000)-145000)),0)),0)+IF(Inputs!B8="Additional / Investor",0.08*A23,0)),IF(Inputs!B7="Wales",(IF(Inputs!B8="Additional / Investor",(MIN(A23,180000)*0.05+MAX(0,MIN(A23,250000)-180000)*0.085+MAX(0,MIN(A23,400000)-250000)*0.1+MAX(0,MIN(A23,750000)-400000)*0.125+MAX(0,MIN(A23,1500000)-750000)*0.15+MAX(0,A23-1500000)*0.17),(MAX(0,MIN(A23,400000)-225000)*0.06+MAX(0,MIN(A23,750000)-400000)*0.075+MAX(0,MIN(A23,1500000)-750000)*0.1+MAX(0,A23-1500000)*0.12))),0)))))+(Inputs!B14+Inputs!B15+Inputs!B16+Inputs!B17)+(Summary!B14)+(Summary!B15)+(((((A23)*Inputs!B20)+(IF(Inputs!B24="Yes",(Summary!B14)*Inputs!B25,0))*Inputs!B26)*Inputs!B21*Inputs!B10/12)+((((A23)*Inputs!B20)+(IF(Inputs!B24="Yes",(Summary!B14)*Inputs!B25,0)))*Inputs!B22)+((((A23)*Inputs!B20)+(IF(Inputs!B24="Yes",(Summary!B14)*Inputs!B25,0)))*Inputs!B23))+(Summary!B17))) -> 102900 | C23: =IF(A23>$B$6,"","")
A24: =$B$5+(13)*$B$7 -> 165000 | B24: =IF(A24>$B$6,"",(Inputs!B6)-((A24)+(IF(Inputs!D13<>"",Inputs!D13,IF(Inputs!B7="England & N. Ireland",(IF(Inputs!B8="First-time buyer",(IF(A24<=500000,MAX(0,A24-300000)*0.05,(MAX(0,MIN(A24,250000)-125000)*0.02+MAX(0,MIN(A24,925000)-250000)*0.05+MAX(0,MIN(A24,1500000)-925000)*0.1+MAX(0,A24-1500000)*0.12))),(MAX(0,MIN(A24,250000)-125000)*0.02+MAX(0,MIN(A24,925000)-250000)*0.05+MAX(0,MIN(A24,1500000)-925000)*0.1+MAX(0,A24-1500000)*0.12)+IF(Inputs!B8="Additional / Investor",0.05*A24,0)+IF(Inputs!B9="Yes",0.02*A24,0))),IF(Inputs!B7="Scotland",((MAX(0,MIN(A24,250000)-145000)*0.02+MAX(0,MIN(A24,325000)-250000)*0.05+MAX(0,MIN(A24,750000)-325000)*0.1+MAX(0,A24-750000)*0.12)-IF(Inputs!B8="First-time buyer",(IF(A24>145000,MIN(600,0.02*(MIN(A24,175000)-145000)),0)),0)+IF(Inputs!B8="Additional / Investor",0.08*A24,0)),IF(Inputs!B7="Wales",(IF(Inputs!B8="Additional / Investor",(MIN(A24,180000)*0.05+MAX(0,MIN(A24,250000)-180000)*0.085+MAX(0,MIN(A24,400000)-250000)*0.1+MAX(0,MIN(A24,750000)-400000)*0.125+MAX(0,MIN(A24,1500000)-750000)*0.15+MAX(0,A24-1500000)*0.17),(MAX(0,MIN(A24,400000)-225000)*0.06+MAX(0,MIN(A24,750000)-400000)*0.075+MAX(0,MIN(A24,1500000)-750000)*0.1+MAX(0,A24-1500000)*0.12))),0)))))+(Inputs!B14+Inputs!B15+Inputs!B16+Inputs!B17)+(Summary!B14)+(Summary!B15)+(((((A24)*Inputs!B20)+(IF(Inputs!B24="Yes",(Summary!B14)*Inputs!B25,0))*Inputs!B26)*Inputs!B21*Inputs!B10/12)+((((A24)*Inputs!B20)+(IF(Inputs!B24="Yes",(Summary!B14)*Inputs!B25,0)))*Inputs!B22)+((((A24)*Inputs!B20)+(IF(Inputs!B24="Yes",(Summary!B14)*Inputs!B25,0)))*Inputs!B23))+(Summary!B17))) -> 97212.5 | C24: =IF(A24>$B$6,"","")
A25: =$B$5+(14)*$B$7 -> 170000 | B25: =IF(A25>$B$6,"",(Inputs!B6)-((A25)+(IF(Inputs!D13<>"",Inputs!D13,IF(Inputs!B7="England & N. Ireland",(IF(Inputs!B8="First-time buyer",(IF(A25<=500000,MAX(0,A25-300000)*0.05,(MAX(0,MIN(A25,250000)-125000)*0.02+MAX(0,MIN(A25,925000)-250000)*0.05+MAX(0,MIN(A25,1500000)-925000)*0.1+MAX(0,A25-1500000)*0.12))),(MAX(0,MIN(A25,250000)-125000)*0.02+MAX(0,MIN(A25,925000)-250000)*0.05+MAX(0,MIN(A25,1500000)-925000)*0.1+MAX(0,A25-1500000)*0.12)+IF(Inputs!B8="Additional / Investor",0.05*A25,0)+IF(Inputs!B9="Yes",0.02*A25,0))),IF(Inputs!B7="Scotland",((MAX(0,MIN(A25,250000)-145000)*0.02+MAX(0,MIN(A25,325000)-250000)*0.05+MAX(0,MIN(A25,750000)-325000)*0.1+MAX(0,A25-750000)*0.12)-IF(Inputs!B8="First-time buyer",(IF(A25>145000,MIN(600,0.02*(MIN(A25,175000)-145000)),0)),0)+IF(Inputs!B8="Additional / Investor",0.08*A25,0)),IF(Inputs!B7="Wales",(IF(Inputs!B8="Additional / Investor",(MIN(A25,180000)*0.05+MAX(0,MIN(A25,250000)-180000)*0.085+MAX(0,MIN(A25,400000)-250000)*0.1+MAX(0,MIN(A25,750000)-400000)*0.125+MAX(0,MIN(A25,1500000)-750000)*0.15+MAX(0,A25-1500000)*0.17),(MAX(0,MIN(A25,400000)-225000)*0.06+MAX(0,MIN(A25,750000)-400000)*0.075+MAX(0,MIN(A25,1500000)-750000)*0.1+MAX(0,A25-1500000)*0.12))),0)))))+(Inputs!B14+Inputs!B15+Inputs!B16+Inputs!B17)+(Summary!B14)+(Summary!B15)+(((((A25)*Inputs!B20)+(IF(Inputs!B24="Yes",(Summary!B14)*Inputs!B25,0))*Inputs!B26)*Inputs!B21*Inputs!B10/12)+((((A25)*Inputs!B20)+(IF(Inputs!B24="Yes",(Summary!B14)*Inputs!B25,0)))*Inputs!B22)+((((A25)*Inputs!B20)+(IF(Inputs!B24="Yes",(Summary!B14)*Inputs!B25,0)))*Inputs!B23))+(Summary!B17))) -> 91525 | C25: =IF(A25>$B$6,"","")
A26: =$B$5+(15)*$B$7 -> 175000 | B26: =IF(A26>$B$6,"",(Inputs!B6)-((A26)+(IF(Inputs!D13<>"",Inputs!D13,IF(Inputs!B7="England & N. Ireland",(IF(Inputs!B8="First-time buyer",(IF(A26<=500000,MAX(0,A26-300000)*0.05,(MAX(0,MIN(A26,250000)-125000)*0.02+MAX(0,MIN(A26,925000)-250000)*0.05+MAX(0,MIN(A26,1500000)-925000)*0.1+MAX(0,A26-1500000)*0.12))),(MAX(0,MIN(A26,250000)-125000)*0.02+MAX(0,MIN(A26,925000)-250000)*0.05+MAX(0,MIN(A26,1500000)-925000)*0.1+MAX(0,A26-1500000)*0.12)+IF(Inputs!B8="Additional / Investor",0.05*A26,0)+IF(Inputs!B9="Yes",0.02*A26,0))),IF(Inputs!B7="Scotland",((MAX(0,MIN(A26,250000)-145000)*0.02+MAX(0,MIN(A26,325000)-250000)*0.05+MAX(0,MIN(A26,750000)-325000)*0.1+MAX(0,A26-750000)*0.12)-IF(Inputs!B8="First-time buyer",(IF(A26>145000,MIN(600,0.02*(MIN(A26,175000)-145000)),0)),0)+IF(Inputs!B8="Additional / Investor",0.08*A26,0)),IF(Inputs!B7="Wales",(IF(Inputs!B8="Additional / Investor",(MIN(A26,180000)*0.05+MAX(0,MIN(A26,250000)-180000)*0.085+MAX(0,MIN(A26,400000)-250000)*0.1+MAX(0,MIN(A26,750000)-400000)*0.125+MAX(0,MIN(A26,1500000)-750000)*0.15+MAX(0,A26-1500000)*0.17),(MAX(0,MIN(A26,400000)-225000)*0.06+MAX(0,MIN(A26,750000)-400000)*0.075+MAX(0,MIN(A26,1500000)-750000)*0.1+MAX(0,A26-1500000)*0.12))),0)))))+(Inputs!B14+Inputs!B15+Inputs!B16+Inputs!B17)+(Summary!B14)+(Summary!B15)+(((((A26)*Inputs!B20)+(IF(Inputs!B24="Yes",(Summary!B14)*Inputs!B25,0))*Inputs!B26)*Inputs!B21*Inputs!B10/12)+((((A26)*Inputs!B20)+(IF(Inputs!B24="Yes",(Summary!B14)*Inputs!B25,0)))*Inputs!B22)+((((A26)*Inputs!B20)+(IF(Inputs!B24="Yes",(Summary!B14)*Inputs!B25,0)))*Inputs!B23))+(Summary!B17))) -> 85837.5 | C26: =IF(A26>$B$6,"","")
A27: =$B$5+(16)*$B$7 -> 180000 | B27: =IF(A27>$B$6,"",(Inputs!B6)-((A27)+(IF(Inputs!D13<>"",Inputs!D13,IF(Inputs!B7="England & N. Ireland",(IF(Inputs!B8="First-time buyer",(IF(A27<=500000,MAX(0,A27-300000)*0.05,(MAX(0,MIN(A27,250000)-125000)*0.02+MAX(0,MIN(A27,925000)-250000)*0.05+MAX(0,MIN(A27,1500000)-925000)*0.1+MAX(0,A27-1500000)*0.12))),(MAX(0,MIN(A27,250000)-125000)*0.02+MAX(0,MIN(A27,925000)-250000)*0.05+MAX(0,MIN(A27,1500000)-925000)*0.1+MAX(0,A27-1500000)*0.12)+IF(Inputs!B8="Additional / Investor",0.05*A27,0)+IF(Inputs!B9="Yes",0.02*A27,0))),IF(Inputs!B7="Scotland",((MAX(0,MIN(A27,250000)-145000)*0.02+MAX(0,MIN(A27,325000)-250000)*0.05+MAX(0,MIN(A27,750000)-325000)*0.1+MAX(0,A27-750000)*0.12)-IF(Inputs!B8="First-time buyer",(IF(A27>145000,MIN(600,0.02*(MIN(A27,175000)-145000)),0)),0)+IF(Inputs!B8="Additional / Investor",0.08*A27,0)),IF(Inputs!B7="Wales",(IF(Inputs!B8="Additional / Investor",(MIN(A27,180000)*0.05+MAX(0,MIN(A27,250000)-180000)*0.085+MAX(0,MIN(A27,400000)-250000)*0.1+MAX(0,MIN(A27,750000)-400000)*0.125+MAX(0,MIN(A27,1500000)-750000)*0.15+MAX(0,A27-1500000)*0.17),(MAX(0,MIN(A27,400000)-225000)*0.06+MAX(0,MIN(A27,750000)-400000)*0.075+MAX(0,MIN(A27,1500000)-750000)*0.1+MAX(0,A27-1500000)*0.12))),0)))))+(Inputs!B14+Inputs!B15+Inputs!B16+Inputs!B17)+(Summary!B14)+(Summary!B15)+(((((A27)*Inputs!B20)+(IF(Inputs!B24="Yes",(Summary!B14)*Inputs!B25,0))*Inputs!B26)*Inputs!B21*Inputs!B10/12)+((((A27)*Inputs!B20)+(IF(Inputs!B24="Yes",(Summary!B14)*Inputs!B25,0)))*Inputs!B22)+((((A27)*Inputs!B20)+(IF(Inputs!B24="Yes",(Summary!B14)*Inputs!B25,0)))*Inputs!B23))+(Summary!B17))) -> 80150 | C27: =IF(A27>$B$6,"","")
A28: =$B$5+(17)*$B$7 -> 185000 | B28: =IF(A28>$B$6,"",(Inputs!B6)-((A28)+(IF(Inputs!D13<>"",Inputs!D13,IF(Inputs!B7="England & N. Ireland",(IF(Inputs!B8="First-time buyer",(IF(A28<=500000,MAX(0,A28-300000)*0.05,(MAX(0,MIN(A28,250000)-125000)*0.02+MAX(0,MIN(A28,925000)-250000)*0.05+MAX(0,MIN(A28,1500000)-925000)*0.1+MAX(0,A28-1500000)*0.12))),(MAX(0,MIN(A28,250000)-125000)*0.02+MAX(0,MIN(A28,925000)-250000)*0.05+MAX(0,MIN(A28,1500000)-925000)*0.1+MAX(0,A28-1500000)*0.12)+IF(Inputs!B8="Additional / Investor",0.05*A28,0)+IF(Inputs!B9="Yes",0.02*A28,0))),IF(Inputs!B7="Scotland",((MAX(0,MIN(A28,250000)-145000)*0.02+MAX(0,MIN(A28,325000)-250000)*0.05+MAX(0,MIN(A28,750000)-325000)*0.1+MAX(0,A28-750000)*0.12)-IF(Inputs!B8="First-time buyer",(IF(A28>145000,MIN(600,0.02*(MIN(A28,175000)-145000)),0)),0)+IF(Inputs!B8="Additional / Investor",0.08*A28,0)),IF(Inputs!B7="Wales",(IF(Inputs!B8="Additional / Investor",(MIN(A28,180000)*0.05+MAX(0,MIN(A28,250000)-180000)*0.085+MAX(0,MIN(A28,400000)-250000)*0.1+MAX(0,MIN(A28,750000)-400000)*0.125+MAX(0,MIN(A28,1500000)-750000)*0.15+MAX(0,A28-1500000)*0.17),(MAX(0,MIN(A28,400000)-225000)*0.06+MAX(0,MIN(A28,750000)-400000)*0.075+MAX(0,MIN(A28,1500000)-750000)*0.1+MAX(0,A28-1500000)*0.12))),0)))))+(Inputs!B14+Inputs!B15+Inputs!B16+Inputs!B17)+(Summary!B14)+(Summary!B15)+(((((A28)*Inputs!B20)+(IF(Inputs!B24="Yes",(Summary!B14)*Inputs!B25,0))*Inputs!B26)*Inputs!B21*Inputs!B10/12)+((((A28)*Inputs!B20)+(IF(Inputs!B24="Yes",(Summary!B14)*Inputs!B25,0)))*Inputs!B22)+((((A28)*Inputs!B20)+(IF(Inputs!B24="Yes",(Summary!B14)*Inputs!B25,0)))*Inputs!B23))+(Summary!B17))) -> 74462.5 | C28: =IF(A28>$B$6,"","")
A29: =$B$5+(18)*$B$7 -> 190000 | B29: =IF(A29>$B$6,"",(Inputs!B6)-((A29)+(IF(Inputs!D13<>"",Inputs!D13,IF(Inputs!B7="England & N. Ireland",(IF(Inputs!B8="First-time buyer",(IF(A29<=500000,MAX(0,A29-300000)*0.05,(MAX(0,MIN(A29,250000)-125000)*0.02+MAX(0,MIN(A29,925000)-250000)*0.05+MAX(0,MIN(A29,1500000)-925000)*0.1+MAX(0,A29-1500000)*0.12))),(MAX(0,MIN(A29,250000)-125000)*0.02+MAX(0,MIN(A29,925000)-250000)*0.05+MAX(0,MIN(A29,1500000)-925000)*0.1+MAX(0,A29-1500000)*0.12)+IF(Inputs!B8="Additional / Investor",0.05*A29,0)+IF(Inputs!B9="Yes",0.02*A29,0))),IF(Inputs!B7="Scotland",((MAX(0,MIN(A29,250000)-145000)*0.02+MAX(0,MIN(A29,325000)-250000)*0.05+MAX(0,MIN(A29,750000)-325000)*0.1+MAX(0,A29-750000)*0.12)-IF(Inputs!B8="First-time buyer",(IF(A29>145000,MIN(600,0.02*(MIN(A29,175000)-145000)),0)),0)+IF(Inputs!B8="Additional / Investor",0.08*A29,0)),IF(Inputs!B7="Wales",(IF(Inputs!B8="Additional / Investor",(MIN(A29,180000)*0.05+MAX(0,MIN(A29,250000)-180000)*0.085+MAX(0,MIN(A29,400000)-250000)*0.1+MAX(0,MIN(A29,750000)-400000)*0.125+MAX(0,MIN(A29,1500000)-750000)*0.15+MAX(0,A29-1500000)*0.17),(MAX(0,MIN(A29,400000)-225000)*0.06+MAX(0,MIN(A29,750000)-400000)*0.075+MAX(0,MIN(A29,1500000)-750000)*0.1+MAX(0,A29-1500000)*0.12))),0)))))+(Inputs!B14+Inputs!B15+Inputs!B16+Inputs!B17)+(Summary!B14)+(Summary!B15)+(((((A29)*Inputs!B20)+(IF(Inputs!B24="Yes",(Summary!B14)*Inputs!B25,0))*Inputs!B26)*Inputs!B21*Inputs!B10/12)+((((A29)*Inputs!B20)+(IF(Inputs!B24="Yes",(Summary!B14)*Inputs!B25,0)))*Inputs!B22)+((((A29)*Inputs!B20)+(IF(Inputs!B24="Yes",(Summary!B14)*Inputs!B25,0)))*Inputs!B23))+(Summary!B17))) -> 68775 | C29: =IF(A29>$B$6,"","")
A30: =$B$5+(19)*$B$7 -> 195000 | B30: =IF(A30>$B$6,"",(Inputs!B6)-((A30)+(IF(Inputs!D13<>"",Inputs!D13,IF(Inputs!B7="England & N. Ireland",(IF(Inputs!B8="First-time buyer",(IF(A30<=500000,MAX(0,A30-300000)*0.05,(MAX(0,MIN(A30,250000)-125000)*0.02+MAX(0,MIN(A30,925000)-250000)*0.05+MAX(0,MIN(A30,1500000)-925000)*0.1+MAX(0,A30-1500000)*0.12))),(MAX(0,MIN(A30,250000)-125000)*0.02+MAX(0,MIN(A30,925000)-250000)*0.05+MAX(0,MIN(A30,1500000)-925000)*0.1+MAX(0,A30-1500000)*0.12)+IF(Inputs!B8="Additional / Investor",0.05*A30,0)+IF(Inputs!B9="Yes",0.02*A30,0))),IF(Inputs!B7="Scotland",((MAX(0,MIN(A30,250000)-145000)*0.02+MAX(0,MIN(A30,325000)-250000)*0.05+MAX(0,MIN(A30,750000)-325000)*0.1+MAX(0,A30-750000)*0.12)-IF(Inputs!B8="First-time buyer",(IF(A30>145000,MIN(600,0.02*(MIN(A30,175000)-145000)),0)),0)+IF(Inputs!B8="Additional / Investor",0.08*A30,0)),IF(Inputs!B7="Wales",(IF(Inputs!B8="Additional / Investor",(MIN(A30,180000)*0.05+MAX(0,MIN(A30,250000)-180000)*0.085+MAX(0,MIN(A30,400000)-250000)*0.1+MAX(0,MIN(A30,750000)-400000)*0.125+MAX(0,MIN(A30,1500000)-750000)*0.15+MAX(0,A30-1500000)*0.17),(MAX(0,MIN(A30,400000)-225000)*0.06+MAX(0,MIN(A30,750000)-400000)*0.075+MAX(0,MIN(A30,1500000)-750000)*0.1+MAX(0,A30-1500000)*0.12))),0)))))+(Inputs!B14+Inputs!B15+Inputs!B16+Inputs!B17)+(Summary!B14)+(Summary!B15)+(((((A30)*Inputs!B20)+(IF(Inputs!B24="Yes",(Summary!B14)*Inputs!B25,0))*Inputs!B26)*Inputs!B21*Inputs!B10/12)+((((A30)*Inputs!B20)+(IF(Inputs!B24="Yes",(Summary!B14)*Inputs!B25,0)))*Inputs!B22)+((((A30)*Inputs!B20)+(IF(Inputs!B24="Yes",(Summary!B14)*Inputs!B25,0)))*Inputs!B23))+(Summary!B17))) -> 63087.5 | C30: =IF(A30>$B$6,"","")
A31: =$B$5+(20)*$B$7 -> 200000 | B31: =IF(A31>$B$6,"",(Inputs!B6)-((A31)+(IF(Inputs!D13<>"",Inputs!D13,IF(Inputs!B7="England & N. Ireland",(IF(Inputs!B8="First-time buyer",(IF(A31<=500000,MAX(0,A31-300000)*0.05,(MAX(0,MIN(A31,250000)-125000)*0.02+MAX(0,MIN(A31,925000)-250000)*0.05+MAX(0,MIN(A31,1500000)-925000)*0.1+MAX(0,A31-1500000)*0.12))),(MAX(0,MIN(A31,250000)-125000)*0.02+MAX(0,MIN(A31,925000)-250000)*0.05+MAX(0,MIN(A31,1500000)-925000)*0.1+MAX(0,A31-1500000)*0.12)+IF(Inputs!B8="Additional / Investor",0.05*A31,0)+IF(Inputs!B9="Yes",0.02*A31,0))),IF(Inputs!B7="Scotland",((MAX(0,MIN(A31,250000)-145000)*0.02+MAX(0,MIN(A31,325000)-250000)*0.05+MAX(0,MIN(A31,750000)-325000)*0.1+MAX(0,A31-750000)*0.12)-IF(Inputs!B8="First-time buyer",(IF(A31>145000,MIN(600,0.02*(MIN(A31,175000)-145000)),0)),0)+IF(Inputs!B8="Additional / Investor",0.08*A31,0)),IF(Inputs!B7="Wales",(IF(Inputs!B8="Additional / Investor",(MIN(A31,180000)*0.05+MAX(0,MIN(A31,250000)-180000)*0.085+MAX(0,MIN(A31,400000)-250000)*0.1+MAX(0,MIN(A31,750000)-400000)*0.125+MAX(0,MIN(A31,1500000)-750000)*0.15+MAX(0,A31-1500000)*0.17),(MAX(0,MIN(A31,400000)-225000)*0.06+MAX(0,MIN(A31,750000)-400000)*0.075+MAX(0,MIN(A31,1500000)-750000)*0.1+MAX(0,A31-1500000)*0.12))),0)))))+(Inputs!B14+Inputs!B15+Inputs!B16+Inputs!B17)+(Summary!B14)+(Summary!B15)+(((((A31)*Inputs!B20)+(IF(Inputs!B24="Yes",(Summary!B14)*Inputs!B25,0))*Inputs!B26)*Inputs!B21*Inputs!B10/12)+((((A31)*Inputs!B20)+(IF(Inputs!B24="Yes",(Summary!B14)*Inputs!B25,0)))*Inputs!B22)+((((A31)*Inputs!B20)+(IF(Inputs!B24="Yes",(Summary!B14)*Inputs!B25,0)))*Inputs!B23))+(Summary!B17))) -> 57400 | C31: =IF(A31>$B$6,"","")
A32: =$B$5+(21)*$B$7 -> 205000 | B32: =IF(A32>$B$6,"",(Inputs!B6)-((A32)+(IF(Inputs!D13<>"",Inputs!D13,IF(Inputs!B7="England & N. Ireland",(IF(Inputs!B8="First-time buyer",(IF(A32<=500000,MAX(0,A32-300000)*0.05,(MAX(0,MIN(A32,250000)-125000)*0.02+MAX(0,MIN(A32,925000)-250000)*0.05+MAX(0,MIN(A32,1500000)-925000)*0.1+MAX(0,A32-1500000)*0.12))),(MAX(0,MIN(A32,250000)-125000)*0.02+MAX(0,MIN(A32,925000)-250000)*0.05+MAX(0,MIN(A32,1500000)-925000)*0.1+MAX(0,A32-1500000)*0.12)+IF(Inputs!B8="Additional / Investor",0.05*A32,0)+IF(Inputs!B9="Yes",0.02*A32,0))),IF(Inputs!B7="Scotland",((MAX(0,MIN(A32,250000)-145000)*0.02+MAX(0,MIN(A32,325000)-250000)*0.05+MAX(0,MIN(A32,750000)-325000)*0.1+MAX(0,A32-750000)*0.12)-IF(Inputs!B8="First-time buyer",(IF(A32>145000,MIN(600,0.02*(MIN(A32,175000)-145000)),0)),0)+IF(Inputs!B8="Additional / Investor",0.08*A32,0)),IF(Inputs!B7="Wales",(IF(Inputs!B8="Additional / Investor",(MIN(A32,180000)*0.05+MAX(0,MIN(A32,250000)-180000)*0.085+MAX(0,MIN(A32,400000)-250000)*0.1+MAX(0,MIN(A32,750000)-400000)*0.125+MAX(0,MIN(A32,1500000)-750000)*0.15+MAX(0,A32-1500000)*0.17),(MAX(0,MIN(A32,400000)-225000)*0.06+MAX(0,MIN(A32,750000)-400000)*0.075+MAX(0,MIN(A32,1500000)-750000)*0.1+MAX(0,A32-1500000)*0.12))),0)))))+(Inputs!B14+Inputs!B15+Inputs!B16+Inputs!B17)+(Summary!B14)+(Summary!B15)+(((((A32)*Inputs!B20)+(IF(Inputs!B24="Yes",(Summary!B14)*Inputs!B25,0))*Inputs!B26)*Inputs!B21*Inputs!B10/12)+((((A32)*Inputs!B20)+(IF(Inputs!B24="Yes",(Summary!B14)*Inputs!B25,0)))*Inputs!B22)+((((A32)*Inputs!B20)+(IF(Inputs!B24="Yes",(Summary!B14)*Inputs!B25,0)))*Inputs!B23))+(Summary!B17))) -> 51712.5 | C32: =IF(A32>$B$6,"","")
A33: =$B$5+(22)*$B$7 -> 210000 | B33: =IF(A33>$B$6,"",(Inputs!B6)-((A33)+(IF(Inputs!D13<>"",Inputs!D13,IF(Inputs!B7="England & N. Ireland",(IF(Inputs!B8="First-time buyer",(IF(A33<=500000,MAX(0,A33-300000)*0.05,(MAX(0,MIN(A33,250000)-125000)*0.02+MAX(0,MIN(A33,925000)-250000)*0.05+MAX(0,MIN(A33,1500000)-925000)*0.1+MAX(0,A33-1500000)*0.12))),(MAX(0,MIN(A33,250000)-125000)*0.02+MAX(0,MIN(A33,925000)-250000)*0.05+MAX(0,MIN(A33,1500000)-925000)*0.1+MAX(0,A33-1500000)*0.12)+IF(Inputs!B8="Additional / Investor",0.05*A33,0)+IF(Inputs!B9="Yes",0.02*A33,0))),IF(Inputs!B7="Scotland",((MAX(0,MIN(A33,250000)-145000)*0.02+MAX(0,MIN(A33,325000)-250000)*0.05+MAX(0,MIN(A33,750000)-325000)*0.1+MAX(0,A33-750000)*0.12)-IF(Inputs!B8="First-time buyer",(IF(A33>145000,MIN(600,0.02*(MIN(A33,175000)-145000)),0)),0)+IF(Inputs!B8="Additional / Investor",0.08*A33,0)),IF(Inputs!B7="Wales",(IF(Inputs!B8="Additional / Investor",(MIN(A33,180000)*0.05+MAX(0,MIN(A33,250000)-180000)*0.085+MAX(0,MIN(A33,400000)-250000)*0.1+MAX(0,MIN(A33,750000)-400000)*0.125+MAX(0,MIN(A33,1500000)-750000)*0.15+MAX(0,A33-1500000)*0.17),(MAX(0,MIN(A33,400000)-225000)*0.06+MAX(0,MIN(A33,750000)-400000)*0.075+MAX(0,MIN(A33,1500000)-750000)*0.1+MAX(0,A33-1500000)*0.12))),0)))))+(Inputs!B14+Inputs!B15+Inputs!B16+Inputs!B17)+(Summary!B14)+(Summary!B15)+(((((A33)*Inputs!B20)+(IF(Inputs!B24="Yes",(Summary!B14)*Inputs!B25,0))*Inputs!B26)*Inputs!B21*Inputs!B10/12)+((((A33)*Inputs!B20)+(IF(Inputs!B24="Yes",(Summary!B14)*Inputs!B25,0)))*Inputs!B22)+((((A33)*Inputs!B20)+(IF(Inputs!B24="Yes",(Summary!B14)*Inputs!B25,0)))*Inputs!B23))+(Summary!B17))) -> 46025 | C33: =IF(A33>$B$6,"","")
A34: =$B$5+(23)*$B$7 -> 215000 | B34: =IF(A34>$B$6,"",(Inputs!B6)-((A34)+(IF(Inputs!D13<>"",Inputs!D13,IF(Inputs!B7="England & N. Ireland",(IF(Inputs!B8="First-time buyer",(IF(A34<=500000,MAX(0,A34-300000)*0.05,(MAX(0,MIN(A34,250000)-125000)*0.02+MAX(0,MIN(A34,925000)-250000)*0.05+MAX(0,MIN(A34,1500000)-925000)*0.1+MAX(0,A34-1500000)*0.12))),(MAX(0,MIN(A34,250000)-125000)*0.02+MAX(0,MIN(A34,925000)-250000)*0.05+MAX(0,MIN(A34,1500000)-925000)*0.1+MAX(0,A34-1500000)*0.12)+IF(Inputs!B8="Additional / Investor",0.05*A34,0)+IF(Inputs!B9="Yes",0.02*A34,0))),IF(Inputs!B7="Scotland",((MAX(0,MIN(A34,250000)-145000)*0.02+MAX(0,MIN(A34,325000)-250000)*0.05+MAX(0,MIN(A34,750000)-325000)*0.1+MAX(0,A34-750000)*0.12)-IF(Inputs!B8="First-time buyer",(IF(A34>145000,MIN(600,0.02*(MIN(A34,175000)-145000)),0)),0)+IF(Inputs!B8="Additional / Investor",0.08*A34,0)),IF(Inputs!B7="Wales",(IF(Inputs!B8="Additional / Investor",(MIN(A34,180000)*0.05+MAX(0,MIN(A34,250000)-180000)*0.085+MAX(0,MIN(A34,400000)-250000)*0.1+MAX(0,MIN(A34,750000)-400000)*0.125+MAX(0,MIN(A34,1500000)-750000)*0.15+MAX(0,A34-1500000)*0.17),(MAX(0,MIN(A34,400000)-225000)*0.06+MAX(0,MIN(A34,750000)-400000)*0.075+MAX(0,MIN(A34,1500000)-750000)*0.1+MAX(0,A34-1500000)*0.12))),0)))))+(Inputs!B14+Inputs!B15+Inputs!B16+Inputs!B17)+(Summary!B14)+(Summary!B15)+(((((A34)*Inputs!B20)+(IF(Inputs!B24="Yes",(Summary!B14)*Inputs!B25,0))*Inputs!B26)*Inputs!B21*Inputs!B10/12)+((((A34)*Inputs!B20)+(IF(Inputs!B24="Yes",(Summary!B14)*Inputs!B25,0)))*Inputs!B22)+((((A34)*Inputs!B20)+(IF(Inputs!B24="Yes",(Summary!B14)*Inputs!B25,0)))*Inputs!B23))+(Summary!B17))) -> 40337.5 | C34: =IF(A34>$B$6,"","")
A35: =$B$5+(24)*$B$7 -> 220000 | B35: =IF(A35>$B$6,"",(Inputs!B6)-((A35)+(IF(Inputs!D13<>"",Inputs!D13,IF(Inputs!B7="England & N. Ireland",(IF(Inputs!B8="First-time buyer",(IF(A35<=500000,MAX(0,A35-300000)*0.05,(MAX(0,MIN(A35,250000)-125000)*0.02+MAX(0,MIN(A35,925000)-250000)*0.05+MAX(0,MIN(A35,1500000)-925000)*0.1+MAX(0,A35-1500000)*0.12))),(MAX(0,MIN(A35,250000)-125000)*0.02+MAX(0,MIN(A35,925000)-250000)*0.05+MAX(0,MIN(A35,1500000)-925000)*0.1+MAX(0,A35-1500000)*0.12)+IF(Inputs!B8="Additional / Investor",0.05*A35,0)+IF(Inputs!B9="Yes",0.02*A35,0))),IF(Inputs!B7="Scotland",((MAX(0,MIN(A35,250000)-145000)*0.02+MAX(0,MIN(A35,325000)-250000)*0.05+MAX(0,MIN(A35,750000)-325000)*0.1+MAX(0,A35-750000)*0.12)-IF(Inputs!B8="First-time buyer",(IF(A35>145000,MIN(600,0.02*(MIN(A35,175000)-145000)),0)),0)+IF(Inputs!B8="Additional / Investor",0.08*A35,0)),IF(Inputs!B7="Wales",(IF(Inputs!B8="Additional / Investor",(MIN(A35,180000)*0.05+MAX(0,MIN(A35,250000)-180000)*0.085+MAX(0,MIN(A35,400000)-250000)*0.1+MAX(0,MIN(A35,750000)-400000)*0.125+MAX(0,MIN(A35,1500000)-750000)*0.15+MAX(0,A35-1500000)*0.17),(MAX(0,MIN(A35,400000)-225000)*0.06+MAX(0,MIN(A35,750000)-400000)*0.075+MAX(0,MIN(A35,1500000)-750000)*0.1+MAX(0,A35-1500000)*0.12))),0)))))+(Inputs!B14+Inputs!B15+Inputs!B16+Inputs!B17)+(Summary!B14)+(Summary!B15)+(((((A35)*Inputs!B20)+(IF(Inputs!B24="Yes",(Summary!B14)*Inputs!B25,0))*Inputs!B26)*Inputs!B21*Inputs!B10/12)+((((A35)*Inputs!B20)+(IF(Inputs!B24="Yes",(Summary!B14)*Inputs!B25,0)))*Inputs!B22)+((((A35)*Inputs!B20)+(IF(Inputs!B24="Yes",(Summary!B14)*Inputs!B25,0)))*Inputs!B23))+(Summary!B17))) -> 34650 | C35: =IF(A35>$B$6,"","")
A36: =$B$5+(25)*$B$7 -> 225000 | B36: =IF(A36>$B$6,"",(Inputs!B6)-((A36)+(IF(Inputs!D13<>"",Inputs!D13,IF(Inputs!B7="England & N. Ireland",(IF(Inputs!B8="First-time buyer",(IF(A36<=500000,MAX(0,A36-300000)*0.05,(MAX(0,MIN(A36,250000)-125000)*0.02+MAX(0,MIN(A36,925000)-250000)*0.05+MAX(0,MIN(A36,1500000)-925000)*0.1+MAX(0,A36-1500000)*0.12))),(MAX(0,MIN(A36,250000)-125000)*0.02+MAX(0,MIN(A36,925000)-250000)*0.05+MAX(0,MIN(A36,1500000)-925000)*0.1+MAX(0,A36-1500000)*0.12)+IF(Inputs!B8="Additional / Investor",0.05*A36,0)+IF(Inputs!B9="Yes",0.02*A36,0))),IF(Inputs!B7="Scotland",((MAX(0,MIN(A36,250000)-145000)*0.02+MAX(0,MIN(A36,325000)-250000)*0.05+MAX(0,MIN(A36,750000)-325000)*0.1+MAX(0,A36-750000)*0.12)-IF(Inputs!B8="First-time buyer",(IF(A36>145000,MIN(600,0.02*(MIN(A36,175000)-145000)),0)),0)+IF(Inputs!B8="Additional / Investor",0.08*A36,0)),IF(Inputs!B7="Wales",(IF(Inputs!B8="Additional / Investor",(MIN(A36,180000)*0.05+MAX(0,MIN(A36,250000)-180000)*0.085+MAX(0,MIN(A36,400000)-250000)*0.1+MAX(0,MIN(A36,750000)-400000)*0.125+MAX(0,MIN(A36,1500000)-750000)*0.15+MAX(0,A36-1500000)*0.17),(MAX(0,MIN(A36,400000)-225000)*0.06+MAX(0,MIN(A36,750000)-400000)*0.075+MAX(0,MIN(A36,1500000)-750000)*0.1+MAX(0,A36-1500000)*0.12))),0)))))+(Inputs!B14+Inputs!B15+Inputs!B16+Inputs!B17)+(Summary!B14)+(Summary!B15)+(((((A36)*Inputs!B20)+(IF(Inputs!B24="Yes",(Summary!B14)*Inputs!B25,0))*Inputs!B26)*Inputs!B21*Inputs!B10/12)+((((A36)*Inputs!B20)+(IF(Inputs!B24="Yes",(Summary!B14)*Inputs!B25,0)))*Inputs!B22)+((((A36)*Inputs!B20)+(IF(Inputs!B24="Yes",(Summary!B14)*Inputs!B25,0)))*Inputs!B23))+(Summary!B17))) -> 28962.5 | C36: =IF(A36>$B$6,"","")
A37: =$B$5+(26)*$B$7 -> 230000 | B37: =IF(A37>$B$6,"",(Inputs!B6)-((A37)+(IF(Inputs!D13<>"",Inputs!D13,IF(Inputs!B7="England & N. Ireland",(IF(Inputs!B8="First-time buyer",(IF(A37<=500000,MAX(0,A37-300000)*0.05,(MAX(0,MIN(A37,250000)-125000)*0.02+MAX(0,MIN(A37,925000)-250000)*0.05+MAX(0,MIN(A37,1500000)-925000)*0.1+MAX(0,A37-1500000)*0.12))),(MAX(0,MIN(A37,250000)-125000)*0.02+MAX(0,MIN(A37,925000)-250000)*0.05+MAX(0,MIN(A37,1500000)-925000)*0.1+MAX(0,A37-1500000)*0.12)+IF(Inputs!B8="Additional / Investor",0.05*A37,0)+IF(Inputs!B9="Yes",0.02*A37,0))),IF(Inputs!B7="Scotland",((MAX(0,MIN(A37,250000)-145000)*0.02+MAX(0,MIN(A37,325000)-250000)*0.05+MAX(0,MIN(A37,750000)-325000)*0.1+MAX(0,A37-750000)*0.12)-IF(Inputs!B8="First-time buyer",(IF(A37>145000,MIN(600,0.02*(MIN(A37,175000)-145000)),0)),0)+IF(Inputs!B8="Additional / Investor",0.08*A37,0)),IF(Inputs!B7="Wales",(IF(Inputs!B8="Additional / Investor",(MIN(A37,180000)*0.05+MAX(0,MIN(A37,250000)-180000)*0.085+MAX(0,MIN(A37,400000)-250000)*0.1+MAX(0,MIN(A37,750000)-400000)*0.125+MAX(0,MIN(A37,1500000)-750000)*0.15+MAX(0,A37-1500000)*0.17),(MAX(0,MIN(A37,400000)-225000)*0.06+MAX(0,MIN(A37,750000)-400000)*0.075+MAX(0,MIN(A37,1500000)-750000)*0.1+MAX(0,A37-1500000)*0.12))),0)))))+(Inputs!B14+Inputs!B15+Inputs!B16+Inputs!B17)+(Summary!B14)+(Summary!B15)+(((((A37)*Inputs!B20)+(IF(Inputs!B24="Yes",(Summary!B14)*Inputs!B25,0))*Inputs!B26)*Inputs!B21*Inputs!B10/12)+((((A37)*Inputs!B20)+(IF(Inputs!B24="Yes",(Summary!B14)*Inputs!B25,0)))*Inputs!B22)+((((A37)*Inputs!B20)+(IF(Inputs!B24="Yes",(Summary!B14)*Inputs!B25,0)))*Inputs!B23))+(Summary!B17))) -> 23275 | C37: =IF(A37>$B$6,"","")
A38: =$B$5+(27)*$B$7 -> 235000 | B38: =IF(A38>$B$6,"",(Inputs!B6)-((A38)+(IF(Inputs!D13<>"",Inputs!D13,IF(Inputs!B7="England & N. Ireland",(IF(Inputs!B8="First-time buyer",(IF(A38<=500000,MAX(0,A38-300000)*0.05,(MAX(0,MIN(A38,250000)-125000)*0.02+MAX(0,MIN(A38,925000)-250000)*0.05+MAX(0,MIN(A38,1500000)-925000)*0.1+MAX(0,A38-1500000)*0.12))),(MAX(0,MIN(A38,250000)-125000)*0.02+MAX(0,MIN(A38,925000)-250000)*0.05+MAX(0,MIN(A38,1500000)-925000)*0.1+MAX(0,A38-1500000)*0.12)+IF(Inputs!B8="Additional / Investor",0.05*A38,0)+IF(Inputs!B9="Yes",0.02*A38,0))),IF(Inputs!B7="Scotland",((MAX(0,MIN(A38,250000)-145000)*0.02+MAX(0,MIN(A38,325000)-250000)*0.05+MAX(0,MIN(A38,750000)-325000)*0.1+MAX(0,A38-750000)*0.12)-IF(Inputs!B8="First-time buyer",(IF(A38>145000,MIN(600,0.02*(MIN(A38,175000)-145000)),0)),0)+IF(Inputs!B8="Additional / Investor",0.08*A38,0)),IF(Inputs!B7="Wales",(IF(Inputs!B8="Additional / Investor",(MIN(A38,180000)*0.05+MAX(0,MIN(A38,250000)-180000)*0.085+MAX(0,MIN(A38,400000)-250000)*0.1+MAX(0,MIN(A38,750000)-400000)*0.125+MAX(0,MIN(A38,1500000)-750000)*0.15+MAX(0,A38-1500000)*0.17),(MAX(0,MIN(A38,400000)-225000)*0.06+MAX(0,MIN(A38,750000)-400000)*0.075+MAX(0,MIN(A38,1500000)-750000)*0.1+MAX(0,A38-1500000)*0.12))),0)))))+(Inputs!B14+Inputs!B15+Inputs!B16+Inputs!B17)+(Summary!B14)+(Summary!B15)+(((((A38)*Inputs!B20)+(IF(Inputs!B24="Yes",(Summary!B14)*Inputs!B25,0))*Inputs!B26)*Inputs!B21*Inputs!B10/12)+((((A38)*Inputs!B20)+(IF(Inputs!B24="Yes",(Summary!B14)*Inputs!B25,0)))*Inputs!B22)+((((A38)*Inputs!B20)+(IF(Inputs!B24="Yes",(Summary!B14)*Inputs!B25,0)))*Inputs!B23))+(Summary!B17))) -> 17587.5 | C38: =IF(A38>$B$6,"","")
A39: =$B$5+(28)*$B$7 -> 240000 | B39: =IF(A39>$B$6,"",(Inputs!B6)-((A39)+(IF(Inputs!D13<>"",Inputs!D13,IF(Inputs!B7="England & N. Ireland",(IF(Inputs!B8="First-time buyer",(IF(A39<=500000,MAX(0,A39-300000)*0.05,(MAX(0,MIN(A39,250000)-125000)*0.02+MAX(0,MIN(A39,925000)-250000)*0.05+MAX(0,MIN(A39,1500000)-925000)*0.1+MAX(0,A39-1500000)*0.12))),(MAX(0,MIN(A39,250000)-125000)*0.02+MAX(0,MIN(A39,925000)-250000)*0.05+MAX(0,MIN(A39,1500000)-925000)*0.1+MAX(0,A39-1500000)*0.12)+IF(Inputs!B8="Additional / Investor",0.05*A39,0)+IF(Inputs!B9="Yes",0.02*A39,0))),IF(Inputs!B7="Scotland",((MAX(0,MIN(A39,250000)-145000)*0.02+MAX(0,MIN(A39,325000)-250000)*0.05+MAX(0,MIN(A39,750000)-325000)*0.1+MAX(0,A39-750000)*0.12)-IF(Inputs!B8="First-time buyer",(IF(A39>145000,MIN(600,0.02*(MIN(A39,175000)-145000)),0)),0)+IF(Inputs!B8="Additional / Investor",0.08*A39,0)),IF(Inputs!B7="Wales",(IF(Inputs!B8="Additional / Investor",(MIN(A39,180000)*0.05+MAX(0,MIN(A39,250000)-180000)*0.085+MAX(0,MIN(A39,400000)-250000)*0.1+MAX(0,MIN(A39,750000)-400000)*0.125+MAX(0,MIN(A39,1500000)-750000)*0.15+MAX(0,A39-1500000)*0.17),(MAX(0,MIN(A39,400000)-225000)*0.06+MAX(0,MIN(A39,750000)-400000)*0.075+MAX(0,MIN(A39,1500000)-750000)*0.1+MAX(0,A39-1500000)*0.12))),0)))))+(Inputs!B14+Inputs!B15+Inputs!B16+Inputs!B17)+(Summary!B14)+(Summary!B15)+(((((A39)*Inputs!B20)+(IF(Inputs!B24="Yes",(Summary!B14)*Inputs!B25,0))*Inputs!B26)*Inputs!B21*Inputs!B10/12)+((((A39)*Inputs!B20)+(IF(Inputs!B24="Yes",(Summary!B14)*Inputs!B25,0)))*Inputs!B22)+((((A39)*Inputs!B20)+(IF(Inputs!B24="Yes",(Summary!B14)*Inputs!B25,0)))*Inputs!B23))+(Summary!B17))) -> 11900 | C39: =IF(A39>$B$6,"","")
A40: =$B$5+(29)*$B$7 -> 245000 | B40: =IF(A40>$B$6,"",(Inputs!B6)-((A40)+(IF(Inputs!D13<>"",Inputs!D13,IF(Inputs!B7="England & N. Ireland",(IF(Inputs!B8="First-time buyer",(IF(A40<=500000,MAX(0,A40-300000)*0.05,(MAX(0,MIN(A40,250000)-125000)*0.02+MAX(0,MIN(A40,925000)-250000)*0.05+MAX(0,MIN(A40,1500000)-925000)*0.1+MAX(0,A40-1500000)*0.12))),(MAX(0,MIN(A40,250000)-125000)*0.02+MAX(0,MIN(A40,925000)-250000)*0.05+MAX(0,MIN(A40,1500000)-925000)*0.1+MAX(0,A40-1500000)*0.12)+IF(Inputs!B8="Additional / Investor",0.05*A40,0)+IF(Inputs!B9="Yes",0.02*A40,0))),IF(Inputs!B7="Scotland",((MAX(0,MIN(A40,250000)-145000)*0.02+MAX(0,MIN(A40,325000)-250000)*0.05+MAX(0,MIN(A40,750000)-325000)*0.1+MAX(0,A40-750000)*0.12)-IF(Inputs!B8="First-time buyer",(IF(A40>145000,MIN(600,0.02*(MIN(A40,175000)-145000)),0)),0)+IF(Inputs!B8="Additional / Investor",0.08*A40,0)),IF(Inputs!B7="Wales",(IF(Inputs!B8="Additional / Investor",(MIN(A40,180000)*0.05+MAX(0,MIN(A40,250000)-180000)*0.085+MAX(0,MIN(A40,400000)-250000)*0.1+MAX(0,MIN(A40,750000)-400000)*0.125+MAX(0,MIN(A40,1500000)-750000)*0.15+MAX(0,A40-1500000)*0.17),(MAX(0,MIN(A40,400000)-225000)*0.06+MAX(0,MIN(A40,750000)-400000)*0.075+MAX(0,MIN(A40,1500000)-750000)*0.1+MAX(0,A40-1500000)*0.12))),0)))))+(Inputs!B14+Inputs!B15+Inputs!B16+Inputs!B17)+(Summary!B14)+(Summary!B15)+(((((A40)*Inputs!B20)+(IF(Inputs!B24="Yes",(Summary!B14)*Inputs!B25,0))*Inputs!B26)*Inputs!B21*Inputs!B10/12)+((((A40)*Inputs!B20)+(IF(Inputs!B24="Yes",(Summary!B14)*Inputs!B25,0)))*Inputs!B22)+((((A40)*Inputs!B20)+(IF(Inputs!B24="Yes",(Summary!B14)*Inputs!B25,0)))*Inputs!B23))+(Summary!B17))) -> 6212.5 | C40: =IF(A40>$B$6,"","")
A41: =$B$5+(30)*$B$7 -> 250000 | B41: =IF(A41>$B$6,"",(Inputs!B6)-((A41)+(IF(Inputs!D13<>"",Inputs!D13,IF(Inputs!B7="England & N. Ireland",(IF(Inputs!B8="First-time buyer",(IF(A41<=500000,MAX(0,A41-300000)*0.05,(MAX(0,MIN(A41,250000)-125000)*0.02+MAX(0,MIN(A41,925000)-250000)*0.05+MAX(0,MIN(A41,1500000)-925000)*0.1+MAX(0,A41-1500000)*0.12))),(MAX(0,MIN(A41,250000)-125000)*0.02+MAX(0,MIN(A41,925000)-250000)*0.05+MAX(0,MIN(A41,1500000)-925000)*0.1+MAX(0,A41-1500000)*0.12)+IF(Inputs!B8="Additional / Investor",0.05*A41,0)+IF(Inputs!B9="Yes",0.02*A41,0))),IF(Inputs!B7="Scotland",((MAX(0,MIN(A41,250000)-145000)*0.02+MAX(0,MIN(A41,325000)-250000)*0.05+MAX(0,MIN(A41,750000)-325000)*0.1+MAX(0,A41-750000)*0.12)-IF(Inputs!B8="First-time buyer",(IF(A41>145000,MIN(600,0.02*(MIN(A41,175000)-145000)),0)),0)+IF(Inputs!B8="Additional / Investor",0.08*A41,0)),IF(Inputs!B7="Wales",(IF(Inputs!B8="Additional / Investor",(MIN(A41,180000)*0.05+MAX(0,MIN(A41,250000)-180000)*0.085+MAX(0,MIN(A41,400000)-250000)*0.1+MAX(0,MIN(A41,750000)-400000)*0.125+MAX(0,MIN(A41,1500000)-750000)*0.15+MAX(0,A41-1500000)*0.17),(MAX(0,MIN(A41,400000)-225000)*0.06+MAX(0,MIN(A41,750000)-400000)*0.075+MAX(0,MIN(A41,1500000)-750000)*0.1+MAX(0,A41-1500000)*0.12))),0)))))+(Inputs!B14+Inputs!B15+Inputs!B16+Inputs!B17)+(Summary!B14)+(Summary!B15)+(((((A41)*Inputs!B20)+(IF(Inputs!B24="Yes",(Summary!B14)*Inputs!B25,0))*Inputs!B26)*Inputs!B21*Inputs!B10/12)+((((A41)*Inputs!B20)+(IF(Inputs!B24="Yes",(Summary!B14)*Inputs!B25,0)))*Inputs!B22)+((((A41)*Inputs!B20)+(IF(Inputs!B24="Yes",(Summary!B14)*Inputs!B25,0)))*Inputs!B23))+(Summary!B17))) -> 525 | C41: =IF(A41>$B$6,"","")
A42: =$B$5+(31)*$B$7 -> 255000 | B42: =IF(A42>$B$6,"",(Inputs!B6)-((A42)+(IF(Inputs!D13<>"",Inputs!D13,IF(Inputs!B7="England & N. Ireland",(IF(Inputs!B8="First-time buyer",(IF(A42<=500000,MAX(0,A42-300000)*0.05,(MAX(0,MIN(A42,250000)-125000)*0.02+MAX(0,MIN(A42,925000)-250000)*0.05+MAX(0,MIN(A42,1500000)-925000)*0.1+MAX(0,A42-1500000)*0.12))),(MAX(0,MIN(A42,250000)-125000)*0.02+MAX(0,MIN(A42,925000)-250000)*0.05+MAX(0,MIN(A42,1500000)-925000)*0.1+MAX(0,A42-1500000)*0.12)+IF(Inputs!B8="Additional / Investor",0.05*A42,0)+IF(Inputs!B9="Yes",0.02*A42,0))),IF(Inputs!B7="Scotland",((MAX(0,MIN(A42,250000)-145000)*0.02+MAX(0,MIN(A42,325000)-250000)*0.05+MAX(0,MIN(A42,750000)-325000)*0.1+MAX(0,A42-750000)*0.12)-IF(Inputs!B8="First-time buyer",(IF(A42>145000,MIN(600,0.02*(MIN(A42,175000)-145000)),0)),0)+IF(Inputs!B8="Additional / Investor",0.08*A42,0)),IF(Inputs!B7="Wales",(IF(Inputs!B8="Additional / Investor",(MIN(A42,180000)*0.05+MAX(0,MIN(A42,250000)-180000)*0.085+MAX(0,MIN(A42,400000)-250000)*0.1+MAX(0,MIN(A42,750000)-400000)*0.125+MAX(0,MIN(A42,1500000)-750000)*0.15+MAX(0,A42-1500000)*0.17),(MAX(0,MIN(A42,400000)-225000)*0.06+MAX(0,MIN(A42,750000)-400000)*0.075+MAX(0,MIN(A42,1500000)-750000)*0.1+MAX(0,A42-1500000)*0.12))),0)))))+(Inputs!B14+Inputs!B15+Inputs!B16+Inputs!B17)+(Summary!B14)+(Summary!B15)+(((((A42)*Inputs!B20)+(IF(Inputs!B24="Yes",(Summary!B14)*Inputs!B25,0))*Inputs!B26)*Inputs!B21*Inputs!B10/12)+((((A42)*Inputs!B20)+(IF(Inputs!B24="Yes",(Summary!B14)*Inputs!B25,0)))*Inputs!B22)+((((A42)*Inputs!B20)+(IF(Inputs!B24="Yes",(Summary!B14)*Inputs!B25,0)))*Inputs!B23))+(Summary!B17))) -> -5312.5 | C42: =IF(A42>$B$6,"","")
A43: =$B$5+(32)*$B$7 -> 260000 | B43: =IF(A43>$B$6,"",(Inputs!B6)-((A43)+(IF(Inputs!D13<>"",Inputs!D13,IF(Inputs!B7="England & N. Ireland",(IF(Inputs!B8="First-time buyer",(IF(A43<=500000,MAX(0,A43-300000)*0.05,(MAX(0,MIN(A43,250000)-125000)*0.02+MAX(0,MIN(A43,925000)-250000)*0.05+MAX(0,MIN(A43,1500000)-925000)*0.1+MAX(0,A43-1500000)*0.12))),(MAX(0,MIN(A43,250000)-125000)*0.02+MAX(0,MIN(A43,925000)-250000)*0.05+MAX(0,MIN(A43,1500000)-925000)*0.1+MAX(0,A43-1500000)*0.12)+IF(Inputs!B8="Additional / Investor",0.05*A43,0)+IF(Inputs!B9="Yes",0.02*A43,0))),IF(Inputs!B7="Scotland",((MAX(0,MIN(A43,250000)-145000)*0.02+MAX(0,MIN(A43,325000)-250000)*0.05+MAX(0,MIN(A43,750000)-325000)*0.1+MAX(0,A43-750000)*0.12)-IF(Inputs!B8="First-time buyer",(IF(A43>145000,MIN(600,0.02*(MIN(A43,175000)-145000)),0)),0)+IF(Inputs!B8="Additional / Investor",0.08*A43,0)),IF(Inputs!B7="Wales",(IF(Inputs!B8="Additional / Investor",(MIN(A43,180000)*0.05+MAX(0,MIN(A43,250000)-180000)*0.085+MAX(0,MIN(A43,400000)-250000)*0.1+MAX(0,MIN(A43,750000)-400000)*0.125+MAX(0,MIN(A43,1500000)-750000)*0.15+MAX(0,A43-1500000)*0.17),(MAX(0,MIN(A43,400000)-225000)*0.06+MAX(0,MIN(A43,750000)-400000)*0.075+MAX(0,MIN(A43,1500000)-750000)*0.1+MAX(0,A43-1500000)*0.12))),0)))))+(Inputs!B14+Inputs!B15+Inputs!B16+Inputs!B17)+(Summary!B14)+(Summary!B15)+(((((A43)*Inputs!B20)+(IF(Inputs!B24="Yes",(Summary!B14)*Inputs!B25,0))*Inputs!B26)*Inputs!B21*Inputs!B10/12)+((((A43)*Inputs!B20)+(IF(Inputs!B24="Yes",(Summary!B14)*Inputs!B25,0)))*Inputs!B22)+((((A43)*Inputs!B20)+(IF(Inputs!B24="Yes",(Summary!B14)*Inputs!B25,0)))*Inputs!B23))+(Summary!B17))) -> -11150 | C43: =IF(A43>$B$6,"","")
A44: =$B$5+(33)*$B$7 -> 265000 | B44: =IF(A44>$B$6,"",(Inputs!B6)-((A44)+(IF(Inputs!D13<>"",Inputs!D13,IF(Inputs!B7="England & N. Ireland",(IF(Inputs!B8="First-time buyer",(IF(A44<=500000,MAX(0,A44-300000)*0.05,(MAX(0,MIN(A44,250000)-125000)*0.02+MAX(0,MIN(A44,925000)-250000)*0.05+MAX(0,MIN(A44,1500000)-925000)*0.1+MAX(0,A44-1500000)*0.12))),(MAX(0,MIN(A44,250000)-125000)*0.02+MAX(0,MIN(A44,925000)-250000)*0.05+MAX(0,MIN(A44,1500000)-925000)*0.1+MAX(0,A44-1500000)*0.12)+IF(Inputs!B8="Additional / Investor",0.05*A44,0)+IF(Inputs!B9="Yes",0.02*A44,0))),IF(Inputs!B7="Scotland",((MAX(0,MIN(A44,250000)-145000)*0.02+MAX(0,MIN(A44,325000)-250000)*0.05+MAX(0,MIN(A44,750000)-325000)*0.1+MAX(0,A44-750000)*0.12)-IF(Inputs!B8="First-time buyer",(IF(A44>145000,MIN(600,0.02*(MIN(A44,175000)-145000)),0)),0)+IF(Inputs!B8="Additional / Investor",0.08*A44,0)),IF(Inputs!B7="Wales",(IF(Inputs!B8="Additional / Investor",(MIN(A44,180000)*0.05+MAX(0,MIN(A44,250000)-180000)*0.085+MAX(0,MIN(A44,400000)-250000)*0.1+MAX(0,MIN(A44,750000)-400000)*0.125+MAX(0,MIN(A44,1500000)-750000)*0.15+MAX(0,A44-1500000)*0.17),(MAX(0,MIN(A44,400000)-225000)*0.06+MAX(0,MIN(A44,750000)-400000)*0.075+MAX(0,MIN(A44,1500000)-750000)*0.1+MAX(0,A44-1500000)*0.12))),0)))))+(Inputs!B14+Inputs!B15+Inputs!B16+Inputs!B17)+(Summary!B14)+(Summary!B15)+(((((A44)*Inputs!B20)+(IF(Inputs!B24="Yes",(Summary!B14)*Inputs!B25,0))*Inputs!B26)*Inputs!B21*Inputs!B10/12)+((((A44)*Inputs!B20)+(IF(Inputs!B24="Yes",(Summary!B14)*Inputs!B25,0)))*Inputs!B22)+((((A44)*Inputs!B20)+(IF(Inputs!B24="Yes",(Summary!B14)*Inputs!B25,0)))*Inputs!B23))+(Summary!B17))) -> -16987.5 | C44: =IF(A44>$B$6,"","")
A45: =$B$5+(34)*$B$7 -> 270000 | B45: =IF(A45>$B$6,"",(Inputs!B6)-((A45)+(IF(Inputs!D13<>"",Inputs!D13,IF(Inputs!B7="England & N. Ireland",(IF(Inputs!B8="First-time buyer",(IF(A45<=500000,MAX(0,A45-300000)*0.05,(MAX(0,MIN(A45,250000)-125000)*0.02+MAX(0,MIN(A45,925000)-250000)*0.05+MAX(0,MIN(A45,1500000)-925000)*0.1+MAX(0,A45-1500000)*0.12))),(MAX(0,MIN(A45,250000)-125000)*0.02+MAX(0,MIN(A45,925000)-250000)*0.05+MAX(0,MIN(A45,1500000)-925000)*0.1+MAX(0,A45-1500000)*0.12)+IF(Inputs!B8="Additional / Investor",0.05*A45,0)+IF(Inputs!B9="Yes",0.02*A45,0))),IF(Inputs!B7="Scotland",((MAX(0,MIN(A45,250000)-145000)*0.02+MAX(0,MIN(A45,325000)-250000)*0.05+MAX(0,MIN(A45,750000)-325000)*0.1+MAX(0,A45-750000)*0.12)-IF(Inputs!B8="First-time buyer",(IF(A45>145000,MIN(600,0.02*(MIN(A45,175000)-145000)),0)),0)+IF(Inputs!B8="Additional / Investor",0.08*A45,0)),IF(Inputs!B7="Wales",(IF(Inputs!B8="Additional / Investor",(MIN(A45,180000)*0.05+MAX(0,MIN(A45,250000)-180000)*0.085+MAX(0,MIN(A45,400000)-250000)*0.1+MAX(0,MIN(A45,750000)-400000)*0.125+MAX(0,MIN(A45,1500000)-750000)*0.15+MAX(0,A45-1500000)*0.17),(MAX(0,MIN(A45,400000)-225000)*0.06+MAX(0,MIN(A45,750000)-400000)*0.075+MAX(0,MIN(A45,1500000)-750000)*0.1+MAX(0,A45-1500000)*0.12))),0)))))+(Inputs!B14+Inputs!B15+Inputs!B16+Inputs!B17)+(Summary!B14)+(Summary!B15)+(((((A45)*Inputs!B20)+(IF(Inputs!B24="Yes",(Summary!B14)*Inputs!B25,0))*Inputs!B26)*Inputs!B21*Inputs!B10/12)+((((A45)*Inputs!B20)+(IF(Inputs!B24="Yes",(Summary!B14)*Inputs!B25,0)))*Inputs!B22)+((((A45)*Inputs!B20)+(IF(Inputs!B24="Yes",(Summary!B14)*Inputs!B25,0)))*Inputs!B23))+(Summary!B17))) -> -22825 | C45: =IF(A45>$B$6,"","")
A46: =$B$5+(35)*$B$7 -> 275000 | B46: =IF(A46>$B$6,"",(Inputs!B6)-((A46)+(IF(Inputs!D13<>"",Inputs!D13,IF(Inputs!B7="England & N. Ireland",(IF(Inputs!B8="First-time buyer",(IF(A46<=500000,MAX(0,A46-300000)*0.05,(MAX(0,MIN(A46,250000)-125000)*0.02+MAX(0,MIN(A46,925000)-250000)*0.05+MAX(0,MIN(A46,1500000)-925000)*0.1+MAX(0,A46-1500000)*0.12))),(MAX(0,MIN(A46,250000)-125000)*0.02+MAX(0,MIN(A46,925000)-250000)*0.05+MAX(0,MIN(A46,1500000)-925000)*0.1+MAX(0,A46-1500000)*0.12)+IF(Inputs!B8="Additional / Investor",0.05*A46,0)+IF(Inputs!B9="Yes",0.02*A46,0))),IF(Inputs!B7="Scotland",((MAX(0,MIN(A46,250000)-145000)*0.02+MAX(0,MIN(A46,325000)-250000)*0.05+MAX(0,MIN(A46,750000)-325000)*0.1+MAX(0,A46-750000)*0.12)-IF(Inputs!B8="First-time buyer",(IF(A46>145000,MIN(600,0.02*(MIN(A46,175000)-145000)),0)),0)+IF(Inputs!B8="Additional / Investor",0.08*A46,0)),IF(Inputs!B7="Wales",(IF(Inputs!B8="Additional / Investor",(MIN(A46,180000)*0.05+MAX(0,MIN(A46,250000)-180000)*0.085+MAX(0,MIN(A46,400000)-250000)*0.1+MAX(0,MIN(A46,750000)-400000)*0.125+MAX(0,MIN(A46,1500000)-750000)*0.15+MAX(0,A46-1500000)*0.17),(MAX(0,MIN(A46,400000)-225000)*0.06+MAX(0,MIN(A46,750000)-400000)*0.075+MAX(0,MIN(A46,1500000)-750000)*0.1+MAX(0,A46-1500000)*0.12))),0)))))+(Inputs!B14+Inputs!B15+Inputs!B16+Inputs!B17)+(Summary!B14)+(Summary!B15)+(((((A46)*Inputs!B20)+(IF(Inputs!B24="Yes",(Summary!B14)*Inputs!B25,0))*Inputs!B26)*Inputs!B21*Inputs!B10/12)+((((A46)*Inputs!B20)+(IF(Inputs!B24="Yes",(Summary!B14)*Inputs!B25,0)))*Inputs!B22)+((((A46)*Inputs!B20)+(IF(Inputs!B24="Yes",(Summary!B14)*Inputs!B25,0)))*Inputs!B23))+(Summary!B17))) -> -28662.5 | C46: =IF(A46>$B$6,"","")
A47: =$B$5+(36)*$B$7 -> 280000 | B47: =IF(A47>$B$6,"",(Inputs!B6)-((A47)+(IF(Inputs!D13<>"",Inputs!D13,IF(Inputs!B7="England & N. Ireland",(IF(Inputs!B8="First-time buyer",(IF(A47<=500000,MAX(0,A47-300000)*0.05,(MAX(0,MIN(A47,250000)-125000)*0.02+MAX(0,MIN(A47,925000)-250000)*0.05+MAX(0,MIN(A47,1500000)-925000)*0.1+MAX(0,A47-1500000)*0.12))),(MAX(0,MIN(A47,250000)-125000)*0.02+MAX(0,MIN(A47,925000)-250000)*0.05+MAX(0,MIN(A47,1500000)-925000)*0.1+MAX(0,A47-1500000)*0.12)+IF(Inputs!B8="Additional / Investor",0.05*A47,0)+IF(Inputs!B9="Yes",0.02*A47,0))),IF(Inputs!B7="Scotland",((MAX(0,MIN(A47,250000)-145000)*0.02+MAX(0,MIN(A47,325000)-250000)*0.05+MAX(0,MIN(A47,750000)-325000)*0.1+MAX(0,A47-750000)*0.12)-IF(Inputs!B8="First-time buyer",(IF(A47>145000,MIN(600,0.02*(MIN(A47,175000)-145000)),0)),0)+IF(Inputs!B8="Additional / Investor",0.08*A47,0)),IF(Inputs!B7="Wales",(IF(Inputs!B8="Additional / Investor",(MIN(A47,180000)*0.05+MAX(0,MIN(A47,250000)-180000)*0.085+MAX(0,MIN(A47,400000)-250000)*0.1+MAX(0,MIN(A47,750000)-400000)*0.125+MAX(0,MIN(A47,1500000)-750000)*0.15+MAX(0,A47-1500000)*0.17),(MAX(0,MIN(A47,400000)-225000)*0.06+MAX(0,MIN(A47,750000)-400000)*0.075+MAX(0,MIN(A47,1500000)-750000)*0.1+MAX(0,A47-1500000)*0.12))),0)))))+(Inputs!B14+Inputs!B15+Inputs!B16+Inputs!B17)+(Summary!B14)+(Summary!B15)+(((((A47)*Inputs!B20)+(IF(Inputs!B24="Yes",(Summary!B14)*Inputs!B25,0))*Inputs!B26)*Inputs!B21*Inputs!B10/12)+((((A47)*Inputs!B20)+(IF(Inputs!B24="Yes",(Summary!B14)*Inputs!B25,0)))*Inputs!B22)+((((A47)*Inputs!B20)+(IF(Inputs!B24="Yes",(Summary!B14)*Inputs!B25,0)))*Inputs!B23))+(Summary!B17))) -> -34500 | C47: =IF(A47>$B$6,"","")
A48: =$B$5+(37)*$B$7 -> 285000 | B48: =IF(A48>$B$6,"",(Inputs!B6)-((A48)+(IF(Inputs!D13<>"",Inputs!D13,IF(Inputs!B7="England & N. Ireland",(IF(Inputs!B8="First-time buyer",(IF(A48<=500000,MAX(0,A48-300000)*0.05,(MAX(0,MIN(A48,250000)-125000)*0.02+MAX(0,MIN(A48,925000)-250000)*0.05+MAX(0,MIN(A48,1500000)-925000)*0.1+MAX(0,A48-1500000)*0.12))),(MAX(0,MIN(A48,250000)-125000)*0.02+MAX(0,MIN(A48,925000)-250000)*0.05+MAX(0,MIN(A48,1500000)-925000)*0.1+MAX(0,A48-1500000)*0.12)+IF(Inputs!B8="Additional / Investor",0.05*A48,0)+IF(Inputs!B9="Yes",0.02*A48,0))),IF(Inputs!B7="Scotland",((MAX(0,MIN(A48,250000)-145000)*0.02+MAX(0,MIN(A48,325000)-250000)*0.05+MAX(0,MIN(A48,750000)-325000)*0.1+MAX(0,A48-750000)*0.12)-IF(Inputs!B8="First-time buyer",(IF(A48>145000,MIN(600,0.02*(MIN(A48,175000)-145000)),0)),0)+IF(Inputs!B8="Additional / Investor",0.08*A48,0)),IF(Inputs!B7="Wales",(IF(Inputs!B8="Additional / Investor",(MIN(A48,180000)*0.05+MAX(0,MIN(A48,250000)-180000)*0.085+MAX(0,MIN(A48,400000)-250000)*0.1+MAX(0,MIN(A48,750000)-400000)*0.125+MAX(0,MIN(A48,1500000)-750000)*0.15+MAX(0,A48-1500000)*0.17),(MAX(0,MIN(A48,400000)-225000)*0.06+MAX(0,MIN(A48,750000)-400000)*0.075+MAX(0,MIN(A48,1500000)-750000)*0.1+MAX(0,A48-1500000)*0.12))),0)))))+(Inputs!B14+Inputs!B15+Inputs!B16+Inputs!B17)+(Summary!B14)+(Summary!B15)+(((((A48)*Inputs!B20)+(IF(Inputs!B24="Yes",(Summary!B14)*Inputs!B25,0))*Inputs!B26)*Inputs!B21*Inputs!B10/12)+((((A48)*Inputs!B20)+(IF(Inputs!B24="Yes",(Summary!B14)*Inputs!B25,0)))*Inputs!B22)+((((A48)*Inputs!B20)+(IF(Inputs!B24="Yes",(Summary!B14)*Inputs!B25,0)))*Inputs!B23))+(Summary!B17))) -> -40337.5 | C48: =IF(A48>$B$6,"","")
A49: =$B$5+(38)*$B$7 -> 290000 | B49: =IF(A49>$B$6,"",(Inputs!B6)-((A49)+(IF(Inputs!D13<>"",Inputs!D13,IF(Inputs!B7="England & N. Ireland",(IF(Inputs!B8="First-time buyer",(IF(A49<=500000,MAX(0,A49-300000)*0.05,(MAX(0,MIN(A49,250000)-125000)*0.02+MAX(0,MIN(A49,925000)-250000)*0.05+MAX(0,MIN(A49,1500000)-925000)*0.1+MAX(0,A49-1500000)*0.12))),(MAX(0,MIN(A49,250000)-125000)*0.02+MAX(0,MIN(A49,925000)-250000)*0.05+MAX(0,MIN(A49,1500000)-925000)*0.1+MAX(0,A49-1500000)*0.12)+IF(Inputs!B8="Additional / Investor",0.05*A49,0)+IF(Inputs!B9="Yes",0.02*A49,0))),IF(Inputs!B7="Scotland",((MAX(0,MIN(A49,250000)-145000)*0.02+MAX(0,MIN(A49,325000)-250000)*0.05+MAX(0,MIN(A49,750000)-325000)*0.1+MAX(0,A49-750000)*0.12)-IF(Inputs!B8="First-time buyer",(IF(A49>145000,MIN(600,0.02*(MIN(A49,175000)-145000)),0)),0)+IF(Inputs!B8="Additional / Investor",0.08*A49,0)),IF(Inputs!B7="Wales",(IF(Inputs!B8="Additional / Investor",(MIN(A49,180000)*0.05+MAX(0,MIN(A49,250000)-180000)*0.085+MAX(0,MIN(A49,400000)-250000)*0.1+MAX(0,MIN(A49,750000)-400000)*0.125+MAX(0,MIN(A49,1500000)-750000)*0.15+MAX(0,A49-1500000)*0.17),(MAX(0,MIN(A49,400000)-225000)*0.06+MAX(0,MIN(A49,750000)-400000)*0.075+MAX(0,MIN(A49,1500000)-750000)*0.1+MAX(0,A49-1500000)*0.12))),0)))))+(Inputs!B14+Inputs!B15+Inputs!B16+Inputs!B17)+(Summary!B14)+(Summary!B15)+(((((A49)*Inputs!B20)+(IF(Inputs!B24="Yes",(Summary!B14)*Inputs!B25,0))*Inputs!B26)*Inputs!B21*Inputs!B10/12)+((((A49)*Inputs!B20)+(IF(Inputs!B24="Yes",(Summary!B14)*Inputs!B25,0)))*Inputs!B22)+((((A49)*Inputs!B20)+(IF(Inputs!B24="Yes",(Summary!B14)*Inputs!B25,0)))*Inputs!B23))+(Summary!B17))) -> -46175 | C49: =IF(A49>$B$6,"","")
A50: =$B$5+(39)*$B$7 -> 295000 | B50: =IF(A50>$B$6,"",(Inputs!B6)-((A50)+(IF(Inputs!D13<>"",Inputs!D13,IF(Inputs!B7="England & N. Ireland",(IF(Inputs!B8="First-time buyer",(IF(A50<=500000,MAX(0,A50-300000)*0.05,(MAX(0,MIN(A50,250000)-125000)*0.02+MAX(0,MIN(A50,925000)-250000)*0.05+MAX(0,MIN(A50,1500000)-925000)*0.1+MAX(0,A50-1500000)*0.12))),(MAX(0,MIN(A50,250000)-125000)*0.02+MAX(0,MIN(A50,925000)-250000)*0.05+MAX(0,MIN(A50,1500000)-925000)*0.1+MAX(0,A50-1500000)*0.12)+IF(Inputs!B8="Additional / Investor",0.05*A50,0)+IF(Inputs!B9="Yes",0.02*A50,0))),IF(Inputs!B7="Scotland",((MAX(0,MIN(A50,250000)-145000)*0.02+MAX(0,MIN(A50,325000)-250000)*0.05+MAX(0,MIN(A50,750000)-325000)*0.1+MAX(0,A50-750000)*0.12)-IF(Inputs!B8="First-time buyer",(IF(A50>145000,MIN(600,0.02*(MIN(A50,175000)-145000)),0)),0)+IF(Inputs!B8="Additional / Investor",0.08*A50,0)),IF(Inputs!B7="Wales",(IF(Inputs!B8="Additional / Investor",(MIN(A50,180000)*0.05+MAX(0,MIN(A50,250000)-180000)*0.085+MAX(0,MIN(A50,400000)-250000)*0.1+MAX(0,MIN(A50,750000)-400000)*0.125+MAX(0,MIN(A50,1500000)-750000)*0.15+MAX(0,A50-1500000)*0.17),(MAX(0,MIN(A50,400000)-225000)*0.06+MAX(0,MIN(A50,750000)-400000)*0.075+MAX(0,MIN(A50,1500000)-750000)*0.1+MAX(0,A50-1500000)*0.12))),0)))))+(Inputs!B14+Inputs!B15+Inputs!B16+Inputs!B17)+(Summary!B14)+(Summary!B15)+(((((A50)*Inputs!B20)+(IF(Inputs!B24="Yes",(Summary!B14)*Inputs!B25,0))*Inputs!B26)*Inputs!B21*Inputs!B10/12)+((((A50)*Inputs!B20)+(IF(Inputs!B24="Yes",(Summary!B14)*Inputs!B25,0)))*Inputs!B22)+((((A50)*Inputs!B20)+(IF(Inputs!B24="Yes",(Summary!B14)*Inputs!B25,0)))*Inputs!B23))+(Summary!B17))) -> -52012.5 | C50: =IF(A50>$B$6,"","")
A51: =$B$5+(40)*$B$7 -> 300000 | B51: =IF(A51>$B$6,"",(Inputs!B6)-((A51)+(IF(Inputs!D13<>"",Inputs!D13,IF(Inputs!B7="England & N. Ireland",(IF(Inputs!B8="First-time buyer",(IF(A51<=500000,MAX(0,A51-300000)*0.05,(MAX(0,MIN(A51,250000)-125000)*0.02+MAX(0,MIN(A51,925000)-250000)*0.05+MAX(0,MIN(A51,1500000)-925000)*0.1+MAX(0,A51-1500000)*0.12))),(MAX(0,MIN(A51,250000)-125000)*0.02+MAX(0,MIN(A51,925000)-250000)*0.05+MAX(0,MIN(A51,1500000)-925000)*0.1+MAX(0,A51-1500000)*0.12)+IF(Inputs!B8="Additional / Investor",0.05*A51,0)+IF(Inputs!B9="Yes",0.02*A51,0))),IF(Inputs!B7="Scotland",((MAX(0,MIN(A51,250000)-145000)*0.02+MAX(0,MIN(A51,325000)-250000)*0.05+MAX(0,MIN(A51,750000)-325000)*0.1+MAX(0,A51-750000)*0.12)-IF(Inputs!B8="First-time buyer",(IF(A51>145000,MIN(600,0.02*(MIN(A51,175000)-145000)),0)),0)+IF(Inputs!B8="Additional / Investor",0.08*A51,0)),IF(Inputs!B7="Wales",(IF(Inputs!B8="Additional / Investor",(MIN(A51,180000)*0.05+MAX(0,MIN(A51,250000)-180000)*0.085+MAX(0,MIN(A51,400000)-250000)*0.1+MAX(0,MIN(A51,750000)-400000)*0.125+MAX(0,MIN(A51,1500000)-750000)*0.15+MAX(0,A51-1500000)*0.17),(MAX(0,MIN(A51,400000)-225000)*0.06+MAX(0,MIN(A51,750000)-400000)*0.075+MAX(0,MIN(A51,1500000)-750000)*0.1+MAX(0,A51-1500000)*0.12))),0)))))+(Inputs!B14+Inputs!B15+Inputs!B16+Inputs!B17)+(Summary!B14)+(Summary!B15)+(((((A51)*Inputs!B20)+(IF(Inputs!B24="Yes",(Summary!B14)*Inputs!B25,0))*Inputs!B26)*Inputs!B21*Inputs!B10/12)+((((A51)*Inputs!B20)+(IF(Inputs!B24="Yes",(Summary!B14)*Inputs!B25,0)))*Inputs!B22)+((((A51)*Inputs!B20)+(IF(Inputs!B24="Yes",(Summary!B14)*Inputs!B25,0)))*Inputs!B23))+(Summary!B17))) -> -57850 | C51: =IF(A51>$B$6,"","")
A52: =$B$5+(41)*$B$7 -> 305000 | B52: =IF(A52>$B$6,"",(Inputs!B6)-((A52)+(IF(Inputs!D13<>"",Inputs!D13,IF(Inputs!B7="England & N. Ireland",(IF(Inputs!B8="First-time buyer",(IF(A52<=500000,MAX(0,A52-300000)*0.05,(MAX(0,MIN(A52,250000)-125000)*0.02+MAX(0,MIN(A52,925000)-250000)*0.05+MAX(0,MIN(A52,1500000)-925000)*0.1+MAX(0,A52-1500000)*0.12))),(MAX(0,MIN(A52,250000)-125000)*0.02+MAX(0,MIN(A52,925000)-250000)*0.05+MAX(0,MIN(A52,1500000)-925000)*0.1+MAX(0,A52-1500000)*0.12)+IF(Inputs!B8="Additional / Investor",0.05*A52,0)+IF(Inputs!B9="Yes",0.02*A52,0))),IF(Inputs!B7="Scotland",((MAX(0,MIN(A52,250000)-145000)*0.02+MAX(0,MIN(A52,325000)-250000)*0.05+MAX(0,MIN(A52,750000)-325000)*0.1+MAX(0,A52-750000)*0.12)-IF(Inputs!B8="First-time buyer",(IF(A52>145000,MIN(600,0.02*(MIN(A52,175000)-145000)),0)),0)+IF(Inputs!B8="Additional / Investor",0.08*A52,0)),IF(Inputs!B7="Wales",(IF(Inputs!B8="Additional / Investor",(MIN(A52,180000)*0.05+MAX(0,MIN(A52,250000)-180000)*0.085+MAX(0,MIN(A52,400000)-250000)*0.1+MAX(0,MIN(A52,750000)-400000)*0.125+MAX(0,MIN(A52,1500000)-750000)*0.15+MAX(0,A52-1500000)*0.17),(MAX(0,MIN(A52,400000)-225000)*0.06+MAX(0,MIN(A52,750000)-400000)*0.075+MAX(0,MIN(A52,1500000)-750000)*0.1+MAX(0,A52-1500000)*0.12))),0)))))+(Inputs!B14+Inputs!B15+Inputs!B16+Inputs!B17)+(Summary!B14)+(Summary!B15)+(((((A52)*Inputs!B20)+(IF(Inputs!B24="Yes",(Summary!B14)*Inputs!B25,0))*Inputs!B26)*Inputs!B21*Inputs!B10/12)+((((A52)*Inputs!B20)+(IF(Inputs!B24="Yes",(Summary!B14)*Inputs!B25,0)))*Inputs!B22)+((((A52)*Inputs!B20)+(IF(Inputs!B24="Yes",(Summary!B14)*Inputs!B25,0)))*Inputs!B23))+(Summary!B17))) -> -63687.5 | C52: =IF(A52>$B$6,"","")
A53: =$B$5+(42)*$B$7 -> 310000 | B53: =IF(A53>$B$6,"",(Inputs!B6)-((A53)+(IF(Inputs!D13<>"",Inputs!D13,IF(Inputs!B7="England & N. Ireland",(IF(Inputs!B8="First-time buyer",(IF(A53<=500000,MAX(0,A53-300000)*0.05,(MAX(0,MIN(A53,250000)-125000)*0.02+MAX(0,MIN(A53,925000)-250000)*0.05+MAX(0,MIN(A53,1500000)-925000)*0.1+MAX(0,A53-1500000)*0.12))),(MAX(0,MIN(A53,250000)-125000)*0.02+MAX(0,MIN(A53,925000)-250000)*0.05+MAX(0,MIN(A53,1500000)-925000)*0.1+MAX(0,A53-1500000)*0.12)+IF(Inputs!B8="Additional / Investor",0.05*A53,0)+IF(Inputs!B9="Yes",0.02*A53,0))),IF(Inputs!B7="Scotland",((MAX(0,MIN(A53,250000)-145000)*0.02+MAX(0,MIN(A53,325000)-250000)*0.05+MAX(0,MIN(A53,750000)-325000)*0.1+MAX(0,A53-750000)*0.12)-IF(Inputs!B8="First-time buyer",(IF(A53>145000,MIN(600,0.02*(MIN(A53,175000)-145000)),0)),0)+IF(Inputs!B8="Additional / Investor",0.08*A53,0)),IF(Inputs!B7="Wales",(IF(Inputs!B8="Additional / Investor",(MIN(A53,180000)*0.05+MAX(0,MIN(A53,250000)-180000)*0.085+MAX(0,MIN(A53,400000)-250000)*0.1+MAX(0,MIN(A53,750000)-400000)*0.125+MAX(0,MIN(A53,1500000)-750000)*0.15+MAX(0,A53-1500000)*0.17),(MAX(0,MIN(A53,400000)-225000)*0.06+MAX(0,MIN(A53,750000)-400000)*0.075+MAX(0,MIN(A53,1500000)-750000)*0.1+MAX(0,A53-1500000)*0.12))),0)))))+(Inputs!B14+Inputs!B15+Inputs!B16+Inputs!B17)+(Summary!B14)+(Summary!B15)+(((((A53)*Inputs!B20)+(IF(Inputs!B24="Yes",(Summary!B14)*Inputs!B25,0))*Inputs!B26)*Inputs!B21*Inputs!B10/12)+((((A53)*Inputs!B20)+(IF(Inputs!B24="Yes",(Summary!B14)*Inputs!B25,0)))*Inputs!B22)+((((A53)*Inputs!B20)+(IF(Inputs!B24="Yes",(Summary!B14)*Inputs!B25,0)))*Inputs!B23))+(Summary!B17))) -> -69525 | C53: =IF(A53>$B$6,"","")
A54: =$B$5+(43)*$B$7 -> 315000 | B54: =IF(A54>$B$6,"",(Inputs!B6)-((A54)+(IF(Inputs!D13<>"",Inputs!D13,IF(Inputs!B7="England & N. Ireland",(IF(Inputs!B8="First-time buyer",(IF(A54<=500000,MAX(0,A54-300000)*0.05,(MAX(0,MIN(A54,250000)-125000)*0.02+MAX(0,MIN(A54,925000)-250000)*0.05+MAX(0,MIN(A54,1500000)-925000)*0.1+MAX(0,A54-1500000)*0.12))),(MAX(0,MIN(A54,250000)-125000)*0.02+MAX(0,MIN(A54,925000)-250000)*0.05+MAX(0,MIN(A54,1500000)-925000)*0.1+MAX(0,A54-1500000)*0.12)+IF(Inputs!B8="Additional / Investor",0.05*A54,0)+IF(Inputs!B9="Yes",0.02*A54,0))),IF(Inputs!B7="Scotland",((MAX(0,MIN(A54,250000)-145000)*0.02+MAX(0,MIN(A54,325000)-250000)*0.05+MAX(0,MIN(A54,750000)-325000)*0.1+MAX(0,A54-750000)*0.12)-IF(Inputs!B8="First-time buyer",(IF(A54>145000,MIN(600,0.02*(MIN(A54,175000)-145000)),0)),0)+IF(Inputs!B8="Additional / Investor",0.08*A54,0)),IF(Inputs!B7="Wales",(IF(Inputs!B8="Additional / Investor",(MIN(A54,180000)*0.05+MAX(0,MIN(A54,250000)-180000)*0.085+MAX(0,MIN(A54,400000)-250000)*0.1+MAX(0,MIN(A54,750000)-400000)*0.125+MAX(0,MIN(A54,1500000)-750000)*0.15+MAX(0,A54-1500000)*0.17),(MAX(0,MIN(A54,400000)-225000)*0.06+MAX(0,MIN(A54,750000)-400000)*0.075+MAX(0,MIN(A54,1500000)-750000)*0.1+MAX(0,A54-1500000)*0.12))),0)))))+(Inputs!B14+Inputs!B15+Inputs!B16+Inputs!B17)+(Summary!B14)+(Summary!B15)+(((((A54)*Inputs!B20)+(IF(Inputs!B24="Yes",(Summary!B14)*Inputs!B25,0))*Inputs!B26)*Inputs!B21*Inputs!B10/12)+((((A54)*Inputs!B20)+(IF(Inputs!B24="Yes",(Summary!B14)*Inputs!B25,0)))*Inputs!B22)+((((A54)*Inputs!B20)+(IF(Inputs!B24="Yes",(Summary!B14)*Inputs!B25,0)))*Inputs!B23))+(Summary!B17))) -> -75362.5 | C54: =IF(A54>$B$6,"","")
A55: =$B$5+(44)*$B$7 -> 320000 | B55: =IF(A55>$B$6,"",(Inputs!B6)-((A55)+(IF(Inputs!D13<>"",Inputs!D13,IF(Inputs!B7="England & N. Ireland",(IF(Inputs!B8="First-time buyer",(IF(A55<=500000,MAX(0,A55-300000)*0.05,(MAX(0,MIN(A55,250000)-125000)*0.02+MAX(0,MIN(A55,925000)-250000)*0.05+MAX(0,MIN(A55,1500000)-925000)*0.1+MAX(0,A55-1500000)*0.12))),(MAX(0,MIN(A55,250000)-125000)*0.02+MAX(0,MIN(A55,925000)-250000)*0.05+MAX(0,MIN(A55,1500000)-925000)*0.1+MAX(0,A55-1500000)*0.12)+IF(Inputs!B8="Additional / Investor",0.05*A55,0)+IF(Inputs!B9="Yes",0.02*A55,0))),IF(Inputs!B7="Scotland",((MAX(0,MIN(A55,250000)-145000)*0.02+MAX(0,MIN(A55,325000)-250000)*0.05+MAX(0,MIN(A55,750000)-325000)*0.1+MAX(0,A55-750000)*0.12)-IF(Inputs!B8="First-time buyer",(IF(A55>145000,MIN(600,0.02*(MIN(A55,175000)-145000)),0)),0)+IF(Inputs!B8="Additional / Investor",0.08*A55,0)),IF(Inputs!B7="Wales",(IF(Inputs!B8="Additional / Investor",(MIN(A55,180000)*0.05+MAX(0,MIN(A55,250000)-180000)*0.085+MAX(0,MIN(A55,400000)-250000)*0.1+MAX(0,MIN(A55,750000)-400000)*0.125+MAX(0,MIN(A55,1500000)-750000)*0.15+MAX(0,A55-1500000)*0.17),(MAX(0,MIN(A55,400000)-225000)*0.06+MAX(0,MIN(A55,750000)-400000)*0.075+MAX(0,MIN(A55,1500000)-750000)*0.1+MAX(0,A55-1500000)*0.12))),0)))))+(Inputs!B14+Inputs!B15+Inputs!B16+Inputs!B17)+(Summary!B14)+(Summary!B15)+(((((A55)*Inputs!B20)+(IF(Inputs!B24="Yes",(Summary!B14)*Inputs!B25,0))*Inputs!B26)*Inputs!B21*Inputs!B10/12)+((((A55)*Inputs!B20)+(IF(Inputs!B24="Yes",(Summary!B14)*Inputs!B25,0)))*Inputs!B22)+((((A55)*Inputs!B20)+(IF(Inputs!B24="Yes",(Summary!B14)*Inputs!B25,0)))*Inputs!B23))+(Summary!B17))) -> -81200 | C55: =IF(A55>$B$6,"","")
A56: =$B$5+(45)*$B$7 -> 325000 | B56: =IF(A56>$B$6,"",(Inputs!B6)-((A56)+(IF(Inputs!D13<>"",Inputs!D13,IF(Inputs!B7="England & N. Ireland",(IF(Inputs!B8="First-time buyer",(IF(A56<=500000,MAX(0,A56-300000)*0.05,(MAX(0,MIN(A56,250000)-125000)*0.02+MAX(0,MIN(A56,925000)-250000)*0.05+MAX(0,MIN(A56,1500000)-925000)*0.1+MAX(0,A56-1500000)*0.12))),(MAX(0,MIN(A56,250000)-125000)*0.02+MAX(0,MIN(A56,925000)-250000)*0.05+MAX(0,MIN(A56,1500000)-925000)*0.1+MAX(0,A56-1500000)*0.12)+IF(Inputs!B8="Additional / Investor",0.05*A56,0)+IF(Inputs!B9="Yes",0.02*A56,0))),IF(Inputs!B7="Scotland",((MAX(0,MIN(A56,250000)-145000)*0.02+MAX(0,MIN(A56,325000)-250000)*0.05+MAX(0,MIN(A56,750000)-325000)*0.1+MAX(0,A56-750000)*0.12)-IF(Inputs!B8="First-time buyer",(IF(A56>145000,MIN(600,0.02*(MIN(A56,175000)-145000)),0)),0)+IF(Inputs!B8="Additional / Investor",0.08*A56,0)),IF(Inputs!B7="Wales",(IF(Inputs!B8="Additional / Investor",(MIN(A56,180000)*0.05+MAX(0,MIN(A56,250000)-180000)*0.085+MAX(0,MIN(A56,400000)-250000)*0.1+MAX(0,MIN(A56,750000)-400000)*0.125+MAX(0,MIN(A56,1500000)-750000)*0.15+MAX(0,A56-1500000)*0.17),(MAX(0,MIN(A56,400000)-225000)*0.06+MAX(0,MIN(A56,750000)-400000)*0.075+MAX(0,MIN(A56,1500000)-750000)*0.1+MAX(0,A56-1500000)*0.12))),0)))))+(Inputs!B14+Inputs!B15+Inputs!B16+Inputs!B17)+(Summary!B14)+(Summary!B15)+(((((A56)*Inputs!B20)+(IF(Inputs!B24="Yes",(Summary!B14)*Inputs!B25,0))*Inputs!B26)*Inputs!B21*Inputs!B10/12)+((((A56)*Inputs!B20)+(IF(Inputs!B24="Yes",(Summary!B14)*Inputs!B25,0)))*Inputs!B22)+((((A56)*Inputs!B20)+(IF(Inputs!B24="Yes",(Summary!B14)*Inputs!B25,0)))*Inputs!B23))+(Summary!B17))) -> -87037.5 | C56: =IF(A56>$B$6,"","")
A57: =$B$5+(46)*$B$7 -> 330000 | B57: =IF(A57>$B$6,"",(Inputs!B6)-((A57)+(IF(Inputs!D13<>"",Inputs!D13,IF(Inputs!B7="England & N. Ireland",(IF(Inputs!B8="First-time buyer",(IF(A57<=500000,MAX(0,A57-300000)*0.05,(MAX(0,MIN(A57,250000)-125000)*0.02+MAX(0,MIN(A57,925000)-250000)*0.05+MAX(0,MIN(A57,1500000)-925000)*0.1+MAX(0,A57-1500000)*0.12))),(MAX(0,MIN(A57,250000)-125000)*0.02+MAX(0,MIN(A57,925000)-250000)*0.05+MAX(0,MIN(A57,1500000)-925000)*0.1+MAX(0,A57-1500000)*0.12)+IF(Inputs!B8="Additional / Investor",0.05*A57,0)+IF(Inputs!B9="Yes",0.02*A57,0))),IF(Inputs!B7="Scotland",((MAX(0,MIN(A57,250000)-145000)*0.02+MAX(0,MIN(A57,325000)-250000)*0.05+MAX(0,MIN(A57,750000)-325000)*0.1+MAX(0,A57-750000)*0.12)-IF(Inputs!B8="First-time buyer",(IF(A57>145000,MIN(600,0.02*(MIN(A57,175000)-145000)),0)),0)+IF(Inputs!B8="Additional / Investor",0.08*A57,0)),IF(Inputs!B7="Wales",(IF(Inputs!B8="Additional / Investor",(MIN(A57,180000)*0.05+MAX(0,MIN(A57,250000)-180000)*0.085+MAX(0,MIN(A57,400000)-250000)*0.1+MAX(0,MIN(A57,750000)-400000)*0.125+MAX(0,MIN(A57,1500000)-750000)*0.15+MAX(0,A57-1500000)*0.17),(MAX(0,MIN(A57,400000)-225000)*0.06+MAX(0,MIN(A57,750000)-400000)*0.075+MAX(0,MIN(A57,1500000)-750000)*0.1+MAX(0,A57-1500000)*0.12))),0)))))+(Inputs!B14+Inputs!B15+Inputs!B16+Inputs!B17)+(Summary!B14)+(Summary!B15)+(((((A57)*Inputs!B20)+(IF(Inputs!B24="Yes",(Summary!B14)*Inputs!B25,0))*Inputs!B26)*Inputs!B21*Inputs!B10/12)+((((A57)*Inputs!B20)+(IF(Inputs!B24="Yes",(Summary!B14)*Inputs!B25,0)))*Inputs!B22)+((((A57)*Inputs!B20)+(IF(Inputs!B24="Yes",(Summary!B14)*Inputs!B25,0)))*Inputs!B23))+(Summary!B17))) -> -92875 | C57: =IF(A57>$B$6,"","")
A58: =$B$5+(47)*$B$7 -> 335000 | B58: =IF(A58>$B$6,"",(Inputs!B6)-((A58)+(IF(Inputs!D13<>"",Inputs!D13,IF(Inputs!B7="England & N. Ireland",(IF(Inputs!B8="First-time buyer",(IF(A58<=500000,MAX(0,A58-300000)*0.05,(MAX(0,MIN(A58,250000)-125000)*0.02+MAX(0,MIN(A58,925000)-250000)*0.05+MAX(0,MIN(A58,1500000)-925000)*0.1+MAX(0,A58-1500000)*0.12))),(MAX(0,MIN(A58,250000)-125000)*0.02+MAX(0,MIN(A58,925000)-250000)*0.05+MAX(0,MIN(A58,1500000)-925000)*0.1+MAX(0,A58-1500000)*0.12)+IF(Inputs!B8="Additional / Investor",0.05*A58,0)+IF(Inputs!B9="Yes",0.02*A58,0))),IF(Inputs!B7="Scotland",((MAX(0,MIN(A58,250000)-145000)*0.02+MAX(0,MIN(A58,325000)-250000)*0.05+MAX(0,MIN(A58,750000)-325000)*0.1+MAX(0,A58-750000)*0.12)-IF(Inputs!B8="First-time buyer",(IF(A58>145000,MIN(600,0.02*(MIN(A58,175000)-145000)),0)),0)+IF(Inputs!B8="Additional / Investor",0.08*A58,0)),IF(Inputs!B7="Wales",(IF(Inputs!B8="Additional / Investor",(MIN(A58,180000)*0.05+MAX(0,MIN(A58,250000)-180000)*0.085+MAX(0,MIN(A58,400000)-250000)*0.1+MAX(0,MIN(A58,750000)-400000)*0.125+MAX(0,MIN(A58,1500000)-750000)*0.15+MAX(0,A58-1500000)*0.17),(MAX(0,MIN(A58,400000)-225000)*0.06+MAX(0,MIN(A58,750000)-400000)*0.075+MAX(0,MIN(A58,1500000)-750000)*0.1+MAX(0,A58-1500000)*0.12))),0)))))+(Inputs!B14+Inputs!B15+Inputs!B16+Inputs!B17)+(Summary!B14)+(Summary!B15)+(((((A58)*Inputs!B20)+(IF(Inputs!B24="Yes",(Summary!B14)*Inputs!B25,0))*Inputs!B26)*Inputs!B21*Inputs!B10/12)+((((A58)*Inputs!B20)+(IF(Inputs!B24="Yes",(Summary!B14)*Inputs!B25,0)))*Inputs!B22)+((((A58)*Inputs!B20)+(IF(Inputs!B24="Yes",(Summary!B14)*Inputs!B25,0)))*Inputs!B23))+(Summary!B17))) -> -98712.5 | C58: =IF(A58>$B$6,"","")
A59: =$B$5+(48)*$B$7 -> 340000 | B59: =IF(A59>$B$6,"",(Inputs!B6)-((A59)+(IF(Inputs!D13<>"",Inputs!D13,IF(Inputs!B7="England & N. Ireland",(IF(Inputs!B8="First-time buyer",(IF(A59<=500000,MAX(0,A59-300000)*0.05,(MAX(0,MIN(A59,250000)-125000)*0.02+MAX(0,MIN(A59,925000)-250000)*0.05+MAX(0,MIN(A59,1500000)-925000)*0.1+MAX(0,A59-1500000)*0.12))),(MAX(0,MIN(A59,250000)-125000)*0.02+MAX(0,MIN(A59,925000)-250000)*0.05+MAX(0,MIN(A59,1500000)-925000)*0.1+MAX(0,A59-1500000)*0.12)+IF(Inputs!B8="Additional / Investor",0.05*A59,0)+IF(Inputs!B9="Yes",0.02*A59,0))),IF(Inputs!B7="Scotland",((MAX(0,MIN(A59,250000)-145000)*0.02+MAX(0,MIN(A59,325000)-250000)*0.05+MAX(0,MIN(A59,750000)-325000)*0.1+MAX(0,A59-750000)*0.12)-IF(Inputs!B8="First-time buyer",(IF(A59>145000,MIN(600,0.02*(MIN(A59,175000)-145000)),0)),0)+IF(Inputs!B8="Additional / Investor",0.08*A59,0)),IF(Inputs!B7="Wales",(IF(Inputs!B8="Additional / Investor",(MIN(A59,180000)*0.05+MAX(0,MIN(A59,250000)-180000)*0.085+MAX(0,MIN(A59,400000)-250000)*0.1+MAX(0,MIN(A59,750000)-400000)*0.125+MAX(0,MIN(A59,1500000)-750000)*0.15+MAX(0,A59-1500000)*0.17),(MAX(0,MIN(A59,400000)-225000)*0.06+MAX(0,MIN(A59,750000)-400000)*0.075+MAX(0,MIN(A59,1500000)-750000)*0.1+MAX(0,A59-1500000)*0.12))),0)))))+(Inputs!B14+Inputs!B15+Inputs!B16+Inputs!B17)+(Summary!B14)+(Summary!B15)+(((((A59)*Inputs!B20)+(IF(Inputs!B24="Yes",(Summary!B14)*Inputs!B25,0))*Inputs!B26)*Inputs!B21*Inputs!B10/12)+((((A59)*Inputs!B20)+(IF(Inputs!B24="Yes",(Summary!B14)*Inputs!B25,0)))*Inputs!B22)+((((A59)*Inputs!B20)+(IF(Inputs!B24="Yes",(Summary!B14)*Inputs!B25,0)))*Inputs!B23))+(Summary!B17))) -> -104550 | C59: =IF(A59>$B$6,"","")
A60: =$B$5+(49)*$B$7 -> 345000 | B60: =IF(A60>$B$6,"",(Inputs!B6)-((A60)+(IF(Inputs!D13<>"",Inputs!D13,IF(Inputs!B7="England & N. Ireland",(IF(Inputs!B8="First-time buyer",(IF(A60<=500000,MAX(0,A60-300000)*0.05,(MAX(0,MIN(A60,250000)-125000)*0.02+MAX(0,MIN(A60,925000)-250000)*0.05+MAX(0,MIN(A60,1500000)-925000)*0.1+MAX(0,A60-1500000)*0.12))),(MAX(0,MIN(A60,250000)-125000)*0.02+MAX(0,MIN(A60,925000)-250000)*0.05+MAX(0,MIN(A60,1500000)-925000)*0.1+MAX(0,A60-1500000)*0.12)+IF(Inputs!B8="Additional / Investor",0.05*A60,0)+IF(Inputs!B9="Yes",0.02*A60,0))),IF(Inputs!B7="Scotland",((MAX(0,MIN(A60,250000)-145000)*0.02+MAX(0,MIN(A60,325000)-250000)*0.05+MAX(0,MIN(A60,750000)-325000)*0.1+MAX(0,A60-750000)*0.12)-IF(Inputs!B8="First-time buyer",(IF(A60>145000,MIN(600,0.02*(MIN(A60,175000)-145000)),0)),0)+IF(Inputs!B8="Additional / Investor",0.08*A60,0)),IF(Inputs!B7="Wales",(IF(Inputs!B8="Additional / Investor",(MIN(A60,180000)*0.05+MAX(0,MIN(A60,250000)-180000)*0.085+MAX(0,MIN(A60,400000)-250000)*0.1+MAX(0,MIN(A60,750000)-400000)*0.125+MAX(0,MIN(A60,1500000)-750000)*0.15+MAX(0,A60-1500000)*0.17),(MAX(0,MIN(A60,400000)-225000)*0.06+MAX(0,MIN(A60,750000)-400000)*0.075+MAX(0,MIN(A60,1500000)-750000)*0.1+MAX(0,A60-1500000)*0.12))),0)))))+(Inputs!B14+Inputs!B15+Inputs!B16+Inputs!B17)+(Summary!B14)+(Summary!B15)+(((((A60)*Inputs!B20)+(IF(Inputs!B24="Yes",(Summary!B14)*Inputs!B25,0))*Inputs!B26)*Inputs!B21*Inputs!B10/12)+((((A60)*Inputs!B20)+(IF(Inputs!B24="Yes",(Summary!B14)*Inputs!B25,0)))*Inputs!B22)+((((A60)*Inputs!B20)+(IF(Inputs!B24="Yes",(Summary!B14)*Inputs!B25,0)))*Inputs!B23))+(Summary!B17))) -> -110387.5 | C60: =IF(A60>$B$6,"","")
A61: =$B$5+(50)*$B$7 -> 350000 | B61: =IF(A61>$B$6,"",(Inputs!B6)-((A61)+(IF(Inputs!D13<>"",Inputs!D13,IF(Inputs!B7="England & N. Ireland",(IF(Inputs!B8="First-time buyer",(IF(A61<=500000,MAX(0,A61-300000)*0.05,(MAX(0,MIN(A61,250000)-125000)*0.02+MAX(0,MIN(A61,925000)-250000)*0.05+MAX(0,MIN(A61,1500000)-925000)*0.1+MAX(0,A61-1500000)*0.12))),(MAX(0,MIN(A61,250000)-125000)*0.02+MAX(0,MIN(A61,925000)-250000)*0.05+MAX(0,MIN(A61,1500000)-925000)*0.1+MAX(0,A61-1500000)*0.12)+IF(Inputs!B8="Additional / Investor",0.05*A61,0)+IF(Inputs!B9="Yes",0.02*A61,0))),IF(Inputs!B7="Scotland",((MAX(0,MIN(A61,250000)-145000)*0.02+MAX(0,MIN(A61,325000)-250000)*0.05+MAX(0,MIN(A61,750000)-325000)*0.1+MAX(0,A61-750000)*0.12)-IF(Inputs!B8="First-time buyer",(IF(A61>145000,MIN(600,0.02*(MIN(A61,175000)-145000)),0)),0)+IF(Inputs!B8="Additional / Investor",0.08*A61,0)),IF(Inputs!B7="Wales",(IF(Inputs!B8="Additional / Investor",(MIN(A61,180000)*0.05+MAX(0,MIN(A61,250000)-180000)*0.085+MAX(0,MIN(A61,400000)-250000)*0.1+MAX(0,MIN(A61,750000)-400000)*0.125+MAX(0,MIN(A61,1500000)-750000)*0.15+MAX(0,A61-1500000)*0.17),(MAX(0,MIN(A61,400000)-225000)*0.06+MAX(0,MIN(A61,750000)-400000)*0.075+MAX(0,MIN(A61,1500000)-750000)*0.1+MAX(0,A61-1500000)*0.12))),0)))))+(Inputs!B14+Inputs!B15+Inputs!B16+Inputs!B17)+(Summary!B14)+(Summary!B15)+(((((A61)*Inputs!B20)+(IF(Inputs!B24="Yes",(Summary!B14)*Inputs!B25,0))*Inputs!B26)*Inputs!B21*Inputs!B10/12)+((((A61)*Inputs!B20)+(IF(Inputs!B24="Yes",(Summary!B14)*Inputs!B25,0)))*Inputs!B22)+((((A61)*Inputs!B20)+(IF(Inputs!B24="Yes",(Summary!B14)*Inputs!B25,0)))*Inputs!B23))+(Summary!B17))) -> -116225 | C61: =IF(A61>$B$6,"","")
A62: =$B$5+(51)*$B$7 -> 355000 | B62: =IF(A62>$B$6,"",(Inputs!B6)-((A62)+(IF(Inputs!D13<>"",Inputs!D13,IF(Inputs!B7="England & N. Ireland",(IF(Inputs!B8="First-time buyer",(IF(A62<=500000,MAX(0,A62-300000)*0.05,(MAX(0,MIN(A62,250000)-125000)*0.02+MAX(0,MIN(A62,925000)-250000)*0.05+MAX(0,MIN(A62,1500000)-925000)*0.1+MAX(0,A62-1500000)*0.12))),(MAX(0,MIN(A62,250000)-125000)*0.02+MAX(0,MIN(A62,925000)-250000)*0.05+MAX(0,MIN(A62,1500000)-925000)*0.1+MAX(0,A62-1500000)*0.12)+IF(Inputs!B8="Additional / Investor",0.05*A62,0)+IF(Inputs!B9="Yes",0.02*A62,0))),IF(Inputs!B7="Scotland",((MAX(0,MIN(A62,250000)-145000)*0.02+MAX(0,MIN(A62,325000)-250000)*0.05+MAX(0,MIN(A62,750000)-325000)*0.1+MAX(0,A62-750000)*0.12)-IF(Inputs!B8="First-time buyer",(IF(A62>145000,MIN(600,0.02*(MIN(A62,175000)-145000)),0)),0)+IF(Inputs!B8="Additional / Investor",0.08*A62,0)),IF(Inputs!B7="Wales",(IF(Inputs!B8="Additional / Investor",(MIN(A62,180000)*0.05+MAX(0,MIN(A62,250000)-180000)*0.085+MAX(0,MIN(A62,400000)-250000)*0.1+MAX(0,MIN(A62,750000)-400000)*0.125+MAX(0,MIN(A62,1500000)-750000)*0.15+MAX(0,A62-1500000)*0.17),(MAX(0,MIN(A62,400000)-225000)*0.06+MAX(0,MIN(A62,750000)-400000)*0.075+MAX(0,MIN(A62,1500000)-750000)*0.1+MAX(0,A62-1500000)*0.12))),0)))))+(Inputs!B14+Inputs!B15+Inputs!B16+Inputs!B17)+(Summary!B14)+(Summary!B15)+(((((A62)*Inputs!B20)+(IF(Inputs!B24="Yes",(Summary!B14)*Inputs!B25,0))*Inputs!B26)*Inputs!B21*Inputs!B10/12)+((((A62)*Inputs!B20)+(IF(Inputs!B24="Yes",(Summary!B14)*Inputs!B25,0)))*Inputs!B22)+((((A62)*Inputs!B20)+(IF(Inputs!B24="Yes",(Summary!B14)*Inputs!B25,0)))*Inputs!B23))+(Summary!B17))) -> -122062.5 | C62: =IF(A62>$B$6,"","")
A63: =$B$5+(52)*$B$7 -> 360000 | B63: =IF(A63>$B$6,"",(Inputs!B6)-((A63)+(IF(Inputs!D13<>"",Inputs!D13,IF(Inputs!B7="England & N. Ireland",(IF(Inputs!B8="First-time buyer",(IF(A63<=500000,MAX(0,A63-300000)*0.05,(MAX(0,MIN(A63,250000)-125000)*0.02+MAX(0,MIN(A63,925000)-250000)*0.05+MAX(0,MIN(A63,1500000)-925000)*0.1+MAX(0,A63-1500000)*0.12))),(MAX(0,MIN(A63,250000)-125000)*0.02+MAX(0,MIN(A63,925000)-250000)*0.05+MAX(0,MIN(A63,1500000)-925000)*0.1+MAX(0,A63-1500000)*0.12)+IF(Inputs!B8="Additional / Investor",0.05*A63,0)+IF(Inputs!B9="Yes",0.02*A63,0))),IF(Inputs!B7="Scotland",((MAX(0,MIN(A63,250000)-145000)*0.02+MAX(0,MIN(A63,325000)-250000)*0.05+MAX(0,MIN(A63,750000)-325000)*0.1+MAX(0,A63-750000)*0.12)-IF(Inputs!B8="First-time buyer",(IF(A63>145000,MIN(600,0.02*(MIN(A63,175000)-145000)),0)),0)+IF(Inputs!B8="Additional / Investor",0.08*A63,0)),IF(Inputs!B7="Wales",(IF(Inputs!B8="Additional / Investor",(MIN(A63,180000)*0.05+MAX(0,MIN(A63,250000)-180000)*0.085+MAX(0,MIN(A63,400000)-250000)*0.1+MAX(0,MIN(A63,750000)-400000)*0.125+MAX(0,MIN(A63,1500000)-750000)*0.15+MAX(0,A63-1500000)*0.17),(MAX(0,MIN(A63,400000)-225000)*0.06+MAX(0,MIN(A63,750000)-400000)*0.075+MAX(0,MIN(A63,1500000)-750000)*0.1+MAX(0,A63-1500000)*0.12))),0)))))+(Inputs!B14+Inputs!B15+Inputs!B16+Inputs!B17)+(Summary!B14)+(Summary!B15)+(((((A63)*Inputs!B20)+(IF(Inputs!B24="Yes",(Summary!B14)*Inputs!B25,0))*Inputs!B26)*Inputs!B21*Inputs!B10/12)+((((A63)*Inputs!B20)+(IF(Inputs!B24="Yes",(Summary!B14)*Inputs!B25,0)))*Inputs!B22)+((((A63)*Inputs!B20)+(IF(Inputs!B24="Yes",(Summary!B14)*Inputs!B25,0)))*Inputs!B23))+(Summary!B17))) -> -127900 | C63: =IF(A63>$B$6,"","")
A64: =$B$5+(53)*$B$7 -> 365000 | B64: =IF(A64>$B$6,"",(Inputs!B6)-((A64)+(IF(Inputs!D13<>"",Inputs!D13,IF(Inputs!B7="England & N. Ireland",(IF(Inputs!B8="First-time buyer",(IF(A64<=500000,MAX(0,A64-300000)*0.05,(MAX(0,MIN(A64,250000)-125000)*0.02+MAX(0,MIN(A64,925000)-250000)*0.05+MAX(0,MIN(A64,1500000)-925000)*0.1+MAX(0,A64-1500000)*0.12))),(MAX(0,MIN(A64,250000)-125000)*0.02+MAX(0,MIN(A64,925000)-250000)*0.05+MAX(0,MIN(A64,1500000)-925000)*0.1+MAX(0,A64-1500000)*0.12)+IF(Inputs!B8="Additional / Investor",0.05*A64,0)+IF(Inputs!B9="Yes",0.02*A64,0))),IF(Inputs!B7="Scotland",((MAX(0,MIN(A64,250000)-145000)*0.02+MAX(0,MIN(A64,325000)-250000)*0.05+MAX(0,MIN(A64,750000)-325000)*0.1+MAX(0,A64-750000)*0.12)-IF(Inputs!B8="First-time buyer",(IF(A64>145000,MIN(600,0.02*(MIN(A64,175000)-145000)),0)),0)+IF(Inputs!B8="Additional / Investor",0.08*A64,0)),IF(Inputs!B7="Wales",(IF(Inputs!B8="Additional / Investor",(MIN(A64,180000)*0.05+MAX(0,MIN(A64,250000)-180000)*0.085+MAX(0,MIN(A64,400000)-250000)*0.1+MAX(0,MIN(A64,750000)-400000)*0.125+MAX(0,MIN(A64,1500000)-750000)*0.15+MAX(0,A64-1500000)*0.17),(MAX(0,MIN(A64,400000)-225000)*0.06+MAX(0,MIN(A64,750000)-400000)*0.075+MAX(0,MIN(A64,1500000)-750000)*0.1+MAX(0,A64-1500000)*0.12))),0)))))+(Inputs!B14+Inputs!B15+Inputs!B16+Inputs!B17)+(Summary!B14)+(Summary!B15)+(((((A64)*Inputs!B20)+(IF(Inputs!B24="Yes",(Summary!B14)*Inputs!B25,0))*Inputs!B26)*Inputs!B21*Inputs!B10/12)+((((A64)*Inputs!B20)+(IF(Inputs!B24="Yes",(Summary!B14)*Inputs!B25,0)))*Inputs!B22)+((((A64)*Inputs!B20)+(IF(Inputs!B24="Yes",(Summary!B14)*Inputs!B25,0)))*Inputs!B23))+(Summary!B17))) -> -133737.5 | C64: =IF(A64>$B$6,"","")
A65: =$B$5+(54)*$B$7 -> 370000 | B65: =IF(A65>$B$6,"",(Inputs!B6)-((A65)+(IF(Inputs!D13<>"",Inputs!D13,IF(Inputs!B7="England & N. Ireland",(IF(Inputs!B8="First-time buyer",(IF(A65<=500000,MAX(0,A65-300000)*0.05,(MAX(0,MIN(A65,250000)-125000)*0.02+MAX(0,MIN(A65,925000)-250000)*0.05+MAX(0,MIN(A65,1500000)-925000)*0.1+MAX(0,A65-1500000)*0.12))),(MAX(0,MIN(A65,250000)-125000)*0.02+MAX(0,MIN(A65,925000)-250000)*0.05+MAX(0,MIN(A65,1500000)-925000)*0.1+MAX(0,A65-1500000)*0.12)+IF(Inputs!B8="Additional / Investor",0.05*A65,0)+IF(Inputs!B9="Yes",0.02*A65,0))),IF(Inputs!B7="Scotland",((MAX(0,MIN(A65,250000)-145000)*0.02+MAX(0,MIN(A65,325000)-250000)*0.05+MAX(0,MIN(A65,750000)-325000)*0.1+MAX(0,A65-750000)*0.12)-IF(Inputs!B8="First-time buyer",(IF(A65>145000,MIN(600,0.02*(MIN(A65,175000)-145000)),0)),0)+IF(Inputs!B8="Additional / Investor",0.08*A65,0)),IF(Inputs!B7="Wales",(IF(Inputs!B8="Additional / Investor",(MIN(A65,180000)*0.05+MAX(0,MIN(A65,250000)-180000)*0.085+MAX(0,MIN(A65,400000)-250000)*0.1+MAX(0,MIN(A65,750000)-400000)*0.125+MAX(0,MIN(A65,1500000)-750000)*0.15+MAX(0,A65-1500000)*0.17),(MAX(0,MIN(A65,400000)-225000)*0.06+MAX(0,MIN(A65,750000)-400000)*0.075+MAX(0,MIN(A65,1500000)-750000)*0.1+MAX(0,A65-1500000)*0.12))),0)))))+(Inputs!B14+Inputs!B15+Inputs!B16+Inputs!B17)+(Summary!B14)+(Summary!B15)+(((((A65)*Inputs!B20)+(IF(Inputs!B24="Yes",(Summary!B14)*Inputs!B25,0))*Inputs!B26)*Inputs!B21*Inputs!B10/12)+((((A65)*Inputs!B20)+(IF(Inputs!B24="Yes",(Summary!B14)*Inputs!B25,0)))*Inputs!B22)+((((A65)*Inputs!B20)+(IF(Inputs!B24="Yes",(Summary!B14)*Inputs!B25,0)))*Inputs!B23))+(Summary!B17))) -> -139575 | C65: =IF(A65>$B$6,"","")
A66: =$B$5+(55)*$B$7 -> 375000 | B66: =IF(A66>$B$6,"",(Inputs!B6)-((A66)+(IF(Inputs!D13<>"",Inputs!D13,IF(Inputs!B7="England & N. Ireland",(IF(Inputs!B8="First-time buyer",(IF(A66<=500000,MAX(0,A66-300000)*0.05,(MAX(0,MIN(A66,250000)-125000)*0.02+MAX(0,MIN(A66,925000)-250000)*0.05+MAX(0,MIN(A66,1500000)-925000)*0.1+MAX(0,A66-1500000)*0.12))),(MAX(0,MIN(A66,250000)-125000)*0.02+MAX(0,MIN(A66,925000)-250000)*0.05+MAX(0,MIN(A66,1500000)-925000)*0.1+MAX(0,A66-1500000)*0.12)+IF(Inputs!B8="Additional / Investor",0.05*A66,0)+IF(Inputs!B9="Yes",0.02*A66,0))),IF(Inputs!B7="Scotland",((MAX(0,MIN(A66,250000)-145000)*0.02+MAX(0,MIN(A66,325000)-250000)*0.05+MAX(0,MIN(A66,750000)-325000)*0.1+MAX(0,A66-750000)*0.12)-IF(Inputs!B8="First-time buyer",(IF(A66>145000,MIN(600,0.02*(MIN(A66,175000)-145000)),0)),0)+IF(Inputs!B8="Additional / Investor",0.08*A66,0)),IF(Inputs!B7="Wales",(IF(Inputs!B8="Additional / Investor",(MIN(A66,180000)*0.05+MAX(0,MIN(A66,250000)-180000)*0.085+MAX(0,MIN(A66,400000)-250000)*0.1+MAX(0,MIN(A66,750000)-400000)*0.125+MAX(0,MIN(A66,1500000)-750000)*0.15+MAX(0,A66-1500000)*0.17),(MAX(0,MIN(A66,400000)-225000)*0.06+MAX(0,MIN(A66,750000)-400000)*0.075+MAX(0,MIN(A66,1500000)-750000)*0.1+MAX(0,A66-1500000)*0.12))),0)))))+(Inputs!B14+Inputs!B15+Inputs!B16+Inputs!B17)+(Summary!B14)+(Summary!B15)+(((((A66)*Inputs!B20)+(IF(Inputs!B24="Yes",(Summary!B14)*Inputs!B25,0))*Inputs!B26)*Inputs!B21*Inputs!B10/12)+((((A66)*Inputs!B20)+(IF(Inputs!B24="Yes",(Summary!B14)*Inputs!B25,0)))*Inputs!B22)+((((A66)*Inputs!B20)+(IF(Inputs!B24="Yes",(Summary!B14)*Inputs!B25,0)))*Inputs!B23))+(Summary!B17))) -> -145412.5 | C66: =IF(A66>$B$6,"","")
A67: =$B$5+(56)*$B$7 -> 380000 | B67: =IF(A67>$B$6,"",(Inputs!B6)-((A67)+(IF(Inputs!D13<>"",Inputs!D13,IF(Inputs!B7="England & N. Ireland",(IF(Inputs!B8="First-time buyer",(IF(A67<=500000,MAX(0,A67-300000)*0.05,(MAX(0,MIN(A67,250000)-125000)*0.02+MAX(0,MIN(A67,925000)-250000)*0.05+MAX(0,MIN(A67,1500000)-925000)*0.1+MAX(0,A67-1500000)*0.12))),(MAX(0,MIN(A67,250000)-125000)*0.02+MAX(0,MIN(A67,925000)-250000)*0.05+MAX(0,MIN(A67,1500000)-925000)*0.1+MAX(0,A67-1500000)*0.12)+IF(Inputs!B8="Additional / Investor",0.05*A67,0)+IF(Inputs!B9="Yes",0.02*A67,0))),IF(Inputs!B7="Scotland",((MAX(0,MIN(A67,250000)-145000)*0.02+MAX(0,MIN(A67,325000)-250000)*0.05+MAX(0,MIN(A67,750000)-325000)*0.1+MAX(0,A67-750000)*0.12)-IF(Inputs!B8="First-time buyer",(IF(A67>145000,MIN(600,0.02*(MIN(A67,175000)-145000)),0)),0)+IF(Inputs!B8="Additional / Investor",0.08*A67,0)),IF(Inputs!B7="Wales",(IF(Inputs!B8="Additional / Investor",(MIN(A67,180000)*0.05+MAX(0,MIN(A67,250000)-180000)*0.085+MAX(0,MIN(A67,400000)-250000)*0.1+MAX(0,MIN(A67,750000)-400000)*0.125+MAX(0,MIN(A67,1500000)-750000)*0.15+MAX(0,A67-1500000)*0.17),(MAX(0,MIN(A67,400000)-225000)*0.06+MAX(0,MIN(A67,750000)-400000)*0.075+MAX(0,MIN(A67,1500000)-750000)*0.1+MAX(0,A67-1500000)*0.12))),0)))))+(Inputs!B14+Inputs!B15+Inputs!B16+Inputs!B17)+(Summary!B14)+(Summary!B15)+(((((A67)*Inputs!B20)+(IF(Inputs!B24="Yes",(Summary!B14)*Inputs!B25,0))*Inputs!B26)*Inputs!B21*Inputs!B10/12)+((((A67)*Inputs!B20)+(IF(Inputs!B24="Yes",(Summary!B14)*Inputs!B25,0)))*Inputs!B22)+((((A67)*Inputs!B20)+(IF(Inputs!B24="Yes",(Summary!B14)*Inputs!B25,0)))*Inputs!B23))+(Summary!B17))) -> -151250 | C67: =IF(A67>$B$6,"","")
A68: =$B$5+(57)*$B$7 -> 385000 | B68: =IF(A68>$B$6,"",(Inputs!B6)-((A68)+(IF(Inputs!D13<>"",Inputs!D13,IF(Inputs!B7="England & N. Ireland",(IF(Inputs!B8="First-time buyer",(IF(A68<=500000,MAX(0,A68-300000)*0.05,(MAX(0,MIN(A68,250000)-125000)*0.02+MAX(0,MIN(A68,925000)-250000)*0.05+MAX(0,MIN(A68,1500000)-925000)*0.1+MAX(0,A68-1500000)*0.12))),(MAX(0,MIN(A68,250000)-125000)*0.02+MAX(0,MIN(A68,925000)-250000)*0.05+MAX(0,MIN(A68,1500000)-925000)*0.1+MAX(0,A68-1500000)*0.12)+IF(Inputs!B8="Additional / Investor",0.05*A68,0)+IF(Inputs!B9="Yes",0.02*A68,0))),IF(Inputs!B7="Scotland",((MAX(0,MIN(A68,250000)-145000)*0.02+MAX(0,MIN(A68,325000)-250000)*0.05+MAX(0,MIN(A68,750000)-325000)*0.1+MAX(0,A68-750000)*0.12)-IF(Inputs!B8="First-time buyer",(IF(A68>145000,MIN(600,0.02*(MIN(A68,175000)-145000)),0)),0)+IF(Inputs!B8="Additional / Investor",0.08*A68,0)),IF(Inputs!B7="Wales",(IF(Inputs!B8="Additional / Investor",(MIN(A68,180000)*0.05+MAX(0,MIN(A68,250000)-180000)*0.085+MAX(0,MIN(A68,400000)-250000)*0.1+MAX(0,MIN(A68,750000)-400000)*0.125+MAX(0,MIN(A68,1500000)-750000)*0.15+MAX(0,A68-1500000)*0.17),(MAX(0,MIN(A68,400000)-225000)*0.06+MAX(0,MIN(A68,750000)-400000)*0.075+MAX(0,MIN(A68,1500000)-750000)*0.1+MAX(0,A68-1500000)*0.12))),0)))))+(Inputs!B14+Inputs!B15+Inputs!B16+Inputs!B17)+(Summary!B14)+(Summary!B15)+(((((A68)*Inputs!B20)+(IF(Inputs!B24="Yes",(Summary!B14)*Inputs!B25,0))*Inputs!B26)*Inputs!B21*Inputs!B10/12)+((((A68)*Inputs!B20)+(IF(Inputs!B24="Yes",(Summary!B14)*Inputs!B25,0)))*Inputs!B22)+((((A68)*Inputs!B20)+(IF(Inputs!B24="Yes",(Summary!B14)*Inputs!B25,0)))*Inputs!B23))+(Summary!B17))) -> -157087.5 | C68: =IF(A68>$B$6,"","")
A69: =$B$5+(58)*$B$7 -> 390000 | B69: =IF(A69>$B$6,"",(Inputs!B6)-((A69)+(IF(Inputs!D13<>"",Inputs!D13,IF(Inputs!B7="England & N. Ireland",(IF(Inputs!B8="First-time buyer",(IF(A69<=500000,MAX(0,A69-300000)*0.05,(MAX(0,MIN(A69,250000)-125000)*0.02+MAX(0,MIN(A69,925000)-250000)*0.05+MAX(0,MIN(A69,1500000)-925000)*0.1+MAX(0,A69-1500000)*0.12))),(MAX(0,MIN(A69,250000)-125000)*0.02+MAX(0,MIN(A69,925000)-250000)*0.05+MAX(0,MIN(A69,1500000)-925000)*0.1+MAX(0,A69-1500000)*0.12)+IF(Inputs!B8="Additional / Investor",0.05*A69,0)+IF(Inputs!B9="Yes",0.02*A69,0))),IF(Inputs!B7="Scotland",((MAX(0,MIN(A69,250000)-145000)*0.02+MAX(0,MIN(A69,325000)-250000)*0.05+MAX(0,MIN(A69,750000)-325000)*0.1+MAX(0,A69-750000)*0.12)-IF(Inputs!B8="First-time buyer",(IF(A69>145000,MIN(600,0.02*(MIN(A69,175000)-145000)),0)),0)+IF(Inputs!B8="Additional / Investor",0.08*A69,0)),IF(Inputs!B7="Wales",(IF(Inputs!B8="Additional / Investor",(MIN(A69,180000)*0.05+MAX(0,MIN(A69,250000)-180000)*0.085+MAX(0,MIN(A69,400000)-250000)*0.1+MAX(0,MIN(A69,750000)-400000)*0.125+MAX(0,MIN(A69,1500000)-750000)*0.15+MAX(0,A69-1500000)*0.17),(MAX(0,MIN(A69,400000)-225000)*0.06+MAX(0,MIN(A69,750000)-400000)*0.075+MAX(0,MIN(A69,1500000)-750000)*0.1+MAX(0,A69-1500000)*0.12))),0)))))+(Inputs!B14+Inputs!B15+Inputs!B16+Inputs!B17)+(Summary!B14)+(Summary!B15)+(((((A69)*Inputs!B20)+(IF(Inputs!B24="Yes",(Summary!B14)*Inputs!B25,0))*Inputs!B26)*Inputs!B21*Inputs!B10/12)+((((A69)*Inputs!B20)+(IF(Inputs!B24="Yes",(Summary!B14)*Inputs!B25,0)))*Inputs!B22)+((((A69)*Inputs!B20)+(IF(Inputs!B24="Yes",(Summary!B14)*Inputs!B25,0)))*Inputs!B23))+(Summary!B17))) -> -162925 | C69: =IF(A69>$B$6,"","")
A70: =$B$5+(59)*$B$7 -> 395000 | B70: =IF(A70>$B$6,"",(Inputs!B6)-((A70)+(IF(Inputs!D13<>"",Inputs!D13,IF(Inputs!B7="England & N. Ireland",(IF(Inputs!B8="First-time buyer",(IF(A70<=500000,MAX(0,A70-300000)*0.05,(MAX(0,MIN(A70,250000)-125000)*0.02+MAX(0,MIN(A70,925000)-250000)*0.05+MAX(0,MIN(A70,1500000)-925000)*0.1+MAX(0,A70-1500000)*0.12))),(MAX(0,MIN(A70,250000)-125000)*0.02+MAX(0,MIN(A70,925000)-250000)*0.05+MAX(0,MIN(A70,1500000)-925000)*0.1+MAX(0,A70-1500000)*0.12)+IF(Inputs!B8="Additional / Investor",0.05*A70,0)+IF(Inputs!B9="Yes",0.02*A70,0))),IF(Inputs!B7="Scotland",((MAX(0,MIN(A70,250000)-145000)*0.02+MAX(0,MIN(A70,325000)-250000)*0.05+MAX(0,MIN(A70,750000)-325000)*0.1+MAX(0,A70-750000)*0.12)-IF(Inputs!B8="First-time buyer",(IF(A70>145000,MIN(600,0.02*(MIN(A70,175000)-145000)),0)),0)+IF(Inputs!B8="Additional / Investor",0.08*A70,0)),IF(Inputs!B7="Wales",(IF(Inputs!B8="Additional / Investor",(MIN(A70,180000)*0.05+MAX(0,MIN(A70,250000)-180000)*0.085+MAX(0,MIN(A70,400000)-250000)*0.1+MAX(0,MIN(A70,750000)-400000)*0.125+MAX(0,MIN(A70,1500000)-750000)*0.15+MAX(0,A70-1500000)*0.17),(MAX(0,MIN(A70,400000)-225000)*0.06+MAX(0,MIN(A70,750000)-400000)*0.075+MAX(0,MIN(A70,1500000)-750000)*0.1+MAX(0,A70-1500000)*0.12))),0)))))+(Inputs!B14+Inputs!B15+Inputs!B16+Inputs!B17)+(Summary!B14)+(Summary!B15)+(((((A70)*Inputs!B20)+(IF(Inputs!B24="Yes",(Summary!B14)*Inputs!B25,0))*Inputs!B26)*Inputs!B21*Inputs!B10/12)+((((A70)*Inputs!B20)+(IF(Inputs!B24="Yes",(Summary!B14)*Inputs!B25,0)))*Inputs!B22)+((((A70)*Inputs!B20)+(IF(Inputs!B24="Yes",(Summary!B14)*Inputs!B25,0)))*Inputs!B23))+(Summary!B17))) -> -168762.5 | C70: =IF(A70>$B$6,"","")
A71: =$B$5+(60)*$B$7 -> 400000 | B71: =IF(A71>$B$6,"",(Inputs!B6)-((A71)+(IF(Inputs!D13<>"",Inputs!D13,IF(Inputs!B7="England & N. Ireland",(IF(Inputs!B8="First-time buyer",(IF(A71<=500000,MAX(0,A71-300000)*0.05,(MAX(0,MIN(A71,250000)-125000)*0.02+MAX(0,MIN(A71,925000)-250000)*0.05+MAX(0,MIN(A71,1500000)-925000)*0.1+MAX(0,A71-1500000)*0.12))),(MAX(0,MIN(A71,250000)-125000)*0.02+MAX(0,MIN(A71,925000)-250000)*0.05+MAX(0,MIN(A71,1500000)-925000)*0.1+MAX(0,A71-1500000)*0.12)+IF(Inputs!B8="Additional / Investor",0.05*A71,0)+IF(Inputs!B9="Yes",0.02*A71,0))),IF(Inputs!B7="Scotland",((MAX(0,MIN(A71,250000)-145000)*0.02+MAX(0,MIN(A71,325000)-250000)*0.05+MAX(0,MIN(A71,750000)-325000)*0.1+MAX(0,A71-750000)*0.12)-IF(Inputs!B8="First-time buyer",(IF(A71>145000,MIN(600,0.02*(MIN(A71,175000)-145000)),0)),0)+IF(Inputs!B8="Additional / Investor",0.08*A71,0)),IF(Inputs!B7="Wales",(IF(Inputs!B8="Additional / Investor",(MIN(A71,180000)*0.05+MAX(0,MIN(A71,250000)-180000)*0.085+MAX(0,MIN(A71,400000)-250000)*0.1+MAX(0,MIN(A71,750000)-400000)*0.125+MAX(0,MIN(A71,1500000)-750000)*0.15+MAX(0,A71-1500000)*0.17),(MAX(0,MIN(A71,400000)-225000)*0.06+MAX(0,MIN(A71,750000)-400000)*0.075+MAX(0,MIN(A71,1500000)-750000)*0.1+MAX(0,A71-1500000)*0.12))),0)))))+(Inputs!B14+Inputs!B15+Inputs!B16+Inputs!B17)+(Summary!B14)+(Summary!B15)+(((((A71)*Inputs!B20)+(IF(Inputs!B24="Yes",(Summary!B14)*Inputs!B25,0))*Inputs!B26)*Inputs!B21*Inputs!B10/12)+((((A71)*Inputs!B20)+(IF(Inputs!B24="Yes",(Summary!B14)*Inputs!B25,0)))*Inputs!B22)+((((A71)*Inputs!B20)+(IF(Inputs!B24="Yes",(Summary!B14)*Inputs!B25,0)))*Inputs!B23))+(Summary!B17))) -> -174600 | C71: =IF(A71>$B$6,"","")
A72: =$B$5+(61)*$B$7 -> 405000 | B72: =IF(A72>$B$6,"",(Inputs!B6)-((A72)+(IF(Inputs!D13<>"",Inputs!D13,IF(Inputs!B7="England & N. Ireland",(IF(Inputs!B8="First-time buyer",(IF(A72<=500000,MAX(0,A72-300000)*0.05,(MAX(0,MIN(A72,250000)-125000)*0.02+MAX(0,MIN(A72,925000)-250000)*0.05+MAX(0,MIN(A72,1500000)-925000)*0.1+MAX(0,A72-1500000)*0.12))),(MAX(0,MIN(A72,250000)-125000)*0.02+MAX(0,MIN(A72,925000)-250000)*0.05+MAX(0,MIN(A72,1500000)-925000)*0.1+MAX(0,A72-1500000)*0.12)+IF(Inputs!B8="Additional / Investor",0.05*A72,0)+IF(Inputs!B9="Yes",0.02*A72,0))),IF(Inputs!B7="Scotland",((MAX(0,MIN(A72,250000)-145000)*0.02+MAX(0,MIN(A72,325000)-250000)*0.05+MAX(0,MIN(A72,750000)-325000)*0.1+MAX(0,A72-750000)*0.12)-IF(Inputs!B8="First-time buyer",(IF(A72>145000,MIN(600,0.02*(MIN(A72,175000)-145000)),0)),0)+IF(Inputs!B8="Additional / Investor",0.08*A72,0)),IF(Inputs!B7="Wales",(IF(Inputs!B8="Additional / Investor",(MIN(A72,180000)*0.05+MAX(0,MIN(A72,250000)-180000)*0.085+MAX(0,MIN(A72,400000)-250000)*0.1+MAX(0,MIN(A72,750000)-400000)*0.125+MAX(0,MIN(A72,1500000)-750000)*0.15+MAX(0,A72-1500000)*0.17),(MAX(0,MIN(A72,400000)-225000)*0.06+MAX(0,MIN(A72,750000)-400000)*0.075+MAX(0,MIN(A72,1500000)-750000)*0.1+MAX(0,A72-1500000)*0.12))),0)))))+(Inputs!B14+Inputs!B15+Inputs!B16+Inputs!B17)+(Summary!B14)+(Summary!B15)+(((((A72)*Inputs!B20)+(IF(Inputs!B24="Yes",(Summary!B14)*Inputs!B25,0))*Inputs!B26)*Inputs!B21*Inputs!B10/12)+((((A72)*Inputs!B20)+(IF(Inputs!B24="Yes",(Summary!B14)*Inputs!B25,0)))*Inputs!B22)+((((A72)*Inputs!B20)+(IF(Inputs!B24="Yes",(Summary!B14)*Inputs!B25,0)))*Inputs!B23))+(Summary!B17))) -> -180437.5 | C72: =IF(A72>$B$6,"","")
A73: =$B$5+(62)*$B$7 -> 410000 | B73: =IF(A73>$B$6,"",(Inputs!B6)-((A73)+(IF(Inputs!D13<>"",Inputs!D13,IF(Inputs!B7="England & N. Ireland",(IF(Inputs!B8="First-time buyer",(IF(A73<=500000,MAX(0,A73-300000)*0.05,(MAX(0,MIN(A73,250000)-125000)*0.02+MAX(0,MIN(A73,925000)-250000)*0.05+MAX(0,MIN(A73,1500000)-925000)*0.1+MAX(0,A73-1500000)*0.12))),(MAX(0,MIN(A73,250000)-125000)*0.02+MAX(0,MIN(A73,925000)-250000)*0.05+MAX(0,MIN(A73,1500000)-925000)*0.1+MAX(0,A73-1500000)*0.12)+IF(Inputs!B8="Additional / Investor",0.05*A73,0)+IF(Inputs!B9="Yes",0.02*A73,0))),IF(Inputs!B7="Scotland",((MAX(0,MIN(A73,250000)-145000)*0.02+MAX(0,MIN(A73,325000)-250000)*0.05+MAX(0,MIN(A73,750000)-325000)*0.1+MAX(0,A73-750000)*0.12)-IF(Inputs!B8="First-time buyer",(IF(A73>145000,MIN(600,0.02*(MIN(A73,175000)-145000)),0)),0)+IF(Inputs!B8="Additional / Investor",0.08*A73,0)),IF(Inputs!B7="Wales",(IF(Inputs!B8="Additional / Investor",(MIN(A73,180000)*0.05+MAX(0,MIN(A73,250000)-180000)*0.085+MAX(0,MIN(A73,400000)-250000)*0.1+MAX(0,MIN(A73,750000)-400000)*0.125+MAX(0,MIN(A73,1500000)-750000)*0.15+MAX(0,A73-1500000)*0.17),(MAX(0,MIN(A73,400000)-225000)*0.06+MAX(0,MIN(A73,750000)-400000)*0.075+MAX(0,MIN(A73,1500000)-750000)*0.1+MAX(0,A73-1500000)*0.12))),0)))))+(Inputs!B14+Inputs!B15+Inputs!B16+Inputs!B17)+(Summary!B14)+(Summary!B15)+(((((A73)*Inputs!B20)+(IF(Inputs!B24="Yes",(Summary!B14)*Inputs!B25,0))*Inputs!B26)*Inputs!B21*Inputs!B10/12)+((((A73)*Inputs!B20)+(IF(Inputs!B24="Yes",(Summary!B14)*Inputs!B25,0)))*Inputs!B22)+((((A73)*Inputs!B20)+(IF(Inputs!B24="Yes",(Summary!B14)*Inputs!B25,0)))*Inputs!B23))+(Summary!B17))) -> -186275 | C73: =IF(A73>$B$6,"","")
A74: =$B$5+(63)*$B$7 -> 415000 | B74: =IF(A74>$B$6,"",(Inputs!B6)-((A74)+(IF(Inputs!D13<>"",Inputs!D13,IF(Inputs!B7="England & N. Ireland",(IF(Inputs!B8="First-time buyer",(IF(A74<=500000,MAX(0,A74-300000)*0.05,(MAX(0,MIN(A74,250000)-125000)*0.02+MAX(0,MIN(A74,925000)-250000)*0.05+MAX(0,MIN(A74,1500000)-925000)*0.1+MAX(0,A74-1500000)*0.12))),(MAX(0,MIN(A74,250000)-125000)*0.02+MAX(0,MIN(A74,925000)-250000)*0.05+MAX(0,MIN(A74,1500000)-925000)*0.1+MAX(0,A74-1500000)*0.12)+IF(Inputs!B8="Additional / Investor",0.05*A74,0)+IF(Inputs!B9="Yes",0.02*A74,0))),IF(Inputs!B7="Scotland",((MAX(0,MIN(A74,250000)-145000)*0.02+MAX(0,MIN(A74,325000)-250000)*0.05+MAX(0,MIN(A74,750000)-325000)*0.1+MAX(0,A74-750000)*0.12)-IF(Inputs!B8="First-time buyer",(IF(A74>145000,MIN(600,0.02*(MIN(A74,175000)-145000)),0)),0)+IF(Inputs!B8="Additional / Investor",0.08*A74,0)),IF(Inputs!B7="Wales",(IF(Inputs!B8="Additional / Investor",(MIN(A74,180000)*0.05+MAX(0,MIN(A74,250000)-180000)*0.085+MAX(0,MIN(A74,400000)-250000)*0.1+MAX(0,MIN(A74,750000)-400000)*0.125+MAX(0,MIN(A74,1500000)-750000)*0.15+MAX(0,A74-1500000)*0.17),(MAX(0,MIN(A74,400000)-225000)*0.06+MAX(0,MIN(A74,750000)-400000)*0.075+MAX(0,MIN(A74,1500000)-750000)*0.1+MAX(0,A74-1500000)*0.12))),0)))))+(Inputs!B14+Inputs!B15+Inputs!B16+Inputs!B17)+(Summary!B14)+(Summary!B15)+(((((A74)*Inputs!B20)+(IF(Inputs!B24="Yes",(Summary!B14)*Inputs!B25,0))*Inputs!B26)*Inputs!B21*Inputs!B10/12)+((((A74)*Inputs!B20)+(IF(Inputs!B24="Yes",(Summary!B14)*Inputs!B25,0)))*Inputs!B22)+((((A74)*Inputs!B20)+(IF(Inputs!B24="Yes",(Summary!B14)*Inputs!B25,0)))*Inputs!B23))+(Summary!B17))) -> -192112.5 | C74: =IF(A74>$B$6,"","")
A75: =$B$5+(64)*$B$7 -> 420000 | B75: =IF(A75>$B$6,"",(Inputs!B6)-((A75)+(IF(Inputs!D13<>"",Inputs!D13,IF(Inputs!B7="England & N. Ireland",(IF(Inputs!B8="First-time buyer",(IF(A75<=500000,MAX(0,A75-300000)*0.05,(MAX(0,MIN(A75,250000)-125000)*0.02+MAX(0,MIN(A75,925000)-250000)*0.05+MAX(0,MIN(A75,1500000)-925000)*0.1+MAX(0,A75-1500000)*0.12))),(MAX(0,MIN(A75,250000)-125000)*0.02+MAX(0,MIN(A75,925000)-250000)*0.05+MAX(0,MIN(A75,1500000)-925000)*0.1+MAX(0,A75-1500000)*0.12)+IF(Inputs!B8="Additional / Investor",0.05*A75,0)+IF(Inputs!B9="Yes",0.02*A75,0))),IF(Inputs!B7="Scotland",((MAX(0,MIN(A75,250000)-145000)*0.02+MAX(0,MIN(A75,325000)-250000)*0.05+MAX(0,MIN(A75,750000)-325000)*0.1+MAX(0,A75-750000)*0.12)-IF(Inputs!B8="First-time buyer",(IF(A75>145000,MIN(600,0.02*(MIN(A75,175000)-145000)),0)),0)+IF(Inputs!B8="Additional / Investor",0.08*A75,0)),IF(Inputs!B7="Wales",(IF(Inputs!B8="Additional / Investor",(MIN(A75,180000)*0.05+MAX(0,MIN(A75,250000)-180000)*0.085+MAX(0,MIN(A75,400000)-250000)*0.1+MAX(0,MIN(A75,750000)-400000)*0.125+MAX(0,MIN(A75,1500000)-750000)*0.15+MAX(0,A75-1500000)*0.17),(MAX(0,MIN(A75,400000)-225000)*0.06+MAX(0,MIN(A75,750000)-400000)*0.075+MAX(0,MIN(A75,1500000)-750000)*0.1+MAX(0,A75-1500000)*0.12))),0)))))+(Inputs!B14+Inputs!B15+Inputs!B16+Inputs!B17)+(Summary!B14)+(Summary!B15)+(((((A75)*Inputs!B20)+(IF(Inputs!B24="Yes",(Summary!B14)*Inputs!B25,0))*Inputs!B26)*Inputs!B21*Inputs!B10/12)+((((A75)*Inputs!B20)+(IF(Inputs!B24="Yes",(Summary!B14)*Inputs!B25,0)))*Inputs!B22)+((((A75)*Inputs!B20)+(IF(Inputs!B24="Yes",(Summary!B14)*Inputs!B25,0)))*Inputs!B23))+(Summary!B17))) -> -197950 | C75: =IF(A75>$B$6,"","")
A76: =$B$5+(65)*$B$7 -> 425000 | B76: =IF(A76>$B$6,"",(Inputs!B6)-((A76)+(IF(Inputs!D13<>"",Inputs!D13,IF(Inputs!B7="England & N. Ireland",(IF(Inputs!B8="First-time buyer",(IF(A76<=500000,MAX(0,A76-300000)*0.05,(MAX(0,MIN(A76,250000)-125000)*0.02+MAX(0,MIN(A76,925000)-250000)*0.05+MAX(0,MIN(A76,1500000)-925000)*0.1+MAX(0,A76-1500000)*0.12))),(MAX(0,MIN(A76,250000)-125000)*0.02+MAX(0,MIN(A76,925000)-250000)*0.05+MAX(0,MIN(A76,1500000)-925000)*0.1+MAX(0,A76-1500000)*0.12)+IF(Inputs!B8="Additional / Investor",0.05*A76,0)+IF(Inputs!B9="Yes",0.02*A76,0))),IF(Inputs!B7="Scotland",((MAX(0,MIN(A76,250000)-145000)*0.02+MAX(0,MIN(A76,325000)-250000)*0.05+MAX(0,MIN(A76,750000)-325000)*0.1+MAX(0,A76-750000)*0.12)-IF(Inputs!B8="First-time buyer",(IF(A76>145000,MIN(600,0.02*(MIN(A76,175000)-145000)),0)),0)+IF(Inputs!B8="Additional / Investor",0.08*A76,0)),IF(Inputs!B7="Wales",(IF(Inputs!B8="Additional / Investor",(MIN(A76,180000)*0.05+MAX(0,MIN(A76,250000)-180000)*0.085+MAX(0,MIN(A76,400000)-250000)*0.1+MAX(0,MIN(A76,750000)-400000)*0.125+MAX(0,MIN(A76,1500000)-750000)*0.15+MAX(0,A76-1500000)*0.17),(MAX(0,MIN(A76,400000)-225000)*0.06+MAX(0,MIN(A76,750000)-400000)*0.075+MAX(0,MIN(A76,1500000)-750000)*0.1+MAX(0,A76-1500000)*0.12))),0)))))+(Inputs!B14+Inputs!B15+Inputs!B16+Inputs!B17)+(Summary!B14)+(Summary!B15)+(((((A76)*Inputs!B20)+(IF(Inputs!B24="Yes",(Summary!B14)*Inputs!B25,0))*Inputs!B26)*Inputs!B21*Inputs!B10/12)+((((A76)*Inputs!B20)+(IF(Inputs!B24="Yes",(Summary!B14)*Inputs!B25,0)))*Inputs!B22)+((((A76)*Inputs!B20)+(IF(Inputs!B24="Yes",(Summary!B14)*Inputs!B25,0)))*Inputs!B23))+(Summary!B17))) -> -203787.5 | C76: =IF(A76>$B$6,"","")
A77: =$B$5+(66)*$B$7 -> 430000 | B77: =IF(A77>$B$6,"",(Inputs!B6)-((A77)+(IF(Inputs!D13<>"",Inputs!D13,IF(Inputs!B7="England & N. Ireland",(IF(Inputs!B8="First-time buyer",(IF(A77<=500000,MAX(0,A77-300000)*0.05,(MAX(0,MIN(A77,250000)-125000)*0.02+MAX(0,MIN(A77,925000)-250000)*0.05+MAX(0,MIN(A77,1500000)-925000)*0.1+MAX(0,A77-1500000)*0.12))),(MAX(0,MIN(A77,250000)-125000)*0.02+MAX(0,MIN(A77,925000)-250000)*0.05+MAX(0,MIN(A77,1500000)-925000)*0.1+MAX(0,A77-1500000)*0.12)+IF(Inputs!B8="Additional / Investor",0.05*A77,0)+IF(Inputs!B9="Yes",0.02*A77,0))),IF(Inputs!B7="Scotland",((MAX(0,MIN(A77,250000)-145000)*0.02+MAX(0,MIN(A77,325000)-250000)*0.05+MAX(0,MIN(A77,750000)-325000)*0.1+MAX(0,A77-750000)*0.12)-IF(Inputs!B8="First-time buyer",(IF(A77>145000,MIN(600,0.02*(MIN(A77,175000)-145000)),0)),0)+IF(Inputs!B8="Additional / Investor",0.08*A77,0)),IF(Inputs!B7="Wales",(IF(Inputs!B8="Additional / Investor",(MIN(A77,180000)*0.05+MAX(0,MIN(A77,250000)-180000)*0.085+MAX(0,MIN(A77,400000)-250000)*0.1+MAX(0,MIN(A77,750000)-400000)*0.125+MAX(0,MIN(A77,1500000)-750000)*0.15+MAX(0,A77-1500000)*0.17),(MAX(0,MIN(A77,400000)-225000)*0.06+MAX(0,MIN(A77,750000)-400000)*0.075+MAX(0,MIN(A77,1500000)-750000)*0.1+MAX(0,A77-1500000)*0.12))),0)))))+(Inputs!B14+Inputs!B15+Inputs!B16+Inputs!B17)+(Summary!B14)+(Summary!B15)+(((((A77)*Inputs!B20)+(IF(Inputs!B24="Yes",(Summary!B14)*Inputs!B25,0))*Inputs!B26)*Inputs!B21*Inputs!B10/12)+((((A77)*Inputs!B20)+(IF(Inputs!B24="Yes",(Summary!B14)*Inputs!B25,0)))*Inputs!B22)+((((A77)*Inputs!B20)+(IF(Inputs!B24="Yes",(Summary!B14)*Inputs!B25,0)))*Inputs!B23))+(Summary!B17))) -> -209625 | C77: =IF(A77>$B$6,"","")
A78: =$B$5+(67)*$B$7 -> 435000 | B78: =IF(A78>$B$6,"",(Inputs!B6)-((A78)+(IF(Inputs!D13<>"",Inputs!D13,IF(Inputs!B7="England & N. Ireland",(IF(Inputs!B8="First-time buyer",(IF(A78<=500000,MAX(0,A78-300000)*0.05,(MAX(0,MIN(A78,250000)-125000)*0.02+MAX(0,MIN(A78,925000)-250000)*0.05+MAX(0,MIN(A78,1500000)-925000)*0.1+MAX(0,A78-1500000)*0.12))),(MAX(0,MIN(A78,250000)-125000)*0.02+MAX(0,MIN(A78,925000)-250000)*0.05+MAX(0,MIN(A78,1500000)-925000)*0.1+MAX(0,A78-1500000)*0.12)+IF(Inputs!B8="Additional / Investor",0.05*A78,0)+IF(Inputs!B9="Yes",0.02*A78,0))),IF(Inputs!B7="Scotland",((MAX(0,MIN(A78,250000)-145000)*0.02+MAX(0,MIN(A78,325000)-250000)*0.05+MAX(0,MIN(A78,750000)-325000)*0.1+MAX(0,A78-750000)*0.12)-IF(Inputs!B8="First-time buyer",(IF(A78>145000,MIN(600,0.02*(MIN(A78,175000)-145000)),0)),0)+IF(Inputs!B8="Additional / Investor",0.08*A78,0)),IF(Inputs!B7="Wales",(IF(Inputs!B8="Additional / Investor",(MIN(A78,180000)*0.05+MAX(0,MIN(A78,250000)-180000)*0.085+MAX(0,MIN(A78,400000)-250000)*0.1+MAX(0,MIN(A78,750000)-400000)*0.125+MAX(0,MIN(A78,1500000)-750000)*0.15+MAX(0,A78-1500000)*0.17),(MAX(0,MIN(A78,400000)-225000)*0.06+MAX(0,MIN(A78,750000)-400000)*0.075+MAX(0,MIN(A78,1500000)-750000)*0.1+MAX(0,A78-1500000)*0.12))),0)))))+(Inputs!B14+Inputs!B15+Inputs!B16+Inputs!B17)+(Summary!B14)+(Summary!B15)+(((((A78)*Inputs!B20)+(IF(Inputs!B24="Yes",(Summary!B14)*Inputs!B25,0))*Inputs!B26)*Inputs!B21*Inputs!B10/12)+((((A78)*Inputs!B20)+(IF(Inputs!B24="Yes",(Summary!B14)*Inputs!B25,0)))*Inputs!B22)+((((A78)*Inputs!B20)+(IF(Inputs!B24="Yes",(Summary!B14)*Inputs!B25,0)))*Inputs!B23))+(Summary!B17))) -> -215462.5 | C78: =IF(A78>$B$6,"","")
A79: =$B$5+(68)*$B$7 -> 440000 | B79: =IF(A79>$B$6,"",(Inputs!B6)-((A79)+(IF(Inputs!D13<>"",Inputs!D13,IF(Inputs!B7="England & N. Ireland",(IF(Inputs!B8="First-time buyer",(IF(A79<=500000,MAX(0,A79-300000)*0.05,(MAX(0,MIN(A79,250000)-125000)*0.02+MAX(0,MIN(A79,925000)-250000)*0.05+MAX(0,MIN(A79,1500000)-925000)*0.1+MAX(0,A79-1500000)*0.12))),(MAX(0,MIN(A79,250000)-125000)*0.02+MAX(0,MIN(A79,925000)-250000)*0.05+MAX(0,MIN(A79,1500000)-925000)*0.1+MAX(0,A79-1500000)*0.12)+IF(Inputs!B8="Additional / Investor",0.05*A79,0)+IF(Inputs!B9="Yes",0.02*A79,0))),IF(Inputs!B7="Scotland",((MAX(0,MIN(A79,250000)-145000)*0.02+MAX(0,MIN(A79,325000)-250000)*0.05+MAX(0,MIN(A79,750000)-325000)*0.1+MAX(0,A79-750000)*0.12)-IF(Inputs!B8="First-time buyer",(IF(A79>145000,MIN(600,0.02*(MIN(A79,175000)-145000)),0)),0)+IF(Inputs!B8="Additional / Investor",0.08*A79,0)),IF(Inputs!B7="Wales",(IF(Inputs!B8="Additional / Investor",(MIN(A79,180000)*0.05+MAX(0,MIN(A79,250000)-180000)*0.085+MAX(0,MIN(A79,400000)-250000)*0.1+MAX(0,MIN(A79,750000)-400000)*0.125+MAX(0,MIN(A79,1500000)-750000)*0.15+MAX(0,A79-1500000)*0.17),(MAX(0,MIN(A79,400000)-225000)*0.06+MAX(0,MIN(A79,750000)-400000)*0.075+MAX(0,MIN(A79,1500000)-750000)*0.1+MAX(0,A79-1500000)*0.12))),0)))))+(Inputs!B14+Inputs!B15+Inputs!B16+Inputs!B17)+(Summary!B14)+(Summary!B15)+(((((A79)*Inputs!B20)+(IF(Inputs!B24="Yes",(Summary!B14)*Inputs!B25,0))*Inputs!B26)*Inputs!B21*Inputs!B10/12)+((((A79)*Inputs!B20)+(IF(Inputs!B24="Yes",(Summary!B14)*Inputs!B25,0)))*Inputs!B22)+((((A79)*Inputs!B20)+(IF(Inputs!B24="Yes",(Summary!B14)*Inputs!B25,0)))*Inputs!B23))+(Summary!B17))) -> -221300 | C79: =IF(A79>$B$6,"","")
A80: =$B$5+(69)*$B$7 -> 445000 | B80: =IF(A80>$B$6,"",(Inputs!B6)-((A80)+(IF(Inputs!D13<>"",Inputs!D13,IF(Inputs!B7="England & N. Ireland",(IF(Inputs!B8="First-time buyer",(IF(A80<=500000,MAX(0,A80-300000)*0.05,(MAX(0,MIN(A80,250000)-125000)*0.02+MAX(0,MIN(A80,925000)-250000)*0.05+MAX(0,MIN(A80,1500000)-925000)*0.1+MAX(0,A80-1500000)*0.12))),(MAX(0,MIN(A80,250000)-125000)*0.02+MAX(0,MIN(A80,925000)-250000)*0.05+MAX(0,MIN(A80,1500000)-925000)*0.1+MAX(0,A80-1500000)*0.12)+IF(Inputs!B8="Additional / Investor",0.05*A80,0)+IF(Inputs!B9="Yes",0.02*A80,0))),IF(Inputs!B7="Scotland",((MAX(0,MIN(A80,250000)-145000)*0.02+MAX(0,MIN(A80,325000)-250000)*0.05+MAX(0,MIN(A80,750000)-325000)*0.1+MAX(0,A80-750000)*0.12)-IF(Inputs!B8="First-time buyer",(IF(A80>145000,MIN(600,0.02*(MIN(A80,175000)-145000)),0)),0)+IF(Inputs!B8="Additional / Investor",0.08*A80,0)),IF(Inputs!B7="Wales",(IF(Inputs!B8="Additional / Investor",(MIN(A80,180000)*0.05+MAX(0,MIN(A80,250000)-180000)*0.085+MAX(0,MIN(A80,400000)-250000)*0.1+MAX(0,MIN(A80,750000)-400000)*0.125+MAX(0,MIN(A80,1500000)-750000)*0.15+MAX(0,A80-1500000)*0.17),(MAX(0,MIN(A80,400000)-225000)*0.06+MAX(0,MIN(A80,750000)-400000)*0.075+MAX(0,MIN(A80,1500000)-750000)*0.1+MAX(0,A80-1500000)*0.12))),0)))))+(Inputs!B14+Inputs!B15+Inputs!B16+Inputs!B17)+(Summary!B14)+(Summary!B15)+(((((A80)*Inputs!B20)+(IF(Inputs!B24="Yes",(Summary!B14)*Inputs!B25,0))*Inputs!B26)*Inputs!B21*Inputs!B10/12)+((((A80)*Inputs!B20)+(IF(Inputs!B24="Yes",(Summary!B14)*Inputs!B25,0)))*Inputs!B22)+((((A80)*Inputs!B20)+(IF(Inputs!B24="Yes",(Summary!B14)*Inputs!B25,0)))*Inputs!B23))+(Summary!B17))) -> -227137.5 | C80: =IF(A80>$B$6,"","")
A81: =$B$5+(70)*$B$7 -> 450000 | B81: =IF(A81>$B$6,"",(Inputs!B6)-((A81)+(IF(Inputs!D13<>"",Inputs!D13,IF(Inputs!B7="England & N. Ireland",(IF(Inputs!B8="First-time buyer",(IF(A81<=500000,MAX(0,A81-300000)*0.05,(MAX(0,MIN(A81,250000)-125000)*0.02+MAX(0,MIN(A81,925000)-250000)*0.05+MAX(0,MIN(A81,1500000)-925000)*0.1+MAX(0,A81-1500000)*0.12))),(MAX(0,MIN(A81,250000)-125000)*0.02+MAX(0,MIN(A81,925000)-250000)*0.05+MAX(0,MIN(A81,1500000)-925000)*0.1+MAX(0,A81-1500000)*0.12)+IF(Inputs!B8="Additional / Investor",0.05*A81,0)+IF(Inputs!B9="Yes",0.02*A81,0))),IF(Inputs!B7="Scotland",((MAX(0,MIN(A81,250000)-145000)*0.02+MAX(0,MIN(A81,325000)-250000)*0.05+MAX(0,MIN(A81,750000)-325000)*0.1+MAX(0,A81-750000)*0.12)-IF(Inputs!B8="First-time buyer",(IF(A81>145000,MIN(600,0.02*(MIN(A81,175000)-145000)),0)),0)+IF(Inputs!B8="Additional / Investor",0.08*A81,0)),IF(Inputs!B7="Wales",(IF(Inputs!B8="Additional / Investor",(MIN(A81,180000)*0.05+MAX(0,MIN(A81,250000)-180000)*0.085+MAX(0,MIN(A81,400000)-250000)*0.1+MAX(0,MIN(A81,750000)-400000)*0.125+MAX(0,MIN(A81,1500000)-750000)*0.15+MAX(0,A81-1500000)*0.17),(MAX(0,MIN(A81,400000)-225000)*0.06+MAX(0,MIN(A81,750000)-400000)*0.075+MAX(0,MIN(A81,1500000)-750000)*0.1+MAX(0,A81-1500000)*0.12))),0)))))+(Inputs!B14+Inputs!B15+Inputs!B16+Inputs!B17)+(Summary!B14)+(Summary!B15)+(((((A81)*Inputs!B20)+(IF(Inputs!B24="Yes",(Summary!B14)*Inputs!B25,0))*Inputs!B26)*Inputs!B21*Inputs!B10/12)+((((A81)*Inputs!B20)+(IF(Inputs!B24="Yes",(Summary!B14)*Inputs!B25,0)))*Inputs!B22)+((((A81)*Inputs!B20)+(IF(Inputs!B24="Yes",(Summary!B14)*Inputs!B25,0)))*Inputs!B23))+(Summary!B17))) -> -232975 | C81: =IF(A81>$B$6,"","")
A82: =$B$5+(71)*$B$7 -> 455000 | B82: =IF(A82>$B$6,"",(Inputs!B6)-((A82)+(IF(Inputs!D13<>"",Inputs!D13,IF(Inputs!B7="England & N. Ireland",(IF(Inputs!B8="First-time buyer",(IF(A82<=500000,MAX(0,A82-300000)*0.05,(MAX(0,MIN(A82,250000)-125000)*0.02+MAX(0,MIN(A82,925000)-250000)*0.05+MAX(0,MIN(A82,1500000)-925000)*0.1+MAX(0,A82-1500000)*0.12))),(MAX(0,MIN(A82,250000)-125000)*0.02+MAX(0,MIN(A82,925000)-250000)*0.05+MAX(0,MIN(A82,1500000)-925000)*0.1+MAX(0,A82-1500000)*0.12)+IF(Inputs!B8="Additional / Investor",0.05*A82,0)+IF(Inputs!B9="Yes",0.02*A82,0))),IF(Inputs!B7="Scotland",((MAX(0,MIN(A82,250000)-145000)*0.02+MAX(0,MIN(A82,325000)-250000)*0.05+MAX(0,MIN(A82,750000)-325000)*0.1+MAX(0,A82-750000)*0.12)-IF(Inputs!B8="First-time buyer",(IF(A82>145000,MIN(600,0.02*(MIN(A82,175000)-145000)),0)),0)+IF(Inputs!B8="Additional / Investor",0.08*A82,0)),IF(Inputs!B7="Wales",(IF(Inputs!B8="Additional / Investor",(MIN(A82,180000)*0.05+MAX(0,MIN(A82,250000)-180000)*0.085+MAX(0,MIN(A82,400000)-250000)*0.1+MAX(0,MIN(A82,750000)-400000)*0.125+MAX(0,MIN(A82,1500000)-750000)*0.15+MAX(0,A82-1500000)*0.17),(MAX(0,MIN(A82,400000)-225000)*0.06+MAX(0,MIN(A82,750000)-400000)*0.075+MAX(0,MIN(A82,1500000)-750000)*0.1+MAX(0,A82-1500000)*0.12))),0)))))+(Inputs!B14+Inputs!B15+Inputs!B16+Inputs!B17)+(Summary!B14)+(Summary!B15)+(((((A82)*Inputs!B20)+(IF(Inputs!B24="Yes",(Summary!B14)*Inputs!B25,0))*Inputs!B26)*Inputs!B21*Inputs!B10/12)+((((A82)*Inputs!B20)+(IF(Inputs!B24="Yes",(Summary!B14)*Inputs!B25,0)))*Inputs!B22)+((((A82)*Inputs!B20)+(IF(Inputs!B24="Yes",(Summary!B14)*Inputs!B25,0)))*Inputs!B23))+(Summary!B17))) -> -238812.5 | C82: =IF(A82>$B$6,"","")
A83: =$B$5+(72)*$B$7 -> 460000 | B83: =IF(A83>$B$6,"",(Inputs!B6)-((A83)+(IF(Inputs!D13<>"",Inputs!D13,IF(Inputs!B7="England & N. Ireland",(IF(Inputs!B8="First-time buyer",(IF(A83<=500000,MAX(0,A83-300000)*0.05,(MAX(0,MIN(A83,250000)-125000)*0.02+MAX(0,MIN(A83,925000)-250000)*0.05+MAX(0,MIN(A83,1500000)-925000)*0.1+MAX(0,A83-1500000)*0.12))),(MAX(0,MIN(A83,250000)-125000)*0.02+MAX(0,MIN(A83,925000)-250000)*0.05+MAX(0,MIN(A83,1500000)-925000)*0.1+MAX(0,A83-1500000)*0.12)+IF(Inputs!B8="Additional / Investor",0.05*A83,0)+IF(Inputs!B9="Yes",0.02*A83,0))),IF(Inputs!B7="Scotland",((MAX(0,MIN(A83,250000)-145000)*0.02+MAX(0,MIN(A83,325000)-250000)*0.05+MAX(0,MIN(A83,750000)-325000)*0.1+MAX(0,A83-750000)*0.12)-IF(Inputs!B8="First-time buyer",(IF(A83>145000,MIN(600,0.02*(MIN(A83,175000)-145000)),0)),0)+IF(Inputs!B8="Additional / Investor",0.08*A83,0)),IF(Inputs!B7="Wales",(IF(Inputs!B8="Additional / Investor",(MIN(A83,180000)*0.05+MAX(0,MIN(A83,250000)-180000)*0.085+MAX(0,MIN(A83,400000)-250000)*0.1+MAX(0,MIN(A83,750000)-400000)*0.125+MAX(0,MIN(A83,1500000)-750000)*0.15+MAX(0,A83-1500000)*0.17),(MAX(0,MIN(A83,400000)-225000)*0.06+MAX(0,MIN(A83,750000)-400000)*0.075+MAX(0,MIN(A83,1500000)-750000)*0.1+MAX(0,A83-1500000)*0.12))),0)))))+(Inputs!B14+Inputs!B15+Inputs!B16+Inputs!B17)+(Summary!B14)+(Summary!B15)+(((((A83)*Inputs!B20)+(IF(Inputs!B24="Yes",(Summary!B14)*Inputs!B25,0))*Inputs!B26)*Inputs!B21*Inputs!B10/12)+((((A83)*Inputs!B20)+(IF(Inputs!B24="Yes",(Summary!B14)*Inputs!B25,0)))*Inputs!B22)+((((A83)*Inputs!B20)+(IF(Inputs!B24="Yes",(Summary!B14)*Inputs!B25,0)))*Inputs!B23))+(Summary!B17))) -> -244650 | C83: =IF(A83>$B$6,"","")
A84: =$B$5+(73)*$B$7 -> 465000 | B84: =IF(A84>$B$6,"",(Inputs!B6)-((A84)+(IF(Inputs!D13<>"",Inputs!D13,IF(Inputs!B7="England & N. Ireland",(IF(Inputs!B8="First-time buyer",(IF(A84<=500000,MAX(0,A84-300000)*0.05,(MAX(0,MIN(A84,250000)-125000)*0.02+MAX(0,MIN(A84,925000)-250000)*0.05+MAX(0,MIN(A84,1500000)-925000)*0.1+MAX(0,A84-1500000)*0.12))),(MAX(0,MIN(A84,250000)-125000)*0.02+MAX(0,MIN(A84,925000)-250000)*0.05+MAX(0,MIN(A84,1500000)-925000)*0.1+MAX(0,A84-1500000)*0.12)+IF(Inputs!B8="Additional / Investor",0.05*A84,0)+IF(Inputs!B9="Yes",0.02*A84,0))),IF(Inputs!B7="Scotland",((MAX(0,MIN(A84,250000)-145000)*0.02+MAX(0,MIN(A84,325000)-250000)*0.05+MAX(0,MIN(A84,750000)-325000)*0.1+MAX(0,A84-750000)*0.12)-IF(Inputs!B8="First-time buyer",(IF(A84>145000,MIN(600,0.02*(MIN(A84,175000)-145000)),0)),0)+IF(Inputs!B8="Additional / Investor",0.08*A84,0)),IF(Inputs!B7="Wales",(IF(Inputs!B8="Additional / Investor",(MIN(A84,180000)*0.05+MAX(0,MIN(A84,250000)-180000)*0.085+MAX(0,MIN(A84,400000)-250000)*0.1+MAX(0,MIN(A84,750000)-400000)*0.125+MAX(0,MIN(A84,1500000)-750000)*0.15+MAX(0,A84-1500000)*0.17),(MAX(0,MIN(A84,400000)-225000)*0.06+MAX(0,MIN(A84,750000)-400000)*0.075+MAX(0,MIN(A84,1500000)-750000)*0.1+MAX(0,A84-1500000)*0.12))),0)))))+(Inputs!B14+Inputs!B15+Inputs!B16+Inputs!B17)+(Summary!B14)+(Summary!B15)+(((((A84)*Inputs!B20)+(IF(Inputs!B24="Yes",(Summary!B14)*Inputs!B25,0))*Inputs!B26)*Inputs!B21*Inputs!B10/12)+((((A84)*Inputs!B20)+(IF(Inputs!B24="Yes",(Summary!B14)*Inputs!B25,0)))*Inputs!B22)+((((A84)*Inputs!B20)+(IF(Inputs!B24="Yes",(Summary!B14)*Inputs!B25,0)))*Inputs!B23))+(Summary!B17))) -> -250487.5 | C84: =IF(A84>$B$6,"","")
A85: =$B$5+(74)*$B$7 -> 470000 | B85: =IF(A85>$B$6,"",(Inputs!B6)-((A85)+(IF(Inputs!D13<>"",Inputs!D13,IF(Inputs!B7="England & N. Ireland",(IF(Inputs!B8="First-time buyer",(IF(A85<=500000,MAX(0,A85-300000)*0.05,(MAX(0,MIN(A85,250000)-125000)*0.02+MAX(0,MIN(A85,925000)-250000)*0.05+MAX(0,MIN(A85,1500000)-925000)*0.1+MAX(0,A85-1500000)*0.12))),(MAX(0,MIN(A85,250000)-125000)*0.02+MAX(0,MIN(A85,925000)-250000)*0.05+MAX(0,MIN(A85,1500000)-925000)*0.1+MAX(0,A85-1500000)*0.12)+IF(Inputs!B8="Additional / Investor",0.05*A85,0)+IF(Inputs!B9="Yes",0.02*A85,0))),IF(Inputs!B7="Scotland",((MAX(0,MIN(A85,250000)-145000)*0.02+MAX(0,MIN(A85,325000)-250000)*0.05+MAX(0,MIN(A85,750000)-325000)*0.1+MAX(0,A85-750000)*0.12)-IF(Inputs!B8="First-time buyer",(IF(A85>145000,MIN(600,0.02*(MIN(A85,175000)-145000)),0)),0)+IF(Inputs!B8="Additional / Investor",0.08*A85,0)),IF(Inputs!B7="Wales",(IF(Inputs!B8="Additional / Investor",(MIN(A85,180000)*0.05+MAX(0,MIN(A85,250000)-180000)*0.085+MAX(0,MIN(A85,400000)-250000)*0.1+MAX(0,MIN(A85,750000)-400000)*0.125+MAX(0,MIN(A85,1500000)-750000)*0.15+MAX(0,A85-1500000)*0.17),(MAX(0,MIN(A85,400000)-225000)*0.06+MAX(0,MIN(A85,750000)-400000)*0.075+MAX(0,MIN(A85,1500000)-750000)*0.1+MAX(0,A85-1500000)*0.12))),0)))))+(Inputs!B14+Inputs!B15+Inputs!B16+Inputs!B17)+(Summary!B14)+(Summary!B15)+(((((A85)*Inputs!B20)+(IF(Inputs!B24="Yes",(Summary!B14)*Inputs!B25,0))*Inputs!B26)*Inputs!B21*Inputs!B10/12)+((((A85)*Inputs!B20)+(IF(Inputs!B24="Yes",(Summary!B14)*Inputs!B25,0)))*Inputs!B22)+((((A85)*Inputs!B20)+(IF(Inputs!B24="Yes",(Summary!B14)*Inputs!B25,0)))*Inputs!B23))+(Summary!B17))) -> -256325 | C85: =IF(A85>$B$6,"","")
A86: =$B$5+(75)*$B$7 -> 475000 | B86: =IF(A86>$B$6,"",(Inputs!B6)-((A86)+(IF(Inputs!D13<>"",Inputs!D13,IF(Inputs!B7="England & N. Ireland",(IF(Inputs!B8="First-time buyer",(IF(A86<=500000,MAX(0,A86-300000)*0.05,(MAX(0,MIN(A86,250000)-125000)*0.02+MAX(0,MIN(A86,925000)-250000)*0.05+MAX(0,MIN(A86,1500000)-925000)*0.1+MAX(0,A86-1500000)*0.12))),(MAX(0,MIN(A86,250000)-125000)*0.02+MAX(0,MIN(A86,925000)-250000)*0.05+MAX(0,MIN(A86,1500000)-925000)*0.1+MAX(0,A86-1500000)*0.12)+IF(Inputs!B8="Additional / Investor",0.05*A86,0)+IF(Inputs!B9="Yes",0.02*A86,0))),IF(Inputs!B7="Scotland",((MAX(0,MIN(A86,250000)-145000)*0.02+MAX(0,MIN(A86,325000)-250000)*0.05+MAX(0,MIN(A86,750000)-325000)*0.1+MAX(0,A86-750000)*0.12)-IF(Inputs!B8="First-time buyer",(IF(A86>145000,MIN(600,0.02*(MIN(A86,175000)-145000)),0)),0)+IF(Inputs!B8="Additional / Investor",0.08*A86,0)),IF(Inputs!B7="Wales",(IF(Inputs!B8="Additional / Investor",(MIN(A86,180000)*0.05+MAX(0,MIN(A86,250000)-180000)*0.085+MAX(0,MIN(A86,400000)-250000)*0.1+MAX(0,MIN(A86,750000)-400000)*0.125+MAX(0,MIN(A86,1500000)-750000)*0.15+MAX(0,A86-1500000)*0.17),(MAX(0,MIN(A86,400000)-225000)*0.06+MAX(0,MIN(A86,750000)-400000)*0.075+MAX(0,MIN(A86,1500000)-750000)*0.1+MAX(0,A86-1500000)*0.12))),0)))))+(Inputs!B14+Inputs!B15+Inputs!B16+Inputs!B17)+(Summary!B14)+(Summary!B15)+(((((A86)*Inputs!B20)+(IF(Inputs!B24="Yes",(Summary!B14)*Inputs!B25,0))*Inputs!B26)*Inputs!B21*Inputs!B10/12)+((((A86)*Inputs!B20)+(IF(Inputs!B24="Yes",(Summary!B14)*Inputs!B25,0)))*Inputs!B22)+((((A86)*Inputs!B20)+(IF(Inputs!B24="Yes",(Summary!B14)*Inputs!B25,0)))*Inputs!B23))+(Summary!B17))) -> -262162.5 | C86: =IF(A86>$B$6,"","")
A87: =$B$5+(76)*$B$7 -> 480000 | B87: =IF(A87>$B$6,"",(Inputs!B6)-((A87)+(IF(Inputs!D13<>"",Inputs!D13,IF(Inputs!B7="England & N. Ireland",(IF(Inputs!B8="First-time buyer",(IF(A87<=500000,MAX(0,A87-300000)*0.05,(MAX(0,MIN(A87,250000)-125000)*0.02+MAX(0,MIN(A87,925000)-250000)*0.05+MAX(0,MIN(A87,1500000)-925000)*0.1+MAX(0,A87-1500000)*0.12))),(MAX(0,MIN(A87,250000)-125000)*0.02+MAX(0,MIN(A87,925000)-250000)*0.05+MAX(0,MIN(A87,1500000)-925000)*0.1+MAX(0,A87-1500000)*0.12)+IF(Inputs!B8="Additional / Investor",0.05*A87,0)+IF(Inputs!B9="Yes",0.02*A87,0))),IF(Inputs!B7="Scotland",((MAX(0,MIN(A87,250000)-145000)*0.02+MAX(0,MIN(A87,325000)-250000)*0.05+MAX(0,MIN(A87,750000)-325000)*0.1+MAX(0,A87-750000)*0.12)-IF(Inputs!B8="First-time buyer",(IF(A87>145000,MIN(600,0.02*(MIN(A87,175000)-145000)),0)),0)+IF(Inputs!B8="Additional / Investor",0.08*A87,0)),IF(Inputs!B7="Wales",(IF(Inputs!B8="Additional / Investor",(MIN(A87,180000)*0.05+MAX(0,MIN(A87,250000)-180000)*0.085+MAX(0,MIN(A87,400000)-250000)*0.1+MAX(0,MIN(A87,750000)-400000)*0.125+MAX(0,MIN(A87,1500000)-750000)*0.15+MAX(0,A87-1500000)*0.17),(MAX(0,MIN(A87,400000)-225000)*0.06+MAX(0,MIN(A87,750000)-400000)*0.075+MAX(0,MIN(A87,1500000)-750000)*0.1+MAX(0,A87-1500000)*0.12))),0)))))+(Inputs!B14+Inputs!B15+Inputs!B16+Inputs!B17)+(Summary!B14)+(Summary!B15)+(((((A87)*Inputs!B20)+(IF(Inputs!B24="Yes",(Summary!B14)*Inputs!B25,0))*Inputs!B26)*Inputs!B21*Inputs!B10/12)+((((A87)*Inputs!B20)+(IF(Inputs!B24="Yes",(Summary!B14)*Inputs!B25,0)))*Inputs!B22)+((((A87)*Inputs!B20)+(IF(Inputs!B24="Yes",(Summary!B14)*Inputs!B25,0)))*Inputs!B23))+(Summary!B17))) -> -268000 | C87: =IF(A87>$B$6,"","")
A88: =$B$5+(77)*$B$7 -> 485000 | B88: =IF(A88>$B$6,"",(Inputs!B6)-((A88)+(IF(Inputs!D13<>"",Inputs!D13,IF(Inputs!B7="England & N. Ireland",(IF(Inputs!B8="First-time buyer",(IF(A88<=500000,MAX(0,A88-300000)*0.05,(MAX(0,MIN(A88,250000)-125000)*0.02+MAX(0,MIN(A88,925000)-250000)*0.05+MAX(0,MIN(A88,1500000)-925000)*0.1+MAX(0,A88-1500000)*0.12))),(MAX(0,MIN(A88,250000)-125000)*0.02+MAX(0,MIN(A88,925000)-250000)*0.05+MAX(0,MIN(A88,1500000)-925000)*0.1+MAX(0,A88-1500000)*0.12)+IF(Inputs!B8="Additional / Investor",0.05*A88,0)+IF(Inputs!B9="Yes",0.02*A88,0))),IF(Inputs!B7="Scotland",((MAX(0,MIN(A88,250000)-145000)*0.02+MAX(0,MIN(A88,325000)-250000)*0.05+MAX(0,MIN(A88,750000)-325000)*0.1+MAX(0,A88-750000)*0.12)-IF(Inputs!B8="First-time buyer",(IF(A88>145000,MIN(600,0.02*(MIN(A88,175000)-145000)),0)),0)+IF(Inputs!B8="Additional / Investor",0.08*A88,0)),IF(Inputs!B7="Wales",(IF(Inputs!B8="Additional / Investor",(MIN(A88,180000)*0.05+MAX(0,MIN(A88,250000)-180000)*0.085+MAX(0,MIN(A88,400000)-250000)*0.1+MAX(0,MIN(A88,750000)-400000)*0.125+MAX(0,MIN(A88,1500000)-750000)*0.15+MAX(0,A88-1500000)*0.17),(MAX(0,MIN(A88,400000)-225000)*0.06+MAX(0,MIN(A88,750000)-400000)*0.075+MAX(0,MIN(A88,1500000)-750000)*0.1+MAX(0,A88-1500000)*0.12))),0)))))+(Inputs!B14+Inputs!B15+Inputs!B16+Inputs!B17)+(Summary!B14)+(Summary!B15)+(((((A88)*Inputs!B20)+(IF(Inputs!B24="Yes",(Summary!B14)*Inputs!B25,0))*Inputs!B26)*Inputs!B21*Inputs!B10/12)+((((A88)*Inputs!B20)+(IF(Inputs!B24="Yes",(Summary!B14)*Inputs!B25,0)))*Inputs!B22)+((((A88)*Inputs!B20)+(IF(Inputs!B24="Yes",(Summary!B14)*Inputs!B25,0)))*Inputs!B23))+(Summary!B17))) -> -273837.5 | C88: =IF(A88>$B$6,"","")
A89: =$B$5+(78)*$B$7 -> 490000 | B89: =IF(A89>$B$6,"",(Inputs!B6)-((A89)+(IF(Inputs!D13<>"",Inputs!D13,IF(Inputs!B7="England & N. Ireland",(IF(Inputs!B8="First-time buyer",(IF(A89<=500000,MAX(0,A89-300000)*0.05,(MAX(0,MIN(A89,250000)-125000)*0.02+MAX(0,MIN(A89,925000)-250000)*0.05+MAX(0,MIN(A89,1500000)-925000)*0.1+MAX(0,A89-1500000)*0.12))),(MAX(0,MIN(A89,250000)-125000)*0.02+MAX(0,MIN(A89,925000)-250000)*0.05+MAX(0,MIN(A89,1500000)-925000)*0.1+MAX(0,A89-1500000)*0.12)+IF(Inputs!B8="Additional / Investor",0.05*A89,0)+IF(Inputs!B9="Yes",0.02*A89,0))),IF(Inputs!B7="Scotland",((MAX(0,MIN(A89,250000)-145000)*0.02+MAX(0,MIN(A89,325000)-250000)*0.05+MAX(0,MIN(A89,750000)-325000)*0.1+MAX(0,A89-750000)*0.12)-IF(Inputs!B8="First-time buyer",(IF(A89>145000,MIN(600,0.02*(MIN(A89,175000)-145000)),0)),0)+IF(Inputs!B8="Additional / Investor",0.08*A89,0)),IF(Inputs!B7="Wales",(IF(Inputs!B8="Additional / Investor",(MIN(A89,180000)*0.05+MAX(0,MIN(A89,250000)-180000)*0.085+MAX(0,MIN(A89,400000)-250000)*0.1+MAX(0,MIN(A89,750000)-400000)*0.125+MAX(0,MIN(A89,1500000)-750000)*0.15+MAX(0,A89-1500000)*0.17),(MAX(0,MIN(A89,400000)-225000)*0.06+MAX(0,MIN(A89,750000)-400000)*0.075+MAX(0,MIN(A89,1500000)-750000)*0.1+MAX(0,A89-1500000)*0.12))),0)))))+(Inputs!B14+Inputs!B15+Inputs!B16+Inputs!B17)+(Summary!B14)+(Summary!B15)+(((((A89)*Inputs!B20)+(IF(Inputs!B24="Yes",(Summary!B14)*Inputs!B25,0))*Inputs!B26)*Inputs!B21*Inputs!B10/12)+((((A89)*Inputs!B20)+(IF(Inputs!B24="Yes",(Summary!B14)*Inputs!B25,0)))*Inputs!B22)+((((A89)*Inputs!B20)+(IF(Inputs!B24="Yes",(Summary!B14)*Inputs!B25,0)))*Inputs!B23))+(Summary!B17))) -> -279675 | C89: =IF(A89>$B$6,"","")
A90: =$B$5+(79)*$B$7 -> 495000 | B90: =IF(A90>$B$6,"",(Inputs!B6)-((A90)+(IF(Inputs!D13<>"",Inputs!D13,IF(Inputs!B7="England & N. Ireland",(IF(Inputs!B8="First-time buyer",(IF(A90<=500000,MAX(0,A90-300000)*0.05,(MAX(0,MIN(A90,250000)-125000)*0.02+MAX(0,MIN(A90,925000)-250000)*0.05+MAX(0,MIN(A90,1500000)-925000)*0.1+MAX(0,A90-1500000)*0.12))),(MAX(0,MIN(A90,250000)-125000)*0.02+MAX(0,MIN(A90,925000)-250000)*0.05+MAX(0,MIN(A90,1500000)-925000)*0.1+MAX(0,A90-1500000)*0.12)+IF(Inputs!B8="Additional / Investor",0.05*A90,0)+IF(Inputs!B9="Yes",0.02*A90,0))),IF(Inputs!B7="Scotland",((MAX(0,MIN(A90,250000)-145000)*0.02+MAX(0,MIN(A90,325000)-250000)*0.05+MAX(0,MIN(A90,750000)-325000)*0.1+MAX(0,A90-750000)*0.12)-IF(Inputs!B8="First-time buyer",(IF(A90>145000,MIN(600,0.02*(MIN(A90,175000)-145000)),0)),0)+IF(Inputs!B8="Additional / Investor",0.08*A90,0)),IF(Inputs!B7="Wales",(IF(Inputs!B8="Additional / Investor",(MIN(A90,180000)*0.05+MAX(0,MIN(A90,250000)-180000)*0.085+MAX(0,MIN(A90,400000)-250000)*0.1+MAX(0,MIN(A90,750000)-400000)*0.125+MAX(0,MIN(A90,1500000)-750000)*0.15+MAX(0,A90-1500000)*0.17),(MAX(0,MIN(A90,400000)-225000)*0.06+MAX(0,MIN(A90,750000)-400000)*0.075+MAX(0,MIN(A90,1500000)-750000)*0.1+MAX(0,A90-1500000)*0.12))),0)))))+(Inputs!B14+Inputs!B15+Inputs!B16+Inputs!B17)+(Summary!B14)+(Summary!B15)+(((((A90)*Inputs!B20)+(IF(Inputs!B24="Yes",(Summary!B14)*Inputs!B25,0))*Inputs!B26)*Inputs!B21*Inputs!B10/12)+((((A90)*Inputs!B20)+(IF(Inputs!B24="Yes",(Summary!B14)*Inputs!B25,0)))*Inputs!B22)+((((A90)*Inputs!B20)+(IF(Inputs!B24="Yes",(Summary!B14)*Inputs!B25,0)))*Inputs!B23))+(Summary!B17))) -> -285512.5 | C90: =IF(A90>$B$6,"","")
A91: =$B$5+(80)*$B$7 -> 500000 | B91: =IF(A91>$B$6,"",(Inputs!B6)-((A91)+(IF(Inputs!D13<>"",Inputs!D13,IF(Inputs!B7="England & N. Ireland",(IF(Inputs!B8="First-time buyer",(IF(A91<=500000,MAX(0,A91-300000)*0.05,(MAX(0,MIN(A91,250000)-125000)*0.02+MAX(0,MIN(A91,925000)-250000)*0.05+MAX(0,MIN(A91,1500000)-925000)*0.1+MAX(0,A91-1500000)*0.12))),(MAX(0,MIN(A91,250000)-125000)*0.02+MAX(0,MIN(A91,925000)-250000)*0.05+MAX(0,MIN(A91,1500000)-925000)*0.1+MAX(0,A91-1500000)*0.12)+IF(Inputs!B8="Additional / Investor",0.05*A91,0)+IF(Inputs!B9="Yes",0.02*A91,0))),IF(Inputs!B7="Scotland",((MAX(0,MIN(A91,250000)-145000)*0.02+MAX(0,MIN(A91,325000)-250000)*0.05+MAX(0,MIN(A91,750000)-325000)*0.1+MAX(0,A91-750000)*0.12)-IF(Inputs!B8="First-time buyer",(IF(A91>145000,MIN(600,0.02*(MIN(A91,175000)-145000)),0)),0)+IF(Inputs!B8="Additional / Investor",0.08*A91,0)),IF(Inputs!B7="Wales",(IF(Inputs!B8="Additional / Investor",(MIN(A91,180000)*0.05+MAX(0,MIN(A91,250000)-180000)*0.085+MAX(0,MIN(A91,400000)-250000)*0.1+MAX(0,MIN(A91,750000)-400000)*0.125+MAX(0,MIN(A91,1500000)-750000)*0.15+MAX(0,A91-1500000)*0.17),(MAX(0,MIN(A91,400000)-225000)*0.06+MAX(0,MIN(A91,750000)-400000)*0.075+MAX(0,MIN(A91,1500000)-750000)*0.1+MAX(0,A91-1500000)*0.12))),0)))))+(Inputs!B14+Inputs!B15+Inputs!B16+Inputs!B17)+(Summary!B14)+(Summary!B15)+(((((A91)*Inputs!B20)+(IF(Inputs!B24="Yes",(Summary!B14)*Inputs!B25,0))*Inputs!B26)*Inputs!B21*Inputs!B10/12)+((((A91)*Inputs!B20)+(IF(Inputs!B24="Yes",(Summary!B14)*Inputs!B25,0)))*Inputs!B22)+((((A91)*Inputs!B20)+(IF(Inputs!B24="Yes",(Summary!B14)*Inputs!B25,0)))*Inputs!B23))+(Summary!B17))) -> -291350 | C91: =IF(A91>$B$6,"","")
A92: =$B$5+(81)*$B$7 -> 505000 | B92: =IF(A92>$B$6,"",(Inputs!B6)-((A92)+(IF(Inputs!D13<>"",Inputs!D13,IF(Inputs!B7="England & N. Ireland",(IF(Inputs!B8="First-time buyer",(IF(A92<=500000,MAX(0,A92-300000)*0.05,(MAX(0,MIN(A92,250000)-125000)*0.02+MAX(0,MIN(A92,925000)-250000)*0.05+MAX(0,MIN(A92,1500000)-925000)*0.1+MAX(0,A92-1500000)*0.12))),(MAX(0,MIN(A92,250000)-125000)*0.02+MAX(0,MIN(A92,925000)-250000)*0.05+MAX(0,MIN(A92,1500000)-925000)*0.1+MAX(0,A92-1500000)*0.12)+IF(Inputs!B8="Additional / Investor",0.05*A92,0)+IF(Inputs!B9="Yes",0.02*A92,0))),IF(Inputs!B7="Scotland",((MAX(0,MIN(A92,250000)-145000)*0.02+MAX(0,MIN(A92,325000)-250000)*0.05+MAX(0,MIN(A92,750000)-325000)*0.1+MAX(0,A92-750000)*0.12)-IF(Inputs!B8="First-time buyer",(IF(A92>145000,MIN(600,0.02*(MIN(A92,175000)-145000)),0)),0)+IF(Inputs!B8="Additional / Investor",0.08*A92,0)),IF(Inputs!B7="Wales",(IF(Inputs!B8="Additional / Investor",(MIN(A92,180000)*0.05+MAX(0,MIN(A92,250000)-180000)*0.085+MAX(0,MIN(A92,400000)-250000)*0.1+MAX(0,MIN(A92,750000)-400000)*0.125+MAX(0,MIN(A92,1500000)-750000)*0.15+MAX(0,A92-1500000)*0.17),(MAX(0,MIN(A92,400000)-225000)*0.06+MAX(0,MIN(A92,750000)-400000)*0.075+MAX(0,MIN(A92,1500000)-750000)*0.1+MAX(0,A92-1500000)*0.12))),0)))))+(Inputs!B14+Inputs!B15+Inputs!B16+Inputs!B17)+(Summary!B14)+(Summary!B15)+(((((A92)*Inputs!B20)+(IF(Inputs!B24="Yes",(Summary!B14)*Inputs!B25,0))*Inputs!B26)*Inputs!B21*Inputs!B10/12)+((((A92)*Inputs!B20)+(IF(Inputs!B24="Yes",(Summary!B14)*Inputs!B25,0)))*Inputs!B22)+((((A92)*Inputs!B20)+(IF(Inputs!B24="Yes",(Summary!B14)*Inputs!B25,0)))*Inputs!B23))+(Summary!B17))) -> -297187.5 | C92: =IF(A92>$B$6,"","")
A93: =$B$5+(82)*$B$7 -> 510000 | B93: =IF(A93>$B$6,"",(Inputs!B6)-((A93)+(IF(Inputs!D13<>"",Inputs!D13,IF(Inputs!B7="England & N. Ireland",(IF(Inputs!B8="First-time buyer",(IF(A93<=500000,MAX(0,A93-300000)*0.05,(MAX(0,MIN(A93,250000)-125000)*0.02+MAX(0,MIN(A93,925000)-250000)*0.05+MAX(0,MIN(A93,1500000)-925000)*0.1+MAX(0,A93-1500000)*0.12))),(MAX(0,MIN(A93,250000)-125000)*0.02+MAX(0,MIN(A93,925000)-250000)*0.05+MAX(0,MIN(A93,1500000)-925000)*0.1+MAX(0,A93-1500000)*0.12)+IF(Inputs!B8="Additional / Investor",0.05*A93,0)+IF(Inputs!B9="Yes",0.02*A93,0))),IF(Inputs!B7="Scotland",((MAX(0,MIN(A93,250000)-145000)*0.02+MAX(0,MIN(A93,325000)-250000)*0.05+MAX(0,MIN(A93,750000)-325000)*0.1+MAX(0,A93-750000)*0.12)-IF(Inputs!B8="First-time buyer",(IF(A93>145000,MIN(600,0.02*(MIN(A93,175000)-145000)),0)),0)+IF(Inputs!B8="Additional / Investor",0.08*A93,0)),IF(Inputs!B7="Wales",(IF(Inputs!B8="Additional / Investor",(MIN(A93,180000)*0.05+MAX(0,MIN(A93,250000)-180000)*0.085+MAX(0,MIN(A93,400000)-250000)*0.1+MAX(0,MIN(A93,750000)-400000)*0.125+MAX(0,MIN(A93,1500000)-750000)*0.15+MAX(0,A93-1500000)*0.17),(MAX(0,MIN(A93,400000)-225000)*0.06+MAX(0,MIN(A93,750000)-400000)*0.075+MAX(0,MIN(A93,1500000)-750000)*0.1+MAX(0,A93-1500000)*0.12))),0)))))+(Inputs!B14+Inputs!B15+Inputs!B16+Inputs!B17)+(Summary!B14)+(Summary!B15)+(((((A93)*Inputs!B20)+(IF(Inputs!B24="Yes",(Summary!B14)*Inputs!B25,0))*Inputs!B26)*Inputs!B21*Inputs!B10/12)+((((A93)*Inputs!B20)+(IF(Inputs!B24="Yes",(Summary!B14)*Inputs!B25,0)))*Inputs!B22)+((((A93)*Inputs!B20)+(IF(Inputs!B24="Yes",(Summary!B14)*Inputs!B25,0)))*Inputs!B23))+(Summary!B17))) -> -303025 | C93: =IF(A93>$B$6,"","")
A94: =$B$5+(83)*$B$7 -> 515000 | B94: =IF(A94>$B$6,"",(Inputs!B6)-((A94)+(IF(Inputs!D13<>"",Inputs!D13,IF(Inputs!B7="England & N. Ireland",(IF(Inputs!B8="First-time buyer",(IF(A94<=500000,MAX(0,A94-300000)*0.05,(MAX(0,MIN(A94,250000)-125000)*0.02+MAX(0,MIN(A94,925000)-250000)*0.05+MAX(0,MIN(A94,1500000)-925000)*0.1+MAX(0,A94-1500000)*0.12))),(MAX(0,MIN(A94,250000)-125000)*0.02+MAX(0,MIN(A94,925000)-250000)*0.05+MAX(0,MIN(A94,1500000)-925000)*0.1+MAX(0,A94-1500000)*0.12)+IF(Inputs!B8="Additional / Investor",0.05*A94,0)+IF(Inputs!B9="Yes",0.02*A94,0))),IF(Inputs!B7="Scotland",((MAX(0,MIN(A94,250000)-145000)*0.02+MAX(0,MIN(A94,325000)-250000)*0.05+MAX(0,MIN(A94,750000)-325000)*0.1+MAX(0,A94-750000)*0.12)-IF(Inputs!B8="First-time buyer",(IF(A94>145000,MIN(600,0.02*(MIN(A94,175000)-145000)),0)),0)+IF(Inputs!B8="Additional / Investor",0.08*A94,0)),IF(Inputs!B7="Wales",(IF(Inputs!B8="Additional / Investor",(MIN(A94,180000)*0.05+MAX(0,MIN(A94,250000)-180000)*0.085+MAX(0,MIN(A94,400000)-250000)*0.1+MAX(0,MIN(A94,750000)-400000)*0.125+MAX(0,MIN(A94,1500000)-750000)*0.15+MAX(0,A94-1500000)*0.17),(MAX(0,MIN(A94,400000)-225000)*0.06+MAX(0,MIN(A94,750000)-400000)*0.075+MAX(0,MIN(A94,1500000)-750000)*0.1+MAX(0,A94-1500000)*0.12))),0)))))+(Inputs!B14+Inputs!B15+Inputs!B16+Inputs!B17)+(Summary!B14)+(Summary!B15)+(((((A94)*Inputs!B20)+(IF(Inputs!B24="Yes",(Summary!B14)*Inputs!B25,0))*Inputs!B26)*Inputs!B21*Inputs!B10/12)+((((A94)*Inputs!B20)+(IF(Inputs!B24="Yes",(Summary!B14)*Inputs!B25,0)))*Inputs!B22)+((((A94)*Inputs!B20)+(IF(Inputs!B24="Yes",(Summary!B14)*Inputs!B25,0)))*Inputs!B23))+(Summary!B17))) -> -308862.5 | C94: =IF(A94>$B$6,"","")
A95: =$B$5+(84)*$B$7 -> 520000 | B95: =IF(A95>$B$6,"",(Inputs!B6)-((A95)+(IF(Inputs!D13<>"",Inputs!D13,IF(Inputs!B7="England & N. Ireland",(IF(Inputs!B8="First-time buyer",(IF(A95<=500000,MAX(0,A95-300000)*0.05,(MAX(0,MIN(A95,250000)-125000)*0.02+MAX(0,MIN(A95,925000)-250000)*0.05+MAX(0,MIN(A95,1500000)-925000)*0.1+MAX(0,A95-1500000)*0.12))),(MAX(0,MIN(A95,250000)-125000)*0.02+MAX(0,MIN(A95,925000)-250000)*0.05+MAX(0,MIN(A95,1500000)-925000)*0.1+MAX(0,A95-1500000)*0.12)+IF(Inputs!B8="Additional / Investor",0.05*A95,0)+IF(Inputs!B9="Yes",0.02*A95,0))),IF(Inputs!B7="Scotland",((MAX(0,MIN(A95,250000)-145000)*0.02+MAX(0,MIN(A95,325000)-250000)*0.05+MAX(0,MIN(A95,750000)-325000)*0.1+MAX(0,A95-750000)*0.12)-IF(Inputs!B8="First-time buyer",(IF(A95>145000,MIN(600,0.02*(MIN(A95,175000)-145000)),0)),0)+IF(Inputs!B8="Additional / Investor",0.08*A95,0)),IF(Inputs!B7="Wales",(IF(Inputs!B8="Additional / Investor",(MIN(A95,180000)*0.05+MAX(0,MIN(A95,250000)-180000)*0.085+MAX(0,MIN(A95,400000)-250000)*0.1+MAX(0,MIN(A95,750000)-400000)*0.125+MAX(0,MIN(A95,1500000)-750000)*0.15+MAX(0,A95-1500000)*0.17),(MAX(0,MIN(A95,400000)-225000)*0.06+MAX(0,MIN(A95,750000)-400000)*0.075+MAX(0,MIN(A95,1500000)-750000)*0.1+MAX(0,A95-1500000)*0.12))),0)))))+(Inputs!B14+Inputs!B15+Inputs!B16+Inputs!B17)+(Summary!B14)+(Summary!B15)+(((((A95)*Inputs!B20)+(IF(Inputs!B24="Yes",(Summary!B14)*Inputs!B25,0))*Inputs!B26)*Inputs!B21*Inputs!B10/12)+((((A95)*Inputs!B20)+(IF(Inputs!B24="Yes",(Summary!B14)*Inputs!B25,0)))*Inputs!B22)+((((A95)*Inputs!B20)+(IF(Inputs!B24="Yes",(Summary!B14)*Inputs!B25,0)))*Inputs!B23))+(Summary!B17))) -> -314700 | C95: =IF(A95>$B$6,"","")
A96: =$B$5+(85)*$B$7 -> 525000 | B96: =IF(A96>$B$6,"",(Inputs!B6)-((A96)+(IF(Inputs!D13<>"",Inputs!D13,IF(Inputs!B7="England & N. Ireland",(IF(Inputs!B8="First-time buyer",(IF(A96<=500000,MAX(0,A96-300000)*0.05,(MAX(0,MIN(A96,250000)-125000)*0.02+MAX(0,MIN(A96,925000)-250000)*0.05+MAX(0,MIN(A96,1500000)-925000)*0.1+MAX(0,A96-1500000)*0.12))),(MAX(0,MIN(A96,250000)-125000)*0.02+MAX(0,MIN(A96,925000)-250000)*0.05+MAX(0,MIN(A96,1500000)-925000)*0.1+MAX(0,A96-1500000)*0.12)+IF(Inputs!B8="Additional / Investor",0.05*A96,0)+IF(Inputs!B9="Yes",0.02*A96,0))),IF(Inputs!B7="Scotland",((MAX(0,MIN(A96,250000)-145000)*0.02+MAX(0,MIN(A96,325000)-250000)*0.05+MAX(0,MIN(A96,750000)-325000)*0.1+MAX(0,A96-750000)*0.12)-IF(Inputs!B8="First-time buyer",(IF(A96>145000,MIN(600,0.02*(MIN(A96,175000)-145000)),0)),0)+IF(Inputs!B8="Additional / Investor",0.08*A96,0)),IF(Inputs!B7="Wales",(IF(Inputs!B8="Additional / Investor",(MIN(A96,180000)*0.05+MAX(0,MIN(A96,250000)-180000)*0.085+MAX(0,MIN(A96,400000)-250000)*0.1+MAX(0,MIN(A96,750000)-400000)*0.125+MAX(0,MIN(A96,1500000)-750000)*0.15+MAX(0,A96-1500000)*0.17),(MAX(0,MIN(A96,400000)-225000)*0.06+MAX(0,MIN(A96,750000)-400000)*0.075+MAX(0,MIN(A96,1500000)-750000)*0.1+MAX(0,A96-1500000)*0.12))),0)))))+(Inputs!B14+Inputs!B15+Inputs!B16+Inputs!B17)+(Summary!B14)+(Summary!B15)+(((((A96)*Inputs!B20)+(IF(Inputs!B24="Yes",(Summary!B14)*Inputs!B25,0))*Inputs!B26)*Inputs!B21*Inputs!B10/12)+((((A96)*Inputs!B20)+(IF(Inputs!B24="Yes",(Summary!B14)*Inputs!B25,0)))*Inputs!B22)+((((A96)*Inputs!B20)+(IF(Inputs!B24="Yes",(Summary!B14)*Inputs!B25,0)))*Inputs!B23))+(Summary!B17))) -> -320537.5 | C96: =IF(A96>$B$6,"","")
A97: =$B$5+(86)*$B$7 -> 530000 | B97: =IF(A97>$B$6,"",(Inputs!B6)-((A97)+(IF(Inputs!D13<>"",Inputs!D13,IF(Inputs!B7="England & N. Ireland",(IF(Inputs!B8="First-time buyer",(IF(A97<=500000,MAX(0,A97-300000)*0.05,(MAX(0,MIN(A97,250000)-125000)*0.02+MAX(0,MIN(A97,925000)-250000)*0.05+MAX(0,MIN(A97,1500000)-925000)*0.1+MAX(0,A97-1500000)*0.12))),(MAX(0,MIN(A97,250000)-125000)*0.02+MAX(0,MIN(A97,925000)-250000)*0.05+MAX(0,MIN(A97,1500000)-925000)*0.1+MAX(0,A97-1500000)*0.12)+IF(Inputs!B8="Additional / Investor",0.05*A97,0)+IF(Inputs!B9="Yes",0.02*A97,0))),IF(Inputs!B7="Scotland",((MAX(0,MIN(A97,250000)-145000)*0.02+MAX(0,MIN(A97,325000)-250000)*0.05+MAX(0,MIN(A97,750000)-325000)*0.1+MAX(0,A97-750000)*0.12)-IF(Inputs!B8="First-time buyer",(IF(A97>145000,MIN(600,0.02*(MIN(A97,175000)-145000)),0)),0)+IF(Inputs!B8="Additional / Investor",0.08*A97,0)),IF(Inputs!B7="Wales",(IF(Inputs!B8="Additional / Investor",(MIN(A97,180000)*0.05+MAX(0,MIN(A97,250000)-180000)*0.085+MAX(0,MIN(A97,400000)-250000)*0.1+MAX(0,MIN(A97,750000)-400000)*0.125+MAX(0,MIN(A97,1500000)-750000)*0.15+MAX(0,A97-1500000)*0.17),(MAX(0,MIN(A97,400000)-225000)*0.06+MAX(0,MIN(A97,750000)-400000)*0.075+MAX(0,MIN(A97,1500000)-750000)*0.1+MAX(0,A97-1500000)*0.12))),0)))))+(Inputs!B14+Inputs!B15+Inputs!B16+Inputs!B17)+(Summary!B14)+(Summary!B15)+(((((A97)*Inputs!B20)+(IF(Inputs!B24="Yes",(Summary!B14)*Inputs!B25,0))*Inputs!B26)*Inputs!B21*Inputs!B10/12)+((((A97)*Inputs!B20)+(IF(Inputs!B24="Yes",(Summary!B14)*Inputs!B25,0)))*Inputs!B22)+((((A97)*Inputs!B20)+(IF(Inputs!B24="Yes",(Summary!B14)*Inputs!B25,0)))*Inputs!B23))+(Summary!B17))) -> -326375 | C97: =IF(A97>$B$6,"","")
A98: =$B$5+(87)*$B$7 -> 535000 | B98: =IF(A98>$B$6,"",(Inputs!B6)-((A98)+(IF(Inputs!D13<>"",Inputs!D13,IF(Inputs!B7="England & N. Ireland",(IF(Inputs!B8="First-time buyer",(IF(A98<=500000,MAX(0,A98-300000)*0.05,(MAX(0,MIN(A98,250000)-125000)*0.02+MAX(0,MIN(A98,925000)-250000)*0.05+MAX(0,MIN(A98,1500000)-925000)*0.1+MAX(0,A98-1500000)*0.12))),(MAX(0,MIN(A98,250000)-125000)*0.02+MAX(0,MIN(A98,925000)-250000)*0.05+MAX(0,MIN(A98,1500000)-925000)*0.1+MAX(0,A98-1500000)*0.12)+IF(Inputs!B8="Additional / Investor",0.05*A98,0)+IF(Inputs!B9="Yes",0.02*A98,0))),IF(Inputs!B7="Scotland",((MAX(0,MIN(A98,250000)-145000)*0.02+MAX(0,MIN(A98,325000)-250000)*0.05+MAX(0,MIN(A98,750000)-325000)*0.1+MAX(0,A98-750000)*0.12)-IF(Inputs!B8="First-time buyer",(IF(A98>145000,MIN(600,0.02*(MIN(A98,175000)-145000)),0)),0)+IF(Inputs!B8="Additional / Investor",0.08*A98,0)),IF(Inputs!B7="Wales",(IF(Inputs!B8="Additional / Investor",(MIN(A98,180000)*0.05+MAX(0,MIN(A98,250000)-180000)*0.085+MAX(0,MIN(A98,400000)-250000)*0.1+MAX(0,MIN(A98,750000)-400000)*0.125+MAX(0,MIN(A98,1500000)-750000)*0.15+MAX(0,A98-1500000)*0.17),(MAX(0,MIN(A98,400000)-225000)*0.06+MAX(0,MIN(A98,750000)-400000)*0.075+MAX(0,MIN(A98,1500000)-750000)*0.1+MAX(0,A98-1500000)*0.12))),0)))))+(Inputs!B14+Inputs!B15+Inputs!B16+Inputs!B17)+(Summary!B14)+(Summary!B15)+(((((A98)*Inputs!B20)+(IF(Inputs!B24="Yes",(Summary!B14)*Inputs!B25,0))*Inputs!B26)*Inputs!B21*Inputs!B10/12)+((((A98)*Inputs!B20)+(IF(Inputs!B24="Yes",(Summary!B14)*Inputs!B25,0)))*Inputs!B22)+((((A98)*Inputs!B20)+(IF(Inputs!B24="Yes",(Summary!B14)*Inputs!B25,0)))*Inputs!B23))+(Summary!B17))) -> -332212.5 | C98: =IF(A98>$B$6,"","")
A99: =$B$5+(88)*$B$7 -> 540000 | B99: =IF(A99>$B$6,"",(Inputs!B6)-((A99)+(IF(Inputs!D13<>"",Inputs!D13,IF(Inputs!B7="England & N. Ireland",(IF(Inputs!B8="First-time buyer",(IF(A99<=500000,MAX(0,A99-300000)*0.05,(MAX(0,MIN(A99,250000)-125000)*0.02+MAX(0,MIN(A99,925000)-250000)*0.05+MAX(0,MIN(A99,1500000)-925000)*0.1+MAX(0,A99-1500000)*0.12))),(MAX(0,MIN(A99,250000)-125000)*0.02+MAX(0,MIN(A99,925000)-250000)*0.05+MAX(0,MIN(A99,1500000)-925000)*0.1+MAX(0,A99-1500000)*0.12)+IF(Inputs!B8="Additional / Investor",0.05*A99,0)+IF(Inputs!B9="Yes",0.02*A99,0))),IF(Inputs!B7="Scotland",((MAX(0,MIN(A99,250000)-145000)*0.02+MAX(0,MIN(A99,325000)-250000)*0.05+MAX(0,MIN(A99,750000)-325000)*0.1+MAX(0,A99-750000)*0.12)-IF(Inputs!B8="First-time buyer",(IF(A99>145000,MIN(600,0.02*(MIN(A99,175000)-145000)),0)),0)+IF(Inputs!B8="Additional / Investor",0.08*A99,0)),IF(Inputs!B7="Wales",(IF(Inputs!B8="Additional / Investor",(MIN(A99,180000)*0.05+MAX(0,MIN(A99,250000)-180000)*0.085+MAX(0,MIN(A99,400000)-250000)*0.1+MAX(0,MIN(A99,750000)-400000)*0.125+MAX(0,MIN(A99,1500000)-750000)*0.15+MAX(0,A99-1500000)*0.17),(MAX(0,MIN(A99,400000)-225000)*0.06+MAX(0,MIN(A99,750000)-400000)*0.075+MAX(0,MIN(A99,1500000)-750000)*0.1+MAX(0,A99-1500000)*0.12))),0)))))+(Inputs!B14+Inputs!B15+Inputs!B16+Inputs!B17)+(Summary!B14)+(Summary!B15)+(((((A99)*Inputs!B20)+(IF(Inputs!B24="Yes",(Summary!B14)*Inputs!B25,0))*Inputs!B26)*Inputs!B21*Inputs!B10/12)+((((A99)*Inputs!B20)+(IF(Inputs!B24="Yes",(Summary!B14)*Inputs!B25,0)))*Inputs!B22)+((((A99)*Inputs!B20)+(IF(Inputs!B24="Yes",(Summary!B14)*Inputs!B25,0)))*Inputs!B23))+(Summary!B17))) -> -338050 | C99: =IF(A99>$B$6,"","")
A100: =$B$5+(89)*$B$7 -> 545000 | B100: =IF(A100>$B$6,"",(Inputs!B6)-((A100)+(IF(Inputs!D13<>"",Inputs!D13,IF(Inputs!B7="England & N. Ireland",(IF(Inputs!B8="First-time buyer",(IF(A100<=500000,MAX(0,A100-300000)*0.05,(MAX(0,MIN(A100,250000)-125000)*0.02+MAX(0,MIN(A100,925000)-250000)*0.05+MAX(0,MIN(A100,1500000)-925000)*0.1+MAX(0,A100-1500000)*0.12))),(MAX(0,MIN(A100,250000)-125000)*0.02+MAX(0,MIN(A100,925000)-250000)*0.05+MAX(0,MIN(A100,1500000)-925000)*0.1+MAX(0,A100-1500000)*0.12)+IF(Inputs!B8="Additional / Investor",0.05*A100,0)+IF(Inputs!B9="Yes",0.02*A100,0))),IF(Inputs!B7="Scotland",((MAX(0,MIN(A100,250000)-145000)*0.02+MAX(0,MIN(A100,325000)-250000)*0.05+MAX(0,MIN(A100,750000)-325000)*0.1+MAX(0,A100-750000)*0.12)-IF(Inputs!B8="First-time buyer",(IF(A100>145000,MIN(600,0.02*(MIN(A100,175000)-145000)),0)),0)+IF(Inputs!B8="Additional / Investor",0.08*A100,0)),IF(Inputs!B7="Wales",(IF(Inputs!B8="Additional / Investor",(MIN(A100,180000)*0.05+MAX(0,MIN(A100,250000)-180000)*0.085+MAX(0,MIN(A100,400000)-250000)*0.1+MAX(0,MIN(A100,750000)-400000)*0.125+MAX(0,MIN(A100,1500000)-750000)*0.15+MAX(0,A100-1500000)*0.17),(MAX(0,MIN(A100,400000)-225000)*0.06+MAX(0,MIN(A100,750000)-400000)*0.075+MAX(0,MIN(A100,1500000)-750000)*0.1+MAX(0,A100-1500000)*0.12))),0)))))+(Inputs!B14+Inputs!B15+Inputs!B16+Inputs!B17)+(Summary!B14)+(Summary!B15)+(((((A100)*Inputs!B20)+(IF(Inputs!B24="Yes",(Summary!B14)*Inputs!B25,0))*Inputs!B26)*Inputs!B21*Inputs!B10/12)+((((A100)*Inputs!B20)+(IF(Inputs!B24="Yes",(Summary!B14)*Inputs!B25,0)))*Inputs!B22)+((((A100)*Inputs!B20)+(IF(Inputs!B24="Yes",(Summary!B14)*Inputs!B25,0)))*Inputs!B23))+(Summary!B17))) -> -343887.5 | C100: =IF(A100>$B$6,"","")
A101: =$B$5+(90)*$B$7 -> 550000 | B101: =IF(A101>$B$6,"",(Inputs!B6)-((A101)+(IF(Inputs!D13<>"",Inputs!D13,IF(Inputs!B7="England & N. Ireland",(IF(Inputs!B8="First-time buyer",(IF(A101<=500000,MAX(0,A101-300000)*0.05,(MAX(0,MIN(A101,250000)-125000)*0.02+MAX(0,MIN(A101,925000)-250000)*0.05+MAX(0,MIN(A101,1500000)-925000)*0.1+MAX(0,A101-1500000)*0.12))),(MAX(0,MIN(A101,250000)-125000)*0.02+MAX(0,MIN(A101,925000)-250000)*0.05+MAX(0,MIN(A101,1500000)-925000)*0.1+MAX(0,A101-1500000)*0.12)+IF(Inputs!B8="Additional / Investor",0.05*A101,0)+IF(Inputs!B9="Yes",0.02*A101,0))),IF(Inputs!B7="Scotland",((MAX(0,MIN(A101,250000)-145000)*0.02+MAX(0,MIN(A101,325000)-250000)*0.05+MAX(0,MIN(A101,750000)-325000)*0.1+MAX(0,A101-750000)*0.12)-IF(Inputs!B8="First-time buyer",(IF(A101>145000,MIN(600,0.02*(MIN(A101,175000)-145000)),0)),0)+IF(Inputs!B8="Additional / Investor",0.08*A101,0)),IF(Inputs!B7="Wales",(IF(Inputs!B8="Additional / Investor",(MIN(A101,180000)*0.05+MAX(0,MIN(A101,250000)-180000)*0.085+MAX(0,MIN(A101,400000)-250000)*0.1+MAX(0,MIN(A101,750000)-400000)*0.125+MAX(0,MIN(A101,1500000)-750000)*0.15+MAX(0,A101-1500000)*0.17),(MAX(0,MIN(A101,400000)-225000)*0.06+MAX(0,MIN(A101,750000)-400000)*0.075+MAX(0,MIN(A101,1500000)-750000)*0.1+MAX(0,A101-1500000)*0.12))),0)))))+(Inputs!B14+Inputs!B15+Inputs!B16+Inputs!B17)+(Summary!B14)+(Summary!B15)+(((((A101)*Inputs!B20)+(IF(Inputs!B24="Yes",(Summary!B14)*Inputs!B25,0))*Inputs!B26)*Inputs!B21*Inputs!B10/12)+((((A101)*Inputs!B20)+(IF(Inputs!B24="Yes",(Summary!B14)*Inputs!B25,0)))*Inputs!B22)+((((A101)*Inputs!B20)+(IF(Inputs!B24="Yes",(Summary!B14)*Inputs!B25,0)))*Inputs!B23))+(Summary!B17))) -> -349725 | C101: =IF(A101>$B$6,"","")
A102: =$B$5+(91)*$B$7 -> 555000 | B102: =IF(A102>$B$6,"",(Inputs!B6)-((A102)+(IF(Inputs!D13<>"",Inputs!D13,IF(Inputs!B7="England & N. Ireland",(IF(Inputs!B8="First-time buyer",(IF(A102<=500000,MAX(0,A102-300000)*0.05,(MAX(0,MIN(A102,250000)-125000)*0.02+MAX(0,MIN(A102,925000)-250000)*0.05+MAX(0,MIN(A102,1500000)-925000)*0.1+MAX(0,A102-1500000)*0.12))),(MAX(0,MIN(A102,250000)-125000)*0.02+MAX(0,MIN(A102,925000)-250000)*0.05+MAX(0,MIN(A102,1500000)-925000)*0.1+MAX(0,A102-1500000)*0.12)+IF(Inputs!B8="Additional / Investor",0.05*A102,0)+IF(Inputs!B9="Yes",0.02*A102,0))),IF(Inputs!B7="Scotland",((MAX(0,MIN(A102,250000)-145000)*0.02+MAX(0,MIN(A102,325000)-250000)*0.05+MAX(0,MIN(A102,750000)-325000)*0.1+MAX(0,A102-750000)*0.12)-IF(Inputs!B8="First-time buyer",(IF(A102>145000,MIN(600,0.02*(MIN(A102,175000)-145000)),0)),0)+IF(Inputs!B8="Additional / Investor",0.08*A102,0)),IF(Inputs!B7="Wales",(IF(Inputs!B8="Additional / Investor",(MIN(A102,180000)*0.05+MAX(0,MIN(A102,250000)-180000)*0.085+MAX(0,MIN(A102,400000)-250000)*0.1+MAX(0,MIN(A102,750000)-400000)*0.125+MAX(0,MIN(A102,1500000)-750000)*0.15+MAX(0,A102-1500000)*0.17),(MAX(0,MIN(A102,400000)-225000)*0.06+MAX(0,MIN(A102,750000)-400000)*0.075+MAX(0,MIN(A102,1500000)-750000)*0.1+MAX(0,A102-1500000)*0.12))),0)))))+(Inputs!B14+Inputs!B15+Inputs!B16+Inputs!B17)+(Summary!B14)+(Summary!B15)+(((((A102)*Inputs!B20)+(IF(Inputs!B24="Yes",(Summary!B14)*Inputs!B25,0))*Inputs!B26)*Inputs!B21*Inputs!B10/12)+((((A102)*Inputs!B20)+(IF(Inputs!B24="Yes",(Summary!B14)*Inputs!B25,0)))*Inputs!B22)+((((A102)*Inputs!B20)+(IF(Inputs!B24="Yes",(Summary!B14)*Inputs!B25,0)))*Inputs!B23))+(Summary!B17))) -> -355562.5 | C102: =IF(A102>$B$6,"","")
A103: =$B$5+(92)*$B$7 -> 560000 | B103: =IF(A103>$B$6,"",(Inputs!B6)-((A103)+(IF(Inputs!D13<>"",Inputs!D13,IF(Inputs!B7="England & N. Ireland",(IF(Inputs!B8="First-time buyer",(IF(A103<=500000,MAX(0,A103-300000)*0.05,(MAX(0,MIN(A103,250000)-125000)*0.02+MAX(0,MIN(A103,925000)-250000)*0.05+MAX(0,MIN(A103,1500000)-925000)*0.1+MAX(0,A103-1500000)*0.12))),(MAX(0,MIN(A103,250000)-125000)*0.02+MAX(0,MIN(A103,925000)-250000)*0.05+MAX(0,MIN(A103,1500000)-925000)*0.1+MAX(0,A103-1500000)*0.12)+IF(Inputs!B8="Additional / Investor",0.05*A103,0)+IF(Inputs!B9="Yes",0.02*A103,0))),IF(Inputs!B7="Scotland",((MAX(0,MIN(A103,250000)-145000)*0.02+MAX(0,MIN(A103,325000)-250000)*0.05+MAX(0,MIN(A103,750000)-325000)*0.1+MAX(0,A103-750000)*0.12)-IF(Inputs!B8="First-time buyer",(IF(A103>145000,MIN(600,0.02*(MIN(A103,175000)-145000)),0)),0)+IF(Inputs!B8="Additional / Investor",0.08*A103,0)),IF(Inputs!B7="Wales",(IF(Inputs!B8="Additional / Investor",(MIN(A103,180000)*0.05+MAX(0,MIN(A103,250000)-180000)*0.085+MAX(0,MIN(A103,400000)-250000)*0.1+MAX(0,MIN(A103,750000)-400000)*0.125+MAX(0,MIN(A103,1500000)-750000)*0.15+MAX(0,A103-1500000)*0.17),(MAX(0,MIN(A103,400000)-225000)*0.06+MAX(0,MIN(A103,750000)-400000)*0.075+MAX(0,MIN(A103,1500000)-750000)*0.1+MAX(0,A103-1500000)*0.12))),0)))))+(Inputs!B14+Inputs!B15+Inputs!B16+Inputs!B17)+(Summary!B14)+(Summary!B15)+(((((A103)*Inputs!B20)+(IF(Inputs!B24="Yes",(Summary!B14)*Inputs!B25,0))*Inputs!B26)*Inputs!B21*Inputs!B10/12)+((((A103)*Inputs!B20)+(IF(Inputs!B24="Yes",(Summary!B14)*Inputs!B25,0)))*Inputs!B22)+((((A103)*Inputs!B20)+(IF(Inputs!B24="Yes",(Summary!B14)*Inputs!B25,0)))*Inputs!B23))+(Summary!B17))) -> -361400 | C103: =IF(A103>$B$6,"","")
...

Sheet Sensitivity
A1: Sensitivity (Profit) — Sale Price vs Refurb Cost
A2: Shows how profit changes if sale price or refurb costs move. (All other inputs held constant.)
A4: Base profit | B4: =Summary!B19 -> 525
A6: Refurb Δ \ Sale Δ | B6: -0.1 | C6: -0.05 | D6: 0 | E6: 0.05 | F6: 0.1
A7: -0.2 | B7: =((Inputs!B6)*(1+-0.1))-((Summary!B13)+((Summary!B14)*(1+-0.2))+(Summary!B15)+(((((Inputs!B5)*(Inputs!B20))+(IF(Inputs!B24="Yes",((Summary!B14)*(1+-0.2))*(Inputs!B25),0))*(Inputs!B26))*(Inputs!B21)*(Inputs!B10)/12)+((((Inputs!B5)*(Inputs!B20))+(IF(Inputs!B24="Yes",((Summary!B14)*(1+-0.2))*(Inputs!B25),0)))*(Inputs!B22))+((((Inputs!B5)*(Inputs!B20))+(IF(Inputs!B24="Yes",((Summary!B14)*(1+-0.2))*(Inputs!B25),0)))*(Inputs!B23)))+(((Summary!B17)-(Inputs!B6)*(Inputs!B40))+((Inputs!B6)*(1+-0.1))*(Inputs!B40))) -> -25495 | C7: =((Inputs!B6)*(1+-0.05))-((Summary!B13)+((Summary!B14)*(1+-0.2))+(Summary!B15)+(((((Inputs!B5)*(Inputs!B20))+(IF(Inputs!B24="Yes",((Summary!B14)*(1+-0.2))*(Inputs!B25),0))*(Inputs!B26))*(Inputs!B21)*(Inputs!B10)/12)+((((Inputs!B5)*(Inputs!B20))+(IF(Inputs!B24="Yes",((Summary!B14)*(1+-0.2))*(Inputs!B25),0)))*(Inputs!B22))+((((Inputs!B5)*(Inputs!B20))+(IF(Inputs!B24="Yes",((Summary!B14)*(1+-0.2))*(Inputs!B25),0)))*(Inputs!B23)))+(((Summary!B17)-(Inputs!B6)*(Inputs!B40))+((Inputs!B6)*(1+-0.05))*(Inputs!B40))) -> -9735 | D7: =((Inputs!B6)*(1+0))-((Summary!B13)+((Summary!B14)*(1+-0.2))+(Summary!B15)+(((((Inputs!B5)*(Inputs!B20))+(IF(Inputs!B24="Yes",((Summary!B14)*(1+-0.2))*(Inputs!B25),0))*(Inputs!B26))*(Inputs!B21)*(Inputs!B10)/12)+((((Inputs!B5)*(Inputs!B20))+(IF(Inputs!B24="Yes",((Summary!B14)*(1+-0.2))*(Inputs!B25),0)))*(Inputs!B22))+((((Inputs!B5)*(Inputs!B20))+(IF(Inputs!B24="Yes",((Summary!B14)*(1+-0.2))*(Inputs!B25),0)))*(Inputs!B23)))+(((Summary!B17)-(Inputs!B6)*(Inputs!B40))+((Inputs!B6)*(1+0))*(Inputs!B40))) -> 6025 | E7: =((Inputs!B6)*(1+0.05))-((Summary!B13)+((Summary!B14)*(1+-0.2))+(Summary!B15)+(((((Inputs!B5)*(Inputs!B20))+(IF(Inputs!B24="Yes",((Summary!B14)*(1+-0.2))*(Inputs!B25),0))*(Inputs!B26))*(Inputs!B21)*(Inputs!B10)/12)+((((Inputs!B5)*(Inputs!B20))+(IF(Inputs!B24="Yes",((Summary!B14)*(1+-0.2))*(Inputs!B25),0)))*(Inputs!B22))+((((Inputs!B5)*(Inputs!B20))+(IF(Inputs!B24="Yes",((Summary!B14)*(1+-0.2))*(Inputs!B25),0)))*(Inputs!B23)))+(((Summary!B17)-(Inputs!B6)*(Inputs!B40))+((Inputs!B6)*(1+0.05))*(Inputs!B40))) -> 21785 | F7: =((Inputs!B6)*(1+0.1))-((Summary!B13)+((Summary!B14)*(1+-0.2))+(Summary!B15)+(((((Inputs!B5)*(Inputs!B20))+(IF(Inputs!B24="Yes",((Summary!B14)*(1+-0.2))*(Inputs!B25),0))*(Inputs!B26))*(Inputs!B21)*(Inputs!B10)/12)+((((Inputs!B5)*(Inputs!B20))+(IF(Inputs!B24="Yes",((Summary!B14)*(1+-0.2))*(Inputs!B25),0)))*(Inputs!B22))+((((Inputs!B5)*(Inputs!B20))+(IF(Inputs!B24="Yes",((Summary!B14)*(1+-0.2))*(Inputs!B25),0)))*(Inputs!B23)))+(((Summary!B17)-(Inputs!B6)*(Inputs!B40))+((Inputs!B6)*(1+0.1))*(Inputs!B40))) -> 37545
A8: -0.1 | B8: =((Inputs!B6)*(1+-0.1))-((Summary!B13)+((Summary!B14)*(1+-0.1))+(Summary!B15)+(((((Inputs!B5)*(Inputs!B20))+(IF(Inputs!B24="Yes",((Summary!B14)*(1+-0.1))*(Inputs!B25),0))*(Inputs!B26))*(Inputs!B21)*(Inputs!B10)/12)+((((Inputs!B5)*(Inputs!B20))+(IF(Inputs!B24="Yes",((Summary!B14)*(1+-0.1))*(Inputs!B25),0)))*(Inputs!B22))+((((Inputs!B5)*(Inputs!B20))+(IF(Inputs!B24="Yes",((Summary!B14)*(1+-0.1))*(Inputs!B25),0)))*(Inputs!B23)))+(((Summary!B17)-(Inputs!B6)*(Inputs!B40))+((Inputs!B6)*(1+-0.1))*(Inputs!B40))) -> -28245 | C8: =((Inputs!B6)*(1+-0.05))-((Summary!B13)+((Summary!B14)*(1+-0.1))+(Summary!B15)+(((((Inputs!B5)*(Inputs!B20))+(IF(Inputs!B24="Yes",((Summary!B14)*(1+-0.1))*(Inputs!B25),0))*(Inputs!B26))*(Inputs!B21)*(Inputs!B10)/12)+((((Inputs!B5)*(Inputs!B20))+(IF(Inputs!B24="Yes",((Summary!B14)*(1+-0.1))*(Inputs!B25),0)))*(Inputs!B22))+((((Inputs!B5)*(Inputs!B20))+(IF(Inputs!B24="Yes",((Summary!B14)*(1+-0.1))*(Inputs!B25),0)))*(Inputs!B23)))+(((Summary!B17)-(Inputs!B6)*(Inputs!B40))+((Inputs!B6)*(1+-0.05))*(Inputs!B40))) -> -12485 | D8: =((Inputs!B6)*(1+0))-((Summary!B13)+((Summary!B14)*(1+-0.1))+(Summary!B15)+(((((Inputs!B5)*(Inputs!B20))+(IF(Inputs!B24="Yes",((Summary!B14)*(1+-0.1))*(Inputs!B25),0))*(Inputs!B26))*(Inputs!B21)*(Inputs!B10)/12)+((((Inputs!B5)*(Inputs!B20))+(IF(Inputs!B24="Yes",((Summary!B14)*(1+-0.1))*(Inputs!B25),0)))*(Inputs!B22))+((((Inputs!B5)*(Inputs!B20))+(IF(Inputs!B24="Yes",((Summary!B14)*(1+-0.1))*(Inputs!B25),0)))*(Inputs!B23)))+(((Summary!B17)-(Inputs!B6)*(Inputs!B40))+((Inputs!B6)*(1+0))*(Inputs!B40))) -> 3275 | E8: =((Inputs!B6)*(1+0.05))-((Summary!B13)+((Summary!B14)*(1+-0.1))+(Summary!B15)+(((((Inputs!B5)*(Inputs!B20))+(IF(Inputs!B24="Yes",((Summary!B14)*(1+-0.1))*(Inputs!B25),0))*(Inputs!B26))*(Inputs!B21)*(Inputs!B10)/12)+((((Inputs!B5)*(Inputs!B20))+(IF(Inputs!B24="Yes",((Summary!B14)*(1+-0.1))*(Inputs!B25),0)))*(Inputs!B22))+((((Inputs!B5)*(Inputs!B20))+(IF(Inputs!B24="Yes",((Summary!B14)*(1+-0.1))*(Inputs!B25),0)))*(Inputs!B23)))+(((Summary!B17)-(Inputs!B6)*(Inputs!B40))+((Inputs!B6)*(1+0.05))*(Inputs!B40))) -> 19035 | F8: =((Inputs!B6)*(1+0.1))-((Summary!B13)+((Summary!B14)*(1+-0.1))+(Summary!B15)+(((((Inputs!B5)*(Inputs!B20))+(IF(Inputs!B24="Yes",((Summary!B14)*(1+-0.1))*(Inputs!B25),0))*(Inputs!B26))*(Inputs!B21)*(Inputs!B10)/12)+((((Inputs!B5)*(Inputs!B20))+(IF(Inputs!B24="Yes",((Summary!B14)*(1+-0.1))*(Inputs!B25),0)))*(Inputs!B22))+((((Inputs!B5)*(Inputs!B20))+(IF(Inputs!B24="Yes",((Summary!B14)*(1+-0.1))*(Inputs!B25),0)))*(Inputs!B23)))+(((Summary!B17)-(Inputs!B6)*(Inputs!B40))+((Inputs!B6)*(1+0.1))*(Inputs!B40))) -> 34795
A9: 0 | B9: =((Inputs!B6)*(1+-0.1))-((Summary!B13)+((Summary!B14)*(1+0))+(Summary!B15)+(((((Inputs!B5)*(Inputs!B20))+(IF(Inputs!B24="Yes",((Summary!B14)*(1+0))*(Inputs!B25),0))*(Inputs!B26))*(Inputs!B21)*(Inputs!B10)/12)+((((Inputs!B5)*(Inputs!B20))+(IF(Inputs!B24="Yes",((Summary!B14)*(1+0))*(Inputs!B25),0)))*(Inputs!B22))+((((Inputs!B5)*(Inputs!B20))+(IF(Inputs!B24="Yes",((Summary!B14)*(1+0))*(Inputs!B25),0)))*(Inputs!B23)))+(((Summary!B17)-(Inputs!B6)*(Inputs!B40))+((Inputs!B6)*(1+-0.1))*(Inputs!B40))) -> -30995 | C9: =((Inputs!B6)*(1+-0.05))-((Summary!B13)+((Summary!B14)*(1+0))+(Summary!B15)+(((((Inputs!B5)*(Inputs!B20))+(IF(Inputs!B24="Yes",((Summary!B14)*(1+0))*(Inputs!B25),0))*(Inputs!B26))*(Inputs!B21)*(Inputs!B10)/12)+((((Inputs!B5)*(Inputs!B20))+(IF(Inputs!B24="Yes",((Summary!B14)*(1+0))*(Inputs!B25),0)))*(Inputs!B22))+((((Inputs!B5)*(Inputs!B20))+(IF(Inputs!B24="Yes",((Summary!B14)*(1+0))*(Inputs!B25),0)))*(Inputs!B23)))+(((Summary!B17)-(Inputs!B6)*(Inputs!B40))+((Inputs!B6)*(1+-0.05))*(Inputs!B40))) -> -15235 | D9: =((Inputs!B6)*(1+0))-((Summary!B13)+((Summary!B14)*(1+0))+(Summary!B15)+(((((Inputs!B5)*(Inputs!B20))+(IF(Inputs!B24="Yes",((Summary!B14)*(1+0))*(Inputs!B25),0))*(Inputs!B26))*(Inputs!B21)*(Inputs!B10)/12)+((((Inputs!B5)*(Inputs!B20))+(IF(Inputs!B24="Yes",((Summary!B14)*(1+0))*(Inputs!B25),0)))*(Inputs!B22))+((((Inputs!B5)*(Inputs!B20))+(IF(Inputs!B24="Yes",((Summary!B14)*(1+0))*(Inputs!B25),0)))*(Inputs!B23)))+(((Summary!B17)-(Inputs!B6)*(Inputs!B40))+((Inputs!B6)*(1+0))*(Inputs!B40))) -> 525 | E9: =((Inputs!B6)*(1+0.05))-((Summary!B13)+((Summary!B14)*(1+0))+(Summary!B15)+(((((Inputs!B5)*(Inputs!B20))+(IF(Inputs!B24="Yes",((Summary!B14)*(1+0))*(Inputs!B25),0))*(Inputs!B26))*(Inputs!B21)*(Inputs!B10)/12)+((((Inputs!B5)*(Inputs!B20))+(IF(Inputs!B24="Yes",((Summary!B14)*(1+0))*(Inputs!B25),0)))*(Inputs!B22))+((((Inputs!B5)*(Inputs!B20))+(IF(Inputs!B24="Yes",((Summary!B14)*(1+0))*(Inputs!B25),0)))*(Inputs!B23)))+(((Summary!B17)-(Inputs!B6)*(Inputs!B40))+((Inputs!B6)*(1+0.05))*(Inputs!B40))) -> 16285 | F9: =((Inputs!B6)*(1+0.1))-((Summary!B13)+((Summary!B14)*(1+0))+(Summary!B15)+(((((Inputs!B5)*(Inputs!B20))+(IF(Inputs!B24="Yes",((Summary!B14)*(1+0))*(Inputs!B25),0))*(Inputs!B26))*(Inputs!B21)*(Inputs!B10)/12)+((((Inputs!B5)*(Inputs!B20))+(IF(Inputs!B24="Yes",((Summary!B14)*(1+0))*(Inputs!B25),0)))*(Inputs!B22))+((((Inputs!B5)*(Inputs!B20))+(IF(Inputs!B24="Yes",((Summary!B14)*(1+0))*(Inputs!B25),0)))*(Inputs!B23)))+(((Summary!B17)-(Inputs!B6)*(Inputs!B40))+((Inputs!B6)*(1+0.1))*(Inputs!B40))) -> 32045
A10: 0.1 | B10: =((Inputs!B6)*(1+-0.1))-((Summary!B13)+((Summary!B14)*(1+0.1))+(Summary!B15)+(((((Inputs!B5)*(Inputs!B20))+(IF(Inputs!B24="Yes",((Summary!B14)*(1+0.1))*(Inputs!B25),0))*(Inputs!B26))*(Inputs!B21)*(Inputs!B10)/12)+((((Inputs!B5)*(Inputs!B20))+(IF(Inputs!B24="Yes",((Summary!B14)*(1+0.1))*(Inputs!B25),0)))*(Inputs!B22))+((((Inputs!B5)*(Inputs!B20))+(IF(Inputs!B24="Yes",((Summary!B14)*(1+0.1))*(Inputs!B25),0)))*(Inputs!B23)))+(((Summary!B17)-(Inputs!B6)*(Inputs!B40))+((Inputs!B6)*(1+-0.1))*(Inputs!B40))) -> -33745 | C10: =((Inputs!B6)*(1+-0.05))-((Summary!B13)+((Summary!B14)*(1+0.1))+(Summary!B15)+(((((Inputs!B5)*(Inputs!B20))+(IF(Inputs!B24="Yes",((Summary!B14)*(1+0.1))*(Inputs!B25),0))*(Inputs!B26))*(Inputs!B21)*(Inputs!B10)/12)+((((Inputs!B5)*(Inputs!B20))+(IF(Inputs!B24="Yes",((Summary!B14)*(1+0.1))*(Inputs!B25),0)))*(Inputs!B22))+((((Inputs!B5)*(Inputs!B20))+(IF(Inputs!B24="Yes",((Summary!B14)*(1+0.1))*(Inputs!B25),0)))*(Inputs!B23)))+(((Summary!B17)-(Inputs!B6)*(Inputs!B40))+((Inputs!B6)*(1+-0.05))*(Inputs!B40))) -> -17985 | D10: =((Inputs!B6)*(1+0))-((Summary!B13)+((Summary!B14)*(1+0.1))+(Summary!B15)+(((((Inputs!B5)*(Inputs!B20))+(IF(Inputs!B24="Yes",((Summary!B14)*(1+0.1))*(Inputs!B25),0))*(Inputs!B26))*(Inputs!B21)*(Inputs!B10)/12)+((((Inputs!B5)*(Inputs!B20))+(IF(Inputs!B24="Yes",((Summary!B14)*(1+0.1))*(Inputs!B25),0)))*(Inputs!B22))+((((Inputs!B5)*(Inputs!B20))+(IF(Inputs!B24="Yes",((Summary!B14)*(1+0.1))*(Inputs!B25),0)))*(Inputs!B23)))+(((Summary!B17)-(Inputs!B6)*(Inputs!B40))+((Inputs!B6)*(1+0))*(Inputs!B40))) -> -2225 | E10: =((Inputs!B6)*(1+0.05))-((Summary!B13)+((Summary!B14)*(1+0.1))+(Summary!B15)+(((((Inputs!B5)*(Inputs!B20))+(IF(Inputs!B24="Yes",((Summary!B14)*(1+0.1))*(Inputs!B25),0))*(Inputs!B26))*(Inputs!B21)*(Inputs!B10)/12)+((((Inputs!B5)*(Inputs!B20))+(IF(Inputs!B24="Yes",((Summary!B14)*(1+0.1))*(Inputs!B25),0)))*(Inputs!B22))+((((Inputs!B5)*(Inputs!B20))+(IF(Inputs!B24="Yes",((Summary!B14)*(1+0.1))*(Inputs!B25),0)))*(Inputs!B23)))+(((Summary!B17)-(Inputs!B6)*(Inputs!B40))+((Inputs!B6)*(1+0.05))*(Inputs!B40))) -> 13535 | F10: =((Inputs!B6)*(1+0.1))-((Summary!B13)+((Summary!B14)*(1+0.1))+(Summary!B15)+(((((Inputs!B5)*(Inputs!B20))+(IF(Inputs!B24="Yes",((Summary!B14)*(1+0.1))*(Inputs!B25),0))*(Inputs!B26))*(Inputs!B21)*(Inputs!B10)/12)+((((Inputs!B5)*(Inputs!B20))+(IF(Inputs!B24="Yes",((Summary!B14)*(1+0.1))*(Inputs!B25),0)))*(Inputs!B22))+((((Inputs!B5)*(Inputs!B20))+(IF(Inputs!B24="Yes",((Summary!B14)*(1+0.1))*(Inputs!B25),0)))*(Inputs!B23)))+(((Summary!B17)-(Inputs!B6)*(Inputs!B40))+((Inputs!B6)*(1+0.1))*(Inputs!B40))) -> 29295
A11: 0.2 | B11: =((Inputs!B6)*(1+-0.1))-((Summary!B13)+((Summary!B14)*(1+0.2))+(Summary!B15)+(((((Inputs!B5)*(Inputs!B20))+(IF(Inputs!B24="Yes",((Summary!B14)*(1+0.2))*(Inputs!B25),0))*(Inputs!B26))*(Inputs!B21)*(Inputs!B10)/12)+((((Inputs!B5)*(Inputs!B20))+(IF(Inputs!B24="Yes",((Summary!B14)*(1+0.2))*(Inputs!B25),0)))*(Inputs!B22))+((((Inputs!B5)*(Inputs!B20))+(IF(Inputs!B24="Yes",((Summary!B14)*(1+0.2))*(Inputs!B25),0)))*(Inputs!B23)))+(((Summary!B17)-(Inputs!B6)*(Inputs!B40))+((Inputs!B6)*(1+-0.1))*(Inputs!B40))) -> -36495 | C11: =((Inputs!B6)*(1+-0.05))-((Summary!B13)+((Summary!B14)*(1+0.2))+(Summary!B15)+(((((Inputs!B5)*(Inputs!B20))+(IF(Inputs!B24="Yes",((Summary!B14)*(1+0.2))*(Inputs!B25),0))*(Inputs!B26))*(Inputs!B21)*(Inputs!B10)/12)+((((Inputs!B5)*(Inputs!B20))+(IF(Inputs!B24="Yes",((Summary!B14)*(1+0.2))*(Inputs!B25),0)))*(Inputs!B22))+((((Inputs!B5)*(Inputs!B20))+(IF(Inputs!B24="Yes",((Summary!B14)*(1+0.2))*(Inputs!B25),0)))*(Inputs!B23)))+(((Summary!B17)-(Inputs!B6)*(Inputs!B40))+((Inputs!B6)*(1+-0.05))*(Inputs!B40))) -> -20735 | D11: =((Inputs!B6)*(1+0))-((Summary!B13)+((Summary!B14)*(1+0.2))+(Summary!B15)+(((((Inputs!B5)*(Inputs!B20))+(IF(Inputs!B24="Yes",((Summary!B14)*(1+0.2))*(Inputs!B25),0))*(Inputs!B26))*(Inputs!B21)*(Inputs!B10)/12)+((((Inputs!B5)*(Inputs!B20))+(IF(Inputs!B24="Yes",((Summary!B14)*(1+0.2))*(Inputs!B25),0)))*(Inputs!B22))+((((Inputs!B5)*(Inputs!B20))+(IF(Inputs!B24="Yes",((Summary!B14)*(1+0.2))*(Inputs!B25),0)))*(Inputs!B23)))+(((Summary!B17)-(Inputs!B6)*(Inputs!B40))+((Inputs!B6)*(1+0))*(Inputs!B40))) -> -4975 | E11: =((Inputs!B6)*(1+0.05))-((Summary!B13)+((Summary!B14)*(1+0.2))+(Summary!B15)+(((((Inputs!B5)*(Inputs!B20))+(IF(Inputs!B24="Yes",((Summary!B14)*(1+0.2))*(Inputs!B25),0))*(Inputs!B26))*(Inputs!B21)*(Inputs!B10)/12)+((((Inputs!B5)*(Inputs!B20))+(IF(Inputs!B24="Yes",((Summary!B14)*(1+0.2))*(Inputs!B25),0)))*(Inputs!B22))+((((Inputs!B5)*(Inputs!B20))+(IF(Inputs!B24="Yes",((Summary!B14)*(1+0.2))*(Inputs!B25),0)))*(Inputs!B23)))+(((Summary!B17)-(Inputs!B6)*(Inputs!B40))+((Inputs!B6)*(1+0.05))*(Inputs!B40))) -> 10785 | F11: =((Inputs!B6)*(1+0.1))-((Summary!B13)+((Summary!B14)*(1+0.2))+(Summary!B15)+(((((Inputs!B5)*(Inputs!B20))+(IF(Inputs!B24="Yes",((Summary!B14)*(1+0.2))*(Inputs!B25),0))*(Inputs!B26))*(Inputs!B21)*(Inputs!B10)/12)+((((Inputs!B5)*(Inputs!B20))+(IF(Inputs!B24="Yes",((Summary!B14)*(1+0.2))*(Inputs!B25),0)))*(Inputs!B22))+((((Inputs!B5)*(Inputs!B20))+(IF(Inputs!B24="Yes",((Summary!B14)*(1+0.2))*(Inputs!B25),0)))*(Inputs!B23)))+(((Summary!B17)-(Inputs!B6)*(Inputs!B40))+((Inputs!B6)*(1+0.1))*(Inputs!B40))) -> 26545
