Workbook

Sheet Summary 
K2: Property Details:
K3: Jointly Let? | L3: no | O3: Yes
K4: Furnished? | L4: yes | O4: No
A6: Tax year:
K7: Based on Split of: | M7: Each
E8: 5th April 20XX | I8: 5th April 20XX
E9: £ | G9: £ | I9: £ | L9: Allocation per person
B10: Income | K10: =B10 -> Income
B12: =Income!A5 -> Rental income | G12: =Income!B22 -> 3390 | K12: =B12 -> Rental income | M12: =G12*$L$7 -> 0
B15: Expenses | K15: =B15 -> Expenses
B17: =Expenses!B5 -> Water rates | E17: =Expenses!B18 -> 0 | K17: =B17 -> Water rates | L17: =E17*$L$7 -> 0
B18: =Expenses!C5 -> Council tax rates | E18: =Expenses!C18 -> 0 | K18: =B18 -> Council tax rates | L18: =E18*$L$7 -> 0
B19: =Expenses!D5 -> Gas saftey | E19: =Expenses!D18 -> 70 | K19: =B19 -> Gas saftey | L19: =E19*$L$7 -> 0
B20: =Expenses!E5 -> Electricity | E20: =Expenses!E18 -> 0 | K20: =B20 -> Electricity | L20: =E20*$L$7 -> 0
B21: =Expenses!F5 -> Repairs & renewals | E21: =Expenses!F18 -> 1246.84 | K21: =B21 -> Repairs & renewals | L21: =E21*$L$7 -> 0
B22: =Expenses!G5 -> Cleaning | E22: =Expenses!G18 -> 200 | K22: =B22 -> Cleaning | L22: =E22*$L$7 -> 0
B23: =Expenses!H5 -> SOLICITOR COST Mortgage DEALINGS | E23: =Expenses!H18 -> 393.36 | K23: =B23 -> SOLICITOR COST Mortgage DEALINGS | L23: =E23*$L$7 -> 0
B24: =Expenses!I5 -> Letting fees | E24: =Expenses!I18 -> 0 | K24: =B24 -> Letting fees | L24: =E24*$L$7 -> 0
B25: =Expenses!J5 -> Management fee | E25: =Expenses!J18 -> 880.07 | K25: =B25 -> Management fee | L25: =E25*$L$7 -> 0
B26: =Expenses!K5 -> Insurance | E26: =Expenses!K18 -> 176.23 | K26: =B26 -> Insurance | L26: =E26*$L$7 -> 0
B27: =Expenses!L5 -> Post & stationery | E27: =Expenses!L18 -> 100 | K27: =B27 -> Post & stationery | L27: =E27*$L$7 -> 0
B28: =Expenses!M5 -> Advertising | E28: =Expenses!M18 -> 0 | K28: =B28 -> Advertising | L28: =E28*$L$7 -> 0
B29: =Expenses!N5 -> Mortgage interest | E29: =Expenses!N18 -> 3129.84 | K29: =B29 -> Mortgage interest | L29: =E29*$L$7 -> 0
B30: =Expenses!O5 -> Accountancy costs | E30: =Expenses!O18 -> 0 | K30: =B30 -> Accountancy costs | L30: =E30*$L$7 -> 0
B31: =IF(L4=O3,"Wear & Tear Allowance","") -> Wear & Tear Allowance | E31: =IF(L4=O3,IF((G12-E17-E18)*10%>0,(G12-E17-E18)*10%,0),"") -> 339 | K31: =B31 -> Wear & Tear Allowance | L31: =IF(L4=O3,E31*$L$7,"") -> 0
E35: =SUM(E17:E30) -> 6196.34 | I35: =SUM(I17:I30) -> 0 | L35: =E35*$L$7 -> 0
B38: Profit | G38: =G12-E35 -> -2806.34 | I38: =I12-I35 -> 0 | L38: =G38*L7 -> 0
C48: COPYRIGHT © PREMIER PROPERTY EDUCATION LIMITED. ALL RIGHTS RESERVED. | E48: JPV BOOTCAMP

Sheet Income
A1: Income
A2: ='Summary '!$A$3 -> 0
A5: Rental income | E5: Bank interest | J5: Deposits received/refunded
E6: Bank:
E7: Account number:
B8: £ | F8: £ - Gross | G8: £- Tax | H8: £ - Net | K8: £
A9: April | E9: April | J9: April
A10: May | E10: May | J10: May
A11: June | E11: June | J11: June
A12: July | E12: July | J12: July
A13: August | E13: August | J13: August
A14: September | E14: September | J14: September
A15: October | B15: 565 | E15: October | J15: October
A16: November | B16: 565 | E16: November | J16: November
A17: December | B17: 565 | E17: December | J17: December
A18: January | B18: 565 | E18: January | J18: January
A19: February | B19: 565 | E19: February | J19: February
A20: March | B20: 565 | E20: March | J20: March
A22: Total | B22: =SUM(B9:B21) -> 3390 | E22: Total | F22: =SUM(F9:F20) -> 0 | G22: =SUM(G9:G20) -> 0 | H22: =SUM(H9:H20) -> 0 | J22: Total | K22: =SUM(K9:K20) -> 0
H24: DO NOT POST BANK INT OR DEPOSITS ONTO RENTALS ON IRIS

Sheet Expenses
A1: Expenses
A2: ='Summary '!$A$3 -> 0
B5: Water rates | C5: Council tax rates | D5: Gas saftey | E5: Electricity | F5: Repairs & renewals | G5: Cleaning | H5: SOLICITOR COST Mortgage DEALINGS | I5: Letting fees | J5: Management fee | K5: Insurance | L5: Post & stationery | M5: Advertising | N5: Mortgage interest | O5: Accountancy costs | P5: LIFE INSURANCE | Q5: Re-Mortgage Fees | R5: Subscription | S5: Capital expenses £ | T5: Date of capital expense | U5: Details
A6: April | D6: 70 | F6: 1246.84 | G6: 200 | H6: 273.36 | L6: 100 | N6: 260.82 | P6: 12.29 | S6: 820.08
A7: May | N7: 260.82 | P7: 12.29 | Q7: 1726
A8: June | H8: 120 | N8: 260.82 | P8: 12.29
A9: July | N9: 260.82 | P9: 12.29
A10: August | K10: 176.23 | N10: 260.82 | P10: 12.29
A11: September | J11: 469.02 | N11: 260.82 | P11: 12.29
A12: October | J12: 151.99 | N12: 260.82 | P12: 12.29
A13: November | J13: 76 | N13: 260.82 | P13: 12.29
A14: December | N14: 260.82 | P14: 12.29
A15: January | J15: 61.02 | N15: 260.82 | P15: 12.29
A16: February | J16: 61.02 | N16: 260.82 | P16: 12.29
A17: March | J17: 61.02 | N17: 260.82 | P17: 12.29
B18: =SUM(B6:B17) -> 0 | C18: =SUM(C6:C17) -> 0 | D18: =SUM(D6:D17) -> 70 | E18: =SUM(E6:E17) -> 0 | F18: =SUM(F6:F17) -> 1246.84 | G18: =SUM(G6:G17) -> 200 | H18: =SUM(H6:H17) -> 393.36 | I18: =SUM(I6:I17) -> 0 | ... S18: =SUM(S6:S17) -> 820.08
J21: Total expenses | L21: =SUM(B18:O18) -> 6196.34
B25: Deposits returned to tenants
C27: £
B28: April
B29: May
B30: June
B31: July
B32: August
B33: September
B34: October
B35: November
B36: December
B37: January
B38: February
B39: March
B41: Total | C41: =SUM(C28:C39) -> 0
B43: DO NOT POST INTO RENTALS ON IRIS
